Workbook
Name _DCFData: _DCFBegin:_DCFSaleYear
Name _DCFData: _DCFBegin:_DCFSaleYear
Name _DCFData: _DCFBegin:_DCFSaleYear
Name _DCFData: _DCFBegin:_DCFSaleYear
Name _DCFData: _DCFBegin:_DCFSaleYear
Name _DCFData: _DCFBegin:_DCFSaleYear
Name _DCFMonths: _DCFFirstMonth:_DCFLastMonth
Name _DCFMonths: _DCFFirstMonth:_DCFLastMonth
Name _DCFMonths: _DCFFirstMonth:_DCFLastMonth
Name _DCFMonths: _DCFFirstMonth:_DCFLastMonth
Name _DCFMonths: _DCFFirstMonth:_DCFLastMonth
Name _DCFMonths: _DCFFirstMonth:_DCFLastMonth
Name _Level_Values: [2]Enumerations!$7:$7
Name _WF_Period_lookup: '1-Yr Waterfall'!$B$358:$E$360
Name _WF_Period_lookup: '3-Yr Waterfall'!$B$358:$E$360
Name _WF_Period_lookup: '4-Yr Waterfall'!$B$358:$E$360
Name _WF_Periodicity: '1-Yr Waterfall'!$R$9
Name _WF_Periodicity: '3-Yr Waterfall'!$R$9
Name _WF_Periodicity: '4-Yr Waterfall'!$R$9
Name _WF_Remainder_GP: '1-Yr Waterfall'!$J$15
Name _WF_Remainder_GP: '3-Yr Waterfall'!$J$15
Name _WF_Remainder_GP: '4-Yr Waterfall'!$J$15
Name _WF_Remainder_LP: '1-Yr Waterfall'!$J$13
Name _WF_Remainder_LP: '3-Yr Waterfall'!$J$13
Name _WF_Remainder_LP: '4-Yr Waterfall'!$J$13
Name _WF_Tier1_GP: '1-Yr Waterfall'!$E$15
Name _WF_Tier1_GP: '3-Yr Waterfall'!$E$15
Name _WF_Tier1_GP: '4-Yr Waterfall'!$E$15
Name _WF_Tier1_LP: '1-Yr Waterfall'!$E$13
Name _WF_Tier1_LP: '3-Yr Waterfall'!$E$13
Name _WF_Tier1_LP: '4-Yr Waterfall'!$E$13
Name _WF_Tier1_Rate: '1-Yr Waterfall'!$D$10
Name _WF_Tier1_Rate: '3-Yr Waterfall'!$D$10
Name _WF_Tier1_Rate: '4-Yr Waterfall'!$D$10
Name _WF_Tier2_GP: '1-Yr Waterfall'!$G$15
Name _WF_Tier2_GP: '3-Yr Waterfall'!$G$15
Name _WF_Tier2_GP: '4-Yr Waterfall'!$G$15
Name _WF_Tier2_LP: '1-Yr Waterfall'!$G$13
Name _WF_Tier2_LP: '3-Yr Waterfall'!$G$13
Name _WF_Tier2_LP: '4-Yr Waterfall'!$G$13
Name _WF_Tier2_Rate: '1-Yr Waterfall'!$F$10
Name _WF_Tier2_Rate: '3-Yr Waterfall'!$F$10
Name _WF_Tier2_Rate: '4-Yr Waterfall'!$F$10
Name _WF_Tier3_GP: '1-Yr Waterfall'!$I$15
Name _WF_Tier3_GP: '3-Yr Waterfall'!$I$15
Name _WF_Tier3_GP: '4-Yr Waterfall'!$I$15
Name _WF_Tier3_LP: '1-Yr Waterfall'!$I$13
Name _WF_Tier3_LP: '3-Yr Waterfall'!$I$13
Name _WF_Tier3_LP: '4-Yr Waterfall'!$I$13
Name _WF_Tier3_Rate: '1-Yr Waterfall'!$H$10
Name _WF_Tier3_Rate: '3-Yr Waterfall'!$H$10
Name _WF_Tier3_Rate: '4-Yr Waterfall'!$H$10
Name A12..F975_: '[3]PH(1)'!#REF!
Name aaa: #REF!
Name aaaa: #REF!
Name aaaaa: #REF!
Name aaaaaaaaaaaa: [4]COMPEST!#REF!
Name Acres: 'Executive Summary'!$E$9
Name AE: #REF!
Name Amortization_Period___Years: "Loan1AmortYrs"

Sheet Executive Summary
B1: =$E$5& " EXECUTIVE SUMMARY" -> VERVE Chapel Hill EXECUTIVE SUMMARY
B4: PROJECT SUMMARY | G4: RETURN METRICS
B5: Project Name | E5: VERVE Chapel Hill | G5: Total Project Budget | K5: Stab. Year | L5: =C48 -> 2.3895397e+08
B6: Address | E6: 600 Martin Luther King Blvd, Chapel Hill, NC 27516 | G6: ="Yr. "&K6&" Return on Cost" -> Yr. 2 Return on Cost | K6: 2 | L6: =OFFSET('Cash Flow'!$F$46,0,K6-1) -> 0.083265659
B7: Land Acquisition | E7: 46753 | G7: Development Spread | L7: =((L6*100)-(J15*100))*100 -> 317.65659
B8: Investment Committee Approval Date | E8: 46082
B9: Land Size (Acres) | E9: =+Development!H19 -> 7.7800046
B10: Number of Stories | E10: 7 Stories | G10: Sale Method | L10: Cap Sale Yr+1
B11: Type of Build | E11: Podium | G11: Cost of Sale | L11: 0.0075
B12: Units | E12: =+Assumptions!D6 -> 461.33501
B13: Beds | E13: =+Assumptions!M22 -> 1241.4577 | G13: ="Holding Period after Delivery ("&TEXT($C$72,"M/d/YY")&")" -> Holding Period after Delivery (8/1/30) | J13: 1 | K13: 3 | L13: 4
B14: Beds/Unit | E14: =Beds/Units -> 2.6910112 | G14: Sale Date | J14: =+'1-Yr Waterfall'!R12 -> 48060 | K14: =+'3-Yr Waterfall'!R12 -> 48791 | L14: =+'4-Yr Waterfall'!R12 -> 49156
B15: Total Parking Spaces | E15: =+ResiParkingSpaces+Assumptions!D39 -> 624 | G15: Exit Cap Rate | J15: 0.0515 | K15: 0.0535 | L15: 0.0545
B16: Residential Parking Spaces | E16: =+Assumptions!D21 -> 624 | G16: Levered IRR | J16: ='Returns Exhibit'!F9 -> 0.36822192 | K16: ='Returns Exhibit'!F21 -> 0.29012798 | L16: ='Returns Exhibit'!F33 -> 0.26983899
B17: % Units Parked | E17: =E16/Units -> 1.3525962 | G17: Levered Multiple | J17: ='Returns Exhibit'!G9 -> 2.7806285 | K17: ='Returns Exhibit'!G21 -> 3.0807703 | L17: ='Returns Exhibit'!G33 -> 3.2530537
B18: % Beds Parked | E18: =E16/Beds -> 0.50263492
B19: Net Residential SF | E19: =+Assumptions!U22 -> 428715
B20: Gross Residential SF | E20: =+Development!H11 -> 502832
B21: Commercial SF | E21: =+Assumptions!I45 -> 1824
B22: Amenity & Leasing SF | E22: =+Development!H12 -> 20325
B23: Total SF (excluding Parking) | E23: =SUM(D20:E22) -> 524981
B24: Parking SF | E24: =+Development!H14 -> 232842
B26: PROJECT BUDGET | G26: UNIT RENT ASSUMPTIONS | O26: Units
K27: Rent/ | L27: Rent/
B28: Uses | C28: Total | D28: $/Bed | E28: $/Unit | G28: Unit Type | H28: # of Beds | I28: % of Beds | J28: SF/Unit | K28: Bed/Month | L28: RSF/Month | O28: =IFERROR(IF(OFFSET(O28,-1,0)+1>$O$35,"",OFFSET(O28,-1,0)+1),"") -> 1
B29: Acquisition Costs | C29: =+'Development Summary'!I14 -> 26063675 | D29: =IFERROR($C29/Beds,0) -> 20994.412 | E29: =IFERROR($C29/Units,0) -> 56496.2 | G29: =IFERROR(OFFSET(Assumptions!$H$24,$O28,0),"") -> STUDIO | H29: =IFERROR(OFFSET(Assumptions!$M$24,$O28,0),"") -> 28.509467 | I29: =+IFERROR(H29/$H$36,"") -> 0.022964509 | J29: =IFERROR(OFFSET(Assumptions!$I$24,$O28,0),"") -> 414 | K29: =IFERROR(OFFSET(Assumptions!$R$24,$O28,0),"") -> 1726.8663 | L29: =IFERROR(OFFSET(Assumptions!$T$24,$O28,0),"") -> 4.1711746 | O29: =IFERROR(IF(OFFSET(O29,-1,0)+1>$O$35,"",OFFSET(O29,-1,0)+1),"") -> 2
B30: Hard Costs | C30: =+'Development Summary'!I20 -> 1.6970318e+08 | D30: =IFERROR($C30/Beds,0) -> 136696.71 | E30: =IFERROR($C30/Units,0) -> 367852.37 | G30: =IFERROR(OFFSET(Assumptions!$H$24,$O29,0),"") -> 1BR/1BA | H30: =IFERROR(OFFSET(Assumptions!$M$24,$O29,0),"") -> 69.977783 | I30: =+IFERROR(H30/$H$36,"") -> 0.056367432 | J30: =IFERROR(OFFSET(Assumptions!$I$24,$O29,0),"") -> 500 | K30: =IFERROR(OFFSET(Assumptions!$R$24,$O29,0),"") -> 2100.1339 | L30: =IFERROR(OFFSET(Assumptions!$T$24,$O29,0),"") -> 4.2002678 | O30: =IFERROR(IF(OFFSET(O30,-1,0)+1>$O$35,"",OFFSET(O30,-1,0)+1),"") -> 3
B31: Architectural / Engineering / Design | C31: =+'Development Summary'!I22 -> 4551801.1 | D31: =IFERROR($C31/Beds,0) -> 3666.4971 | E31: =IFERROR($C31/Units,0) -> 9866.5849 | G31: =IFERROR(OFFSET(Assumptions!$H$24,$O30,0),"") -> 2BR/2BA | H31: =IFERROR(OFFSET(Assumptions!$M$24,$O30,0),"") -> 233.25928 | I31: =+IFERROR(H31/$H$36,"") -> 0.18789144 | J31: =IFERROR(OFFSET(Assumptions!$I$24,$O30,0),"") -> 750 | K31: =IFERROR(OFFSET(Assumptions!$R$24,$O30,0),"") -> 1722.8211 | L31: =IFERROR(OFFSET(Assumptions!$T$24,$O30,0),"") -> 4.5941895 | O31: =IFERROR(IF(OFFSET(O31,-1,0)+1>$O$35,"",OFFSET(O31,-1,0)+1),"") -> 4
B32: Diligence Consultants | C32: =+'Development Summary'!I23 -> 538617.69 | D32: =IFERROR($C32/Beds,0) -> 433.85907 | E32: =IFERROR($C32/Units,0) -> 1167.5196 | G32: =IFERROR(OFFSET(Assumptions!$H$24,$O31,0),"") -> 3BR/3BA | H32: =IFERROR(OFFSET(Assumptions!$M$24,$O31,0),"") -> 225.48397 | I32: =+IFERROR(H32/$H$36,"") -> 0.18162839 | J32: =IFERROR(OFFSET(Assumptions!$I$24,$O31,0),"") -> 1050 | K32: =IFERROR(OFFSET(Assumptions!$R$24,$O31,0),"") -> 1684.7353 | L32: =IFERROR(OFFSET(Assumptions!$T$24,$O31,0),"") -> 4.8135295 | O32: =IFERROR(IF(OFFSET(O32,-1,0)+1>$O$35,"",OFFSET(O32,-1,0)+1),"") -> 5
B33: Permit / City Fees | C33: =+'Development Summary'!I24 -> 1321042.2 | D33: =IFERROR($C33/Beds,0) -> 1064.1057 | E33: =IFERROR($C33/Units,0) -> 2863.5204 | G33: =IFERROR(OFFSET(Assumptions!$H$24,$O32,0),"") -> 4BR/4BA | H33: =IFERROR(OFFSET(Assumptions!$M$24,$O32,0),"") -> 684.22721 | I33: =+IFERROR(H33/$H$36,"") -> 0.55114823 | J33: =IFERROR(OFFSET(Assumptions!$I$24,$O32,0),"") -> 1260 | K33: =IFERROR(OFFSET(Assumptions!$R$24,$O32,0),"") -> 1693.7269 | L33: =IFERROR(OFFSET(Assumptions!$T$24,$O32,0),"") -> 5.3769106 | O33: =IFERROR(IF(OFFSET(O33,-1,0)+1>$O$35,"",OFFSET(O33,-1,0)+1),"")
B34: Legal / Professional / Admin Services | C34: =+'Development Summary'!I25 -> 1290000 | D34: =IFERROR($C34/Beds,0) -> 1039.101 | E34: =IFERROR($C34/Units,0) -> 2796.2326 | G34: =IFERROR(OFFSET(Assumptions!$H$24,$O33,0),"") | H34: =IFERROR(OFFSET(Assumptions!$M$24,$O33,0),"") | I34: =+IFERROR(H34/$H$36,"") | J34: =IFERROR(OFFSET(Assumptions!$I$24,$O33,0),"") | K34: =IFERROR(OFFSET(Assumptions!$R$24,$O33,0),"") | L34: =IFERROR(OFFSET(Assumptions!$T$24,$O33,0),"") | O34: =IFERROR(IF(OFFSET(O34,-1,0)+1>$O$35,"",OFFSET(O34,-1,0)+1),"")
B35: Leasing & Operations | C35: =+'Development Summary'!I26 -> 2422981.3 | D35: =IFERROR($C35/Beds,0) -> 1951.7228 | E35: =IFERROR($C35/Units,0) -> 5252.108 | O35: =+Assumptions!F37 -> 5
B36: FF&E | C36: =+'Development Summary'!I27 -> 6448298.9 | D36: =IFERROR($C36/Beds,0) -> 5194.135 | E36: =IFERROR($C36/Units,0) -> 13977.476 | G36: Total Residential | H36: =SUM(H29:H34) -> 1241.4577 | I36: =+H36/$H$36 -> 1 | J36: =Assumptions!I22 -> 929.29213 | K36: =SUMPRODUCT(K29:K34,$H$29:$H$34)/$H$36 -> 1721.2294 | L36: =Assumptions!S22/Assumptions!I22 -> 4.9842752
B37: Taxes and Insurance | C37: =+'Development Summary'!I28 -> 3006319.7 | D37: =IFERROR($C37/Beds,0) -> 2421.6046 | E37: =IFERROR($C37/Units,0) -> 6516.5652
B38: Construction Financing Costs | C38: =+'Development Summary'!I29 -> 9958874.8 | D38: =IFERROR($C38/Beds,0) -> 8021.9203 | E38: =IFERROR($C38/Units,0) -> 21587.078 | G38: Unit Type | J38: RSF/Unit | K38: Rent/Year | L38: RSF/Year | O38: =IFERROR(IF(OFFSET(O38,-1,0)+1>$O$41,"",OFFSET(O38,-1,0)+1),"") -> 1
B39: Soft Cost Contingency | C39: =+'Development Summary'!I30 -> 1064579.8 | D39: =IFERROR($C39/Beds,0) -> 857.52401 | E39: =IFERROR($C39/Units,0) -> 2307.6068 | G39: =IF(Assumptions!$G43=0,"",Assumptions!$G43) -> Retail | J39: =IF(Assumptions!$I43=0,"",Assumptions!$I43) -> 1824 | K39: =IF(Assumptions!$N43=0,"",Assumptions!$N43) -> 63780.29 | L39: =IF(Assumptions!$L43=0,"",Assumptions!$L43) -> 32 | O39: =IFERROR(IF(OFFSET(O39,-1,0)+1>$O$41,"",OFFSET(O39,-1,0)+1),"")
B40: Development Fee | C40: =+'Development Summary'!I31 -> 9190537.3 | D40: =IFERROR($C40/Beds,0) -> 7403.0209 | E40: =IFERROR($C40/Units,0) -> 19921.612 | G40: =IF(Assumptions!$G44=0,"",Assumptions!$G44) | J40: =IF(Assumptions!$I44=0,"",Assumptions!$I44) | K40: =IF(Assumptions!$N44=0,"",Assumptions!$N44) | L40: =IF(Assumptions!$L44=0,"",Assumptions!$L44) | O40: =IFERROR(IF(OFFSET(O40,-1,0)+1>$O$41,"",OFFSET(O40,-1,0)+1),"")
B41: Construction Management Fee | C41: =+'Development Summary'!I32 -> 3394063.6 | D41: =IFERROR($C41/Beds,0) -> 2733.9341 | E41: =IFERROR($C41/Units,0) -> 7357.0474 | G41: Total Commercial | J41: =Assumptions!I45 -> 1824 | K41: =Assumptions!N45 -> 63780.29 | L41: =Assumptions!L45 -> 32 | O41: =+Assumptions!F45 -> 1
B42: Total Uses | C42: =+'Development Summary'!I36 -> 2.3895397e+08 | D42: =IFERROR($C42/Beds,0) -> 192478.54 | E42: =IFERROR($C42/Units,0) -> 517961.92
G43: ="OPERATING BUDGET (Yr. "&K44&")" -> OPERATING BUDGET (Yr. 2)
B44: Sources | C44: Total | D44: $/Bed | E44: % of Total | K44: 2 | L44: Per Bed
B45: Equity | C45: =Development!G265 -> 83633890 | D45: =IFERROR($C45/Beds,0) -> 67367.49 | E45: =Development!H265 -> 0.35 | G45: ='Cash Flow'!B4 -> Gross Potential Rent | K45: =OFFSET('Cash Flow'!F4,0,$K$44-1) -> 26578935 | L45: =IFERROR($K45/Beds,0) -> 21409.457
B46: Mezz Debt | C46: =Development!G266 -> 0 | D46: =IFERROR($C46/Beds,0) -> 0 | E46: =Development!H266 -> 0 | G46: ='Cash Flow'!B5 -> General Vacancy Loss | K46: =OFFSET('Cash Flow'!F5,0,$K$44-1) -> -1328946.8 | L46: =IFERROR($K46/Beds,0) -> -1070.4728
B47: Construction Loan | C47: =Development!G267 -> 1.5532008e+08 | D47: =IFERROR($C47/Beds,0) -> 125111.05 | E47: =Development!H267 -> 0.65 | G47: ='Cash Flow'!B6 -> Collection/ Bad Debt Expense | K47: =OFFSET('Cash Flow'!F6,0,$K$44-1) -> -189374.91 | L47: =IFERROR($K47/Beds,0) -> -152.54238
B48: Total Sources | C48: =SUM(C45:C47) -> 2.3895397e+08 | D48: =IFERROR($C$48/Beds,0) -> 192478.54 | E48: =SUM(E45:E47) -> 1 | G48: ='Cash Flow'!B7 -> Parking Revenue | K48: =OFFSET('Cash Flow'!F7,0,$K$44-1) -> 1474866.7 | L48: =IFERROR($K48/Beds,0) -> 1188.0121
G49: ='Cash Flow'!B8 -> Other Income | K49: =OFFSET('Cash Flow'!F8,0,$K$44-1) -> 606220.41 | L49: =IFERROR($K49/Beds,0) -> 488.31338
G50: ='Cash Flow'!B9 -> Utility Income | K50: =OFFSET('Cash Flow'!F9,0,$K$44-1) -> 634349.82 | L50: =IFERROR($K50/Beds,0) -> 510.97176
G51: ='Cash Flow'!B10 -> Effective Gross Residential Revenue | K51: =SUM(K45:K50) -> 27776051 | L51: =IFERROR($K51/Beds,0) -> 22373.739
G52: ='Cash Flow'!B16 -> Effective Gross Commercial Revenue | K52: =OFFSET('Cash Flow'!F16,0,$K$44-1) -> 65325.928 | L52: =IFERROR($K52/Beds,0) -> 52.620341
B53: FINANCING SUMMARY | G53: Total Effective Gross Revenue | K53: =+SUM(K51:K52) -> 27841377 | L53: =IFERROR($K53/Beds,0) -> 22426.359
D54: Construction | E54: Permanent
B55: Base Rate | D55: SOFR | E55: 0.05
B56: Spread | D56: =+Development!P210 -> 0.0325 | E56: N/A
B57: Loan Amount | D57: =+Development!G267 -> 1.5532008e+08 | E57: =+'Sale Proceeds'!D59*'Executive Summary'!E58 -> 2.3760089e+08 | G57: Operating Expenses
B58: LTC | D58: =+Development!H267 -> 0.65 | E58: 0.615 | G58: ='Cash Flow'!B28 -> Ground Lease | J58: =IFERROR(K58/$K$53,0) -> 0.0084406746 | K58: =OFFSET('Cash Flow'!F28,0,$K$44-1) -> 235000 | L58: =IFERROR($K58/Beds,0) -> 189.2936
B59: Amortization | E59: 30 | G59: ='Cash Flow'!B29 -> Property Taxes | J59: =IFERROR(K59/$K$53,0) -> 0.088594996 | K59: =OFFSET('Cash Flow'!F29,0,$K$44-1) -> 2466606.6 | L59: =IFERROR($K59/Beds,0) -> 1986.8632
B60: DSCR | E60: =+'3-Yr Waterfall'!D64 -> 1.2999327 | G60: ='Cash Flow'!B31 -> Insurance | J60: =IFERROR(K60/$K$53,0) -> 0.017226805 | K60: =OFFSET('Cash Flow'!F31,0,$K$44-1) -> 479617.96 | L60: =IFERROR($K60/Beds,0) -> 386.33451
B61: Interest Only Period | E61: 5 | G61: ='Cash Flow'!B20 -> General & Administrative | J61: =IFERROR(K61/$K$53,0) -> 0.01181808 | K61: =OFFSET('Cash Flow'!F20,0,$K$44-1) -> 329031.62 | L61: =IFERROR($K61/Beds,0) -> 265.03651
B62: I/O Start Date | E62: =+C73-1 -> 48060 | G62: ='Cash Flow'!B22 -> Leasing and Marketing | J62: =IFERROR(K62/$K$53,0) -> 0.008146802 | K62: =OFFSET('Cash Flow'!F22,0,$K$44-1) -> 226818.18 | L62: =IFERROR($K62/Beds,0) -> 182.70311
B63: I/O End Date | E63: =+EDATE(E62,E61*12) -> 49887 | G63: ='Cash Flow'!B21 -> Payroll | J63: =IFERROR(K63/$K$53,0) -> 0.037697171 | K63: =OFFSET('Cash Flow'!F21,0,$K$44-1) -> 1049541.1 | L63: =IFERROR($K63/Beds,0) -> 845.41029
B64: PMT Interest Only | E64: =+E57*E55/12 -> 990003.71 | G64: ='Cash Flow'!B23 -> Maintenance and Repairs | J64: =IFERROR(K64/$K$53,0) -> 0.0038666794 | K64: =OFFSET('Cash Flow'!F23,0,$K$44-1) -> 107653.68 | L64: =IFERROR($K64/Beds,0) -> 86.715541
B65: PMT Amortizing | E65: =PMT(E55/12,E59*12,-E57,0) -> 1275493 | G65: ='Cash Flow'!B24 -> Contract Services | J65: =IFERROR(K65/$K$53,0) -> 0.015996319 | K65: =OFFSET('Cash Flow'!F24,0,$K$44-1) -> 445359.53 | L65: =IFERROR($K65/Beds,0) -> 358.73919
B66: Origination Fee | E66: 0.005 | G66: ='Cash Flow'!B25 -> Turnover | J66: =IFERROR(K66/$K$53,0) -> 0.006632812 | K66: =OFFSET('Cash Flow'!F25,0,$K$44-1) -> 184666.62 | L66: =IFERROR($K66/Beds,0) -> 148.74983
G67: ='Cash Flow'!B27 -> Utilities | J67: =IFERROR(K67/$K$53,0) -> 0.050400709 | K67: =OFFSET('Cash Flow'!F27,0,$K$44-1) -> 1403225.1 | L67: =IFERROR($K67/Beds,0) -> 1130.3044
G68: ='Cash Flow'!B32 -> Management Fees | J68: =IFERROR(K68/$K$53,0) -> 0.03 | K68: =OFFSET('Cash Flow'!F32,0,$K$44-1) -> 835241.3 | L68: =IFERROR($K68/Beds,0) -> 672.79078
B69: DEVELOPMENT SCHEDULE | G69: ='Cash Flow'!B34 -> Total Commercial Operating Expenses | J69: =IFERROR(K69/$K$53,0) -> 0.00026205601 | K69: =OFFSET('Cash Flow'!F34,0,$K$44-1) -> 7296 | L69: =IFERROR($K69/Beds,0) -> 5.8769622
B70: Land Acquisition | C70: =+StartDate -> 46753 | G70: Total Operating Expenses | J70: =SUM(J58:J69) -> 0.2790831 | K70: =SUM(K58:K69) -> 7770057.7 | L70: =SUM(L58:L69) -> 6258.8179
B71: Construction Start Date | C71: =+Development!M8 -> 46784
B72: Lease-Up Start Date | C72: =+Development!M9 -> 47696 | D72: =+DATEDIF($C$70,C72,"M") -> 31 | E72: mos from land acq. | G72: Capital Reserves
B73: Stabilized Year Start Date | C73: =+Development!M10 -> 48061 | D73: =+DATEDIF($C$70,C73,"M") -> 43 | E73: mos from land acq. | G73: ='Cash Flow'!B41 -> Commercial Capital Reserves | K73: =OFFSET('Cash Flow'!F41,0,$K$44-1) -> 0 | L73: =IFERROR($K73/Units,0) -> 0
G74: ='Cash Flow'!B42 -> Residential Capital Reserve | K74: =OFFSET('Cash Flow'!F42,0,$K$44-1) -> 174658.95 | L74: =IFERROR($K74/Beds,0) -> 140.6886
C75: Duration | D75: Start Date | E75: End Date | G75: Total Capital Reserves | K75: =SUM(K73:K74) -> 174658.95 | L75: =SUM(L73:L74) -> 140.6886
B76: Land Hold Period | C76: =+Development!O7 -> 1 | D76: =+C70 -> 46753 | E76: =EOMONTH(D76-1,C76) -> 46783
B77: Construction Period | C77: =+Development!O8 -> 30 | D77: =+E76+1 -> 46784 | E77: =EOMONTH(D77-1,C77) -> 47695 | G77: NET OPERATING INCOME | K77: =K53-K70-K75 -> 19896660 | L77: =L53-L70-L75 -> 16026.853
B78: Total | C78: =SUM(C76:C77) -> 31 | D78: =D76 -> 46753 | E78: =E77 -> 47695

Sheet Development Summary
D1: =+'Executive Summary'!E5 & " DEVELOPMENT COST SUMMARY" -> VERVE Chapel Hill DEVELOPMENT COST SUMMARY
E5: Development Costs | L5: Project Size
L6: Units | N6: Beds | P6: Gross SF | R6: Net SF
A7: Filters/Lookups | L7: =Development!$H$9 -> 461.33501 | N7: =Development!$H$10 -> 1241.4577 | P7: =Development!$H$15 -> 757823 | R7: =Development!$H$16 -> 428715
A8: CODE | B8: # | C8: Asset | E8: Line Items | G8: % of Total | I8: $ Amount | L8: $/Unit | N8: $/Bed | P8: $/GSF | R8: $/NRSF
A9: =B9&" - "&E9 -> # - | B9: =OFFSET(B9,-1,0) -> # | C9: =OFFSET(C9,-1,0) -> Asset
A10: =B10&" - "&E10 -> # - Land Costs | B10: =OFFSET(B10,-1,0) -> # | C10: =OFFSET(C10,-1,0) -> Asset | E10: =+Development!E35 -> Land Costs | G10: =I10/$I$36 -> 0.10708129 | I10: =+Development!G40 -> 25587500 | L10: =IFERROR($I10/L$7,0) -> 55464.032 | N10: =IFERROR($I10/N$7,0) -> 20610.851 | P10: =IFERROR($I10/P$7,0) -> 33.764481 | R10: =IFERROR($I10/R$7,0) -> 59.684172
A11: =B11&" - "&E11 -> # - Closing Costs | B11: =OFFSET(B11,-1,0) -> # | C11: =OFFSET(C11,-1,0) -> Asset | E11: =+Development!E42 -> Closing Costs | G11: =I11/$I$36 -> 0.0009465212 | I11: =+Development!G49 -> 226175 | L11: =IFERROR($I11/L$7,0) -> 490.26194 | N11: =IFERROR($I11/N$7,0) -> 182.18502 | P11: =IFERROR($I11/P$7,0) -> 0.2984536 | R11: =IFERROR($I11/R$7,0) -> 0.52756493
A12: =B12&" - "&E12 -> # - Total Miscellaneous | B12: =OFFSET(B12,-1,0) -> # | C12: =OFFSET(C12,-1,0) -> Asset | E12: =+Development!E56 -> Total Miscellaneous | G12: =I12/$I$36 -> 0.0010462266 | I12: =+Development!G56 -> 250000 | L12: =IFERROR($I12/L$7,0) -> 541.90554 | N12: =IFERROR($I12/N$7,0) -> 201.37617 | P12: =IFERROR($I12/P$7,0) -> 0.32989234 | R12: =IFERROR($I12/R$7,0) -> 0.58313798
A13: =B13&" - "&E13 -> # - | B13: =OFFSET(B13,-1,0) -> # | C13: =OFFSET(C13,-1,0) -> Asset
A14: =B14&" - "&E14 -> # - Total Acquisition Costs | B14: =OFFSET(B14,-1,0) -> # | C14: =OFFSET(C14,-1,0) -> Asset | E14: Total Acquisition Costs | G14: =I14/$I$36 -> 0.10907404 | I14: =+SUM(I10:I13) -> 26063675 | L14: =IFERROR($I14/L$7,0) -> 56496.2 | N14: =IFERROR($I14/N$7,0) -> 20994.412 | P14: =IFERROR($I14/P$7,0) -> 34.392827 | R14: =IFERROR($I14/R$7,0) -> 60.794875
A15: =B15&" - "&E15 -> # - | B15: =OFFSET(B15,-1,0) -> # | C15: =OFFSET(C15,-1,0) -> Asset
A16: =B16&" - "&E16 -> # - Site Work | B16: =OFFSET(B16,-1,0) -> # | C16: =OFFSET(C16,-1,0) -> Asset | E16: =+Development!E62 -> Site Work | G16: =I16/$I$36 -> 0.0032433025 | I16: =+Development!G69 -> 775000 | L16: =IFERROR($I16/L$7,0) -> 1679.9072 | N16: =IFERROR($I16/N$7,0) -> 624.26613 | P16: =IFERROR($I16/P$7,0) -> 1.0226662 | R16: =IFERROR($I16/R$7,0) -> 1.8077277
A17: =B17&" - "&E17 -> # - Construction Costs | B17: =OFFSET(B17,-1,0) -> # | C17: =OFFSET(C17,-1,0) -> Asset | E17: =+Development!E71 -> Construction Costs | G17: =I17/$I$36 -> 0.67312995 | I17: =+Development!G81 -> 1.6084708e+08 | L17: =IFERROR($I17/L$7,0) -> 348655.69 | N17: =IFERROR($I17/N$7,0) -> 129563.07 | P17: =IFERROR($I17/P$7,0) -> 212.24887 | R17: =IFERROR($I17/R$7,0) -> 375.18416
A18: =B18&" - "&E18 -> # - Hard Cost Contingency | B18: =OFFSET(B18,-1,0) -> # | C18: =OFFSET(C18,-1,0) -> Asset | E18: =+Development!E83 -> Hard Cost Contingency | G18: =I18/$I$36 -> 0.033818663 | I18: =+Development!G87 -> 8081103.8 | L18: =IFERROR($I18/L$7,0) -> 17516.78 | N18: =IFERROR($I18/N$7,0) -> 6509.367 | P18: =IFERROR($I18/P$7,0) -> 10.663577 | R18: =IFERROR($I18/R$7,0) -> 18.849594
A19: =B19&" - "&E19 -> # - | B19: =OFFSET(B19,-1,0) -> # | C19: =OFFSET(C19,-1,0) -> Asset
A20: =B20&" - "&E20 -> # - Total Hard Costs | B20: =OFFSET(B20,-1,0) -> # | C20: =OFFSET(C20,-1,0) -> Asset | E20: Total Hard Costs | G20: =I20/$I$36 -> 0.71019192 | I20: =+SUM(I16:I19) -> 1.6970318e+08 | L20: =IFERROR($I20/L$7,0) -> 367852.37 | N20: =IFERROR($I20/N$7,0) -> 136696.71 | P20: =IFERROR($I20/P$7,0) -> 223.93511 | R20: =IFERROR($I20/R$7,0) -> 395.84148
A21: =B21&" - "&E21 -> # - | B21: =OFFSET(B21,-1,0) -> # | C21: =OFFSET(C21,-1,0) -> Asset
A22: =B22&" - "&E22 -> # - Architectural / Engineering / Design | B22: =OFFSET(B22,-1,0) -> # | C22: =OFFSET(C22,-1,0) -> Asset | E22: =+Development!E93 -> Architectural / Engineering / Design | G22: =I22/$I$36 -> 0.019048862 | I22: =+Development!G110 -> 4551801.1 | L22: =IFERROR($I22/L$7,0) -> 9866.5849 | N22: =IFERROR($I22/N$7,0) -> 3666.4971 | P22: =IFERROR($I22/P$7,0) -> 6.0064172 | R22: =IFERROR($I22/R$7,0) -> 10.617312
A23: =B23&" - "&E23 -> # - Diligence Consultants | B23: =OFFSET(B23,-1,0) -> # | C23: =OFFSET(C23,-1,0) -> Asset | E23: =+Development!E112 -> Diligence Consultants | G23: =I23/$I$36 -> 0.0022540646 | I23: =+Development!G123 -> 538617.69 | L23: =IFERROR($I23/L$7,0) -> 1167.5196 | N23: =IFERROR($I23/N$7,0) -> 433.85907 | P23: =IFERROR($I23/P$7,0) -> 0.71074339 | R23: =IFERROR($I23/R$7,0) -> 1.2563537
A24: =B24&" - "&E24 -> # - Permit/City Fees | B24: =OFFSET(B24,-1,0) -> # | C24: =OFFSET(C24,-1,0) -> Asset | E24: =+Development!E125 -> Permit/City Fees | G24: =I24/$I$36 -> 0.0055284381 | I24: =+Development!G146 -> 1321042.2 | L24: =IFERROR($I24/L$7,0) -> 2863.5204 | N24: =IFERROR($I24/N$7,0) -> 1064.1057 | P24: =IFERROR($I24/P$7,0) -> 1.7432068 | R24: =IFERROR($I24/R$7,0) -> 3.0813996
A25: =B25&" - "&E25 -> # - Legal / Professional / Admin Services | B25: =OFFSET(B25,-1,0) -> # | C25: =OFFSET(C25,-1,0) -> Asset | E25: =+Development!E148 -> Legal / Professional / Admin Services | G25: =I25/$I$36 -> 0.0053985293 | I25: =+Development!G161 -> 1290000 | L25: =IFERROR($I25/L$7,0) -> 2796.2326 | N25: =IFERROR($I25/N$7,0) -> 1039.101 | P25: =IFERROR($I25/P$7,0) -> 1.7022445 | R25: =IFERROR($I25/R$7,0) -> 3.008992
A26: =B26&" - "&E26 -> # - Leasing & Operations | B26: =OFFSET(B26,-1,0) -> # | C26: =OFFSET(C26,-1,0) -> Asset | E26: =+Development!E163 -> Leasing & Operations | G26: =I26/$I$36 -> 0.01013995 | I26: =+Development!G174 -> 2422981.3 | L26: =IFERROR($I26/L$7,0) -> 5252.108 | N26: =IFERROR($I26/N$7,0) -> 1951.7228 | P26: =IFERROR($I26/P$7,0) -> 3.1972919 | R26: =IFERROR($I26/R$7,0) -> 5.6517297
A27: =B27&" - "&E27 -> # - FF&E | B27: =OFFSET(B27,-1,0) -> # | C27: =OFFSET(C27,-1,0) -> Asset | E27: =+Development!E176 -> FF&E | G27: =I27/$I$36 -> 0.026985527 | I27: =+Development!G196 -> 6448298.9 | L27: =IFERROR($I27/L$7,0) -> 13977.476 | N27: =IFERROR($I27/N$7,0) -> 5194.135 | P27: =IFERROR($I27/P$7,0) -> 8.5089776 | R27: =IFERROR($I27/R$7,0) -> 15.040992
A28: =B28&" - "&E28 -> # - Taxes and Insurance | B28: =OFFSET(B28,-1,0) -> # | C28: =OFFSET(C28,-1,0) -> Asset | E28: =+Development!E198 -> Taxes and Insurance | G28: =I28/$I$36 -> 0.012581167 | I28: =+Development!G205 -> 3006319.7 | L28: =IFERROR($I28/L$7,0) -> 6516.5652 | N28: =IFERROR($I28/N$7,0) -> 2421.6046 | P28: =IFERROR($I28/P$7,0) -> 3.9670473 | R28: =IFERROR($I28/R$7,0) -> 7.0123968
A29: =B29&" - "&E29 -> # - Construction Financing Costs | B29: =OFFSET(B29,-1,0) -> # | C29: =OFFSET(C29,-1,0) -> Asset | E29: =+Development!E212 -> Construction Financing Costs | G29: =I29/$I$36 -> 0.041676959 | I29: =+Development!G225 -> 9958874.8 | L29: =IFERROR($I29/L$7,0) -> 21587.078 | N29: =IFERROR($I29/N$7,0) -> 8021.9203 | P29: =IFERROR($I29/P$7,0) -> 13.141426 | R29: =IFERROR($I29/R$7,0) -> 23.229593
A30: =B30&" - "&E30 -> # - Soft Cost Contingency | B30: =OFFSET(B30,-1,0) -> # | C30: =OFFSET(C30,-1,0) -> Asset | E30: =+Development!E227 -> Soft Cost Contingency | G30: =I30/$I$36 -> 0.0044551668 | I30: =+Development!G231 -> 1064579.8 | L30: =IFERROR($I30/L$7,0) -> 2307.6068 | N30: =IFERROR($I30/N$7,0) -> 857.52401 | P30: =IFERROR($I30/P$7,0) -> 1.4047869 | R30: =IFERROR($I30/R$7,0) -> 2.4831877
A31: =B31&" - "&E31 -> # - Development Fee | B31: =OFFSET(B31,-1,0) -> # | C31: =OFFSET(C31,-1,0) -> Asset | E31: =+Development!E234 -> Development Fee | G31: =I31/$I$36 -> 0.038461538 | I31: =+Development!G238 -> 9190537.3 | L31: =IFERROR($I31/L$7,0) -> 19921.612 | N31: =IFERROR($I31/N$7,0) -> 7403.0209 | P31: =IFERROR($I31/P$7,0) -> 12.127551 | R31: =IFERROR($I31/R$7,0) -> 21.437406
A32: =B32&" - "&E32 -> # - Construction Management Fee | B32: =OFFSET(B32,-1,0) -> # | C32: =OFFSET(C32,-1,0) -> Asset | E32: =+Development!E240 -> Construction Management Fee | G32: =I32/$I$36 -> 0.014203838 | I32: =+Development!G244 -> 3394063.6 | L32: =IFERROR($I32/L$7,0) -> 7357.0474 | N32: =IFERROR($I32/N$7,0) -> 2733.9341 | P32: =IFERROR($I32/P$7,0) -> 4.4787023 | R32: =IFERROR($I32/R$7,0) -> 7.9168296
A33: =B33&" - "&E33 -> # - | B33: =OFFSET(B33,-1,0) -> # | C33: =OFFSET(C33,-1,0) -> Asset
A34: =B34&" - "&E34 -> # - Total Soft Costs | B34: =OFFSET(B34,-1,0) -> # | C34: =OFFSET(C34,-1,0) -> Asset | E34: Total Soft Costs | G34: =I34/$I$36 -> 0.18073404 | I34: =+SUM(I22:I33) -> 43187116 | L34: =IFERROR($I34/L$7,0) -> 93613.351 | N34: =IFERROR($I34/N$7,0) -> 34787.425 | P34: =IFERROR($I34/P$7,0) -> 56.988395 | R34: =IFERROR($I34/R$7,0) -> 100.73619
A35: =B35&" - "&E35 -> # - | B35: =OFFSET(B35,-1,0) -> # | C35: =OFFSET(C35,-1,0) -> Asset
A36: =B36&" - "&#REF! -> #REF! | B36: =OFFSET(B36,-1,0) -> # | C36: =OFFSET(C36,-1,0) -> Asset | E36: TOTAL DEVELOPMENT COSTS | G36: =I36/$I$36 -> 1 | I36: =+SUM(I14,I20,I34) -> 2.3895397e+08 | L36: =IFERROR($I36/L$7,0) -> 517961.92 | N36: =IFERROR($I36/N$7,0) -> 192478.54 | P36: =IFERROR($I36/P$7,0) -> 315.31633 | R36: =IFERROR($I36/R$7,0) -> 557.37255
E38: ='Executive Summary'!E58 -> 0.615 | G38: =I38/$I$36 -> 0.65 | I38: =Debt -> 1.5532008e+08 | L38: =IFERROR($I38/L$7,0) -> 336675.25 | N38: =IFERROR($I38/N$7,0) -> 125111.05 | P38: =IFERROR($I38/P$7,0) -> 204.95562 | R38: =IFERROR($I38/R$7,0) -> 362.29215
E39: Total Equity | G39: =I39/$I$36 -> 0.35 | I39: =Equity -> 83633890 | L39: =IFERROR($I39/L$7,0) -> 181286.67 | N39: =IFERROR($I39/N$7,0) -> 67367.49 | P39: =IFERROR($I39/P$7,0) -> 110.36072 | R39: =IFERROR($I39/R$7,0) -> 195.08039
D224: =+D210-D221 -> 0

Sheet Cash Flow
A1: ='Executive Summary'!$E$5 & " CASH FLOW" -> VERVE Chapel Hill CASH FLOW
A2: CASH FLOW | E2: Per Bed | F2: 1 | G2: =+F2+1 -> 2 | H2: =+G2+1 -> 3 | I2: =+H2+1 -> 4 | J2: =+I2+1 -> 5 | K2: =+J2+1 -> 6 | L2: =+K2+1 -> 7 | M2: =+L2+1 -> 8 | N2: =+M2+1 -> 9 | O2: =+N2+1 -> 10 | Q2: Untrended | S2: Trending | U2: Stabilized Year (Year 2)
A3: EFFECTIVE GROSS REVENUE | Q3: Current Year | U3: Expense Ratios
B4: Gross Potential Rent | E4: =G4/Beds -> 21409.457 | F4: =Assumptions!V60 -> 25804792 | G4: =Assumptions!H60 -> 26578935 | H4: =G4*(1+$S4) -> 27376303 | I4: =H4*(1+$S4) -> 28197592 | J4: =I4*(1+$S4) -> 29043520 | K4: =J4*(1+$S4) -> 29914826 | L4: =K4*(1+$S4) -> 30812271 | M4: =L4*(1+$S4) -> 31736639 | N4: =M4*(1+$S4) -> 32688738 | O4: =N4*(1+$S4) -> 33669400 | Q4: =Assumptions!H60/((1+Assumptions!$D$17)*(1+Assumptions!$D$18)*(1+Assumptions!$D$19)*(1+'Cash Flow'!$S4)) -> 23615040 | S4: =Assumptions!$G60 -> 0.03 | U4: =G36/G17 -> 0.2790831
B5: General Vacancy Loss | E5: =G5/Beds -> -1070.4728 | F5: =Assumptions!V61 -> -5160958.3 | G5: =Assumptions!H61 -> -1328946.8 | H5: =-H4*$S5 -> -1368815.2 | I5: =-I4*$S5 -> -1409879.6 | J5: =-J4*$S5 -> -1452176 | K5: =-K4*$S5 -> -1495741.3 | L5: =-L4*$S5 -> -1540613.5 | M5: =-M4*$S5 -> -1586831.9 | N5: =-N4*$S5 -> -1634436.9 | O5: =-O4*$S5 -> -1683470 | Q5: =-Q4*$S5 -> -1180752 | S5: =Assumptions!$G61 -> 0.05 | U5: Controllable Expenses Per Bed
B6: Collection/ Bad Debt Expense | E6: =G6/Beds -> -152.54238 | F6: =Assumptions!V62 -> -154828.75 | G6: =Assumptions!H62 -> -189374.91 | H6: =-SUM(H4:H5)*$S6 -> -195056.16 | I6: =-SUM(I4:I5)*$S6 -> -200907.85 | J6: =-SUM(J4:J5)*$S6 -> -206935.08 | K6: =-SUM(K4:K5)*$S6 -> -213143.13 | L6: =-SUM(L4:L5)*$S6 -> -219537.43 | M6: =-SUM(M4:M5)*$S6 -> -226123.55 | N6: =-SUM(N4:N5)*$S6 -> -232907.26 | O6: =-SUM(O4:O5)*$S6 -> -239894.48 | Q6: =-SUM(Q4:Q5)*$S6 -> -168257.16 | S6: 0.0075 | U6: =SUM(E20:E25) -> 1887.3545
B7: Parking Revenue | E7: =G7/Beds -> 1188.0121 | F7: =Assumptions!V68 -> 1145527.6 | G7: =Assumptions!H68 -> 1474866.7 | H7: =G7*(1+$S7) -> 1519112.7 | I7: =H7*(1+$S7) -> 1564686.1 | J7: =I7*(1+$S7) -> 1611626.7 | K7: =J7*(1+$S7) -> 1659975.5 | L7: =K7*(1+$S7) -> 1709774.8 | M7: =L7*(1+$S7) -> 1761068 | N7: =M7*(1+$S7) -> 1813900.1 | O7: =N7*(1+$S7) -> 1868317.1 | Q7: =+Assumptions!H68/((1+Assumptions!$D$17)*(1+Assumptions!$D$18)*(1+Assumptions!$D$19)*(1+'Cash Flow'!$S7)) -> 1310400 | S7: =Assumptions!$G68 -> 0.03
B8: Other Income | E8: =G8/Beds -> 488.31338 | F8: =+Assumptions!V84+Assumptions!V86+Assumptions!V106 -> 460127.29 | G8: =+Assumptions!H84+Assumptions!H86+Assumptions!H106 -> 606220.41 | H8: =G8*(1+$S8) -> 624407.02 | I8: =H8*(1+$S8) -> 643139.23 | J8: =I8*(1+$S8) -> 662433.41 | K8: =J8*(1+$S8) -> 682306.41 | L8: =K8*(1+$S8) -> 702775.6 | M8: =L8*(1+$S8) -> 723858.87 | N8: =M8*(1+$S8) -> 745574.64 | O8: =N8*(1+$S8) -> 767941.88 | Q8: =+(Assumptions!H84+Assumptions!H86+Assumptions!H106)/((1+Assumptions!$D$17)*(1+Assumptions!$D$18)*(1+Assumptions!$D$19)*(1+'Cash Flow'!$S8)) -> 538618.98 | S8: =Assumptions!$G84 -> 0.03 | U8: Net Utility Expense Per Bed
B9: Utility Income | E9: =G9/Beds -> 510.97176 | F9: =Assumptions!V80 -> 494638.37 | G9: =Assumptions!H80 -> 634349.82 | H9: =G9*(1+$S9) -> 653380.32 | I9: =H9*(1+$S9) -> 672981.73 | J9: =I9*(1+$S9) -> 693171.18 | K9: =J9*(1+$S9) -> 713966.31 | L9: =K9*(1+$S9) -> 735385.3 | M9: =L9*(1+$S9) -> 757446.86 | N9: =M9*(1+$S9) -> 780170.27 | O9: =N9*(1+$S9) -> 803575.38 | Q9: =+Assumptions!H80/((1+Assumptions!$D$17)*(1+Assumptions!$D$18)*(1+Assumptions!$D$19)*(1+'Cash Flow'!$S9)) -> 563611.6 | S9: =Assumptions!$G80 -> 0.03 | U9: =E27-E9 -> 619.33264
B10: Effective Gross Residential Revenue | E10: =G10/Beds -> 22373.739 | F10: =SUM(F4:F9) -> 22589298 | G10: =SUM(G4:G9) -> 27776051 | H10: =SUM(H4:H9) -> 28609332 | I10: =SUM(I4:I9) -> 29467612 | J10: =SUM(J4:J9) -> 30351640 | K10: =SUM(K4:K9) -> 31262190 | L10: =SUM(L4:L9) -> 32200055 | M10: =SUM(M4:M9) -> 33166057 | ... O10: =SUM(O4:O9) -> 35185870 | Q10: =SUM(Q4:Q9) -> 24678661
B12: Commercial Rent | E12: =G12/Beds -> 52.916582 | F12: =Assumptions!V114 -> 47835.217 | G12: =Assumptions!H114 -> 65693.698 | H12: =+G12 -> 65693.698 | I12: =+H12 -> 65693.698 | J12: =+I12 -> 65693.698 | K12: =+J12 -> 65693.698 | L12: =+K12 -> 65693.698 | M12: =+L12 -> 65693.698 | N12: =+M12 -> 65693.698 | O12: =+N12 -> 65693.698 | Q12: =Assumptions!M45 -> 58368 | S12: =Assumptions!G114 -> 0.03
B13: Commercial Vacancy Loss | E13: =G13/Beds -> -5.2916582 | F13: =-F12*$S13 -> -4783.5217 | G13: =-G12*$S13 -> -6569.3698 | H13: =-H12*$S13 -> -6569.3698 | I13: =-I12*$S13 -> -6569.3698 | J13: =-J12*$S13 -> -6569.3698 | K13: =-K12*$S13 -> -6569.3698 | L13: =-L12*$S13 -> -6569.3698 | M13: =-M12*$S13 -> -6569.3698 | ... O13: =-O12*$S13 -> -6569.3698 | Q13: =-Q12*$S13 -> -5836.8 | S13: =Assumptions!G115 -> 0.1
B14: Commercial Parking | E14: =G14/Beds -> 0 | F14: =Assumptions!V118 -> 0 | G14: =Assumptions!H118 -> 0 | H14: =+G14 -> 0 | I14: =+H14 -> 0 | J14: =+I14 -> 0 | K14: =+J14 -> 0 | L14: =+K14 -> 0 | M14: =+L14 -> 0 | N14: =+M14 -> 0 | O14: =+N14 -> 0 | Q14: =Assumptions!H118 -> 0 | S14: =Assumptions!G118 -> 0.03
B15: CAM Reimbursement | E15: =G15/Beds -> 4.9954179 | F15: =Assumptions!V119 -> 4651.2 | G15: =G34*$S15 -> 6201.6 | H15: =H34*$S15 -> 6356.64 | I15: =I34*$S15 -> 6515.556 | J15: =J34*$S15 -> 6678.4449 | K15: =K34*$S15 -> 6845.406 | L15: =L34*$S15 -> 7016.5412 | M15: =M34*$S15 -> 7191.9547 | N15: =N34*$S15 -> 7371.7536 | O15: =O34*$S15 -> 7556.0474 | Q15: =Q34*$S15 -> 6201.6 | S15: =Assumptions!G119 -> 0.85
B16: Effective Gross Commercial Revenue | E16: =G16/Beds -> 52.620341 | F16: =SUM(F12:F15) -> 47702.895 | G16: =SUM(G12:G15) -> 65325.928 | H16: =SUM(H12:H15) -> 65480.968 | I16: =SUM(I12:I15) -> 65639.884 | J16: =SUM(J12:J15) -> 65802.773 | K16: =SUM(K12:K15) -> 65969.734 | L16: =SUM(L12:L15) -> 66140.87 | M16: =SUM(M12:M15) -> 66316.283 | ... O16: =SUM(O12:O15) -> 66680.376 | Q16: =SUM(Q12:Q15) -> 58732.8
A17: TOTAL EFFECTIVE GROSS REVENUE | E17: =G17/Beds -> 22426.359 | F17: =SUM(F10,F16) -> 22637001 | G17: =SUM(G10,G16) -> 27841377 | H17: =SUM(H10,H16) -> 28674813 | I17: =SUM(I10,I16) -> 29533252 | J17: =SUM(J10,J16) -> 30417443 | K17: =SUM(K10,K16) -> 31328159 | L17: =SUM(L10,L16) -> 32266196 | M17: =SUM(M10,M16) -> 33232373 | ... O17: =SUM(O10,O16) -> 35252550 | Q17: =SUM(Q10,Q16) -> 24737394
U18: Untrended Year
A19: CONTROLLABLE OPERATING EXPENSES | U19: Expense Ratios
B20: =Assumptions!C155 -> General & Administrative | E20: =G20/Beds -> 265.03651 | F20: =Assumptions!V155 -> 321006.46 | G20: =Assumptions!H155 -> 329031.62 | H20: =G20*(1+$S20) -> 337257.41 | I20: =H20*(1+$S20) -> 345688.85 | J20: =I20*(1+$S20) -> 354331.07 | K20: =J20*(1+$S20) -> 363189.35 | L20: =K20*(1+$S20) -> 372269.08 | M20: =L20*(1+$S20) -> 381575.81 | N20: =M20*(1+$S20) -> 391115.2 | O20: =N20*(1+$S20) -> 400893.08 | Q20: =+Assumptions!H155/(1+S20)^(Assumptions!$D$16+1) -> 298086.41 | S20: =Assumptions!G155 -> 0.025 | U20: =$Q$36/$Q$17 -> 0.2843451
B21: =Assumptions!C191 -> Payroll | E21: =G21/Beds -> 845.41029 | F21: =Assumptions!V191 -> 1023942.6 | G21: =Assumptions!H191 -> 1049541.1 | H21: =G21*(1+$S21) -> 1075779.7 | I21: =H21*(1+$S21) -> 1102674.1 | J21: =I21*(1+$S21) -> 1130241 | K21: =J21*(1+$S21) -> 1158497 | L21: =K21*(1+$S21) -> 1187459.4 | M21: =L21*(1+$S21) -> 1217145.9 | N21: =M21*(1+$S21) -> 1247574.6 | O21: =N21*(1+$S21) -> 1278763.9 | Q21: =+Assumptions!H191/(1+S21)^(Assumptions!$D$16+1) -> 950832.46 | S21: =Assumptions!G191 -> 0.025 | U21: Controllable Expenses Per Bed
B22: =Assumptions!C171 -> Leasing and Marketing | E22: =G22/Beds -> 182.70311 | F22: =Assumptions!V171 -> 221286.03 | G22: =Assumptions!H171 -> 226818.18 | H22: =G22*(1+$S22) -> 232488.64 | I22: =H22*(1+$S22) -> 238300.85 | J22: =I22*(1+$S22) -> 244258.38 | K22: =J22*(1+$S22) -> 250364.83 | L22: =K22*(1+$S22) -> 256623.96 | M22: =L22*(1+$S22) -> 263039.55 | N22: =M22*(1+$S22) -> 269615.54 | O22: =N22*(1+$S22) -> 276355.93 | Q22: =+Assumptions!H171/(1+S22)^(Assumptions!$D$16+1) -> 205486.08 | S22: =Assumptions!G171 -> 0.025 | U22: =SUM($Q$20:$Q$25)/Beds -> 1709.85
B23: =Assumptions!C213 -> Maintenance and Repairs | E23: =G23/Beds -> 86.715541 | F23: =Assumptions!V213 -> 105027.98 | G23: =Assumptions!H213 -> 107653.68 | H23: =G23*(1+$S23) -> 110345.02 | I23: =H23*(1+$S23) -> 113103.64 | J23: =I23*(1+$S23) -> 115931.23 | K23: =J23*(1+$S23) -> 118829.52 | L23: =K23*(1+$S23) -> 121800.25 | M23: =L23*(1+$S23) -> 124845.26 | N23: =M23*(1+$S23) -> 127966.39 | O23: =N23*(1+$S23) -> 131165.55 | Q23: =+Assumptions!H213/(1+S23)^(Assumptions!$D$16+1) -> 97528.917 | S23: =Assumptions!G213 -> 0.025
B24: =Assumptions!C233 -> Contract Services | E24: =G24/Beds -> 358.73919 | F24: =Assumptions!V233 -> 434497.1 | G24: =Assumptions!H233 -> 445359.53 | H24: =G24*(1+$S24) -> 456493.52 | I24: =H24*(1+$S24) -> 467905.86 | J24: =I24*(1+$S24) -> 479603.5 | K24: =J24*(1+$S24) -> 491593.59 | L24: =K24*(1+$S24) -> 503883.43 | M24: =L24*(1+$S24) -> 516480.52 | N24: =M24*(1+$S24) -> 529392.53 | O24: =N24*(1+$S24) -> 542627.34 | Q24: =+Assumptions!H233/(1+S24)^(Assumptions!$D$16+1) -> 403473.75 | S24: =Assumptions!G233 -> 0.025 | U24: Net Utility Expense Per Bed
B25: =Assumptions!C243 -> Turnover | E25: =G25/Beds -> 148.74983 | F25: =Assumptions!V243 -> 180162.55 | G25: =Assumptions!H243 -> 184666.62 | H25: =G25*(1+$S25) -> 189283.28 | I25: =H25*(1+$S25) -> 194015.36 | J25: =I25*(1+$S25) -> 198865.75 | K25: =J25*(1+$S25) -> 203837.39 | L25: =K25*(1+$S25) -> 208933.33 | M25: =L25*(1+$S25) -> 214156.66 | N25: =M25*(1+$S25) -> 219510.58 | O25: =N25*(1+$S25) -> 224998.34 | Q25: =+Assumptions!H243/(1+S25)^(Assumptions!$D$16+1) -> 167298.84 | S25: =Assumptions!G243 -> 0.025 | U25: =($Q$27-$Q$9)/Beds -> 570.00821
A26: NON-CONTROLLABLE OPERATING EXPENSES
B27: =Assumptions!C255 -> Utilities | E27: =G27/Beds -> 1130.3044 | F27: =Assumptions!V255 -> 1095016.8 | G27: =Assumptions!H255 -> 1403225.1 | H27: =G27*(1+$S27) -> 1438305.7 | I27: =H27*(1+$S27) -> 1474263.4 | J27: =I27*(1+$S27) -> 1511120 | K27: =J27*(1+$S27) -> 1548898 | L27: =K27*(1+$S27) -> 1587620.4 | M27: =L27*(1+$S27) -> 1627310.9 | N27: =M27*(1+$S27) -> 1667993.7 | O27: =N27*(1+$S27) -> 1709693.5 | Q27: =+Assumptions!H255/(1+S27)^(Assumptions!$D$16+1) -> 1271252.7 | S27: =Assumptions!G255 -> 0.025
B28: =Assumptions!C128 -> Ground Lease | E28: =G28/Beds -> 189.2936 | F28: =Assumptions!V128 -> 235000 | G28: =+F28 -> 235000 | H28: =+G28 -> 235000 | I28: =+H28 -> 235000 | J28: =+I28 -> 235000 | K28: =J28*(1+S28*5) -> 258500 | L28: =+K28 -> 258500 | M28: =+L28 -> 258500 | N28: =+M28 -> 258500 | O28: =+N28 -> 258500 | Q28: =+Assumptions!H128/(1+S28)^(Assumptions!$D$16+1) -> 221445.75 | S28: =Assumptions!G128 -> 0.02
B29: =Assumptions!C129 -> Property Taxes | E29: =G29/Beds -> 1986.8632 | F29: =Assumptions!V129 -> 2406445.5 | G29: =Assumptions!H129 -> 2466606.6 | H29: =G29*(1+$S29) -> 2528271.8 | I29: =H29*(1+$S29) -> 2591478.6 | J29: =I29*(1+$S29) -> 2656265.6 | K29: =J29*(1+$S29) -> 2722672.2 | L29: =K29*(1+$S29) -> 2790739 | M29: =L29*(1+$S29) -> 2860507.5 | N29: =M29*(1+$S29) -> 2932020.2 | O29: =N29*(1+$S29) -> 3005320.7 | Q29: =+Assumptions!H129/(1+S29)^(Assumptions!$D$16+1) -> 2234623.9 | S29: =Assumptions!G129 -> 0.025
B30: =Assumptions!C130 -> Tax Abatement | E30: =G30/Beds -> 0 | F30: =+'Sale Proceeds'!D20 -> 0 | G30: =+'Sale Proceeds'!E20 -> 0 | H30: =+'Sale Proceeds'!F20 -> 0 | I30: =+'Sale Proceeds'!G20 -> 0 | J30: =+'Sale Proceeds'!H20 -> 0 | K30: =+'Sale Proceeds'!I20 -> 0 | L30: =+'Sale Proceeds'!J20 -> 0 | M30: =+'Sale Proceeds'!K20 -> 0 | ... O30: =+'Sale Proceeds'!M20 -> 0 | Q30: =IF(F30<0,-Q29*'Sale Proceeds'!D15,0) -> 0
B31: =Assumptions!C131 -> Insurance | E31: =G31/Beds -> 386.33451 | F31: =Assumptions!V131 -> 467919.96 | G31: =Assumptions!H131 -> 479617.96 | H31: =G31*(1+$S31) -> 491608.41 | I31: =H31*(1+$S31) -> 503898.62 | J31: =I31*(1+$S31) -> 516496.08 | K31: =J31*(1+$S31) -> 529408.48 | L31: =K31*(1+$S31) -> 542643.7 | M31: =L31*(1+$S31) -> 556209.79 | N31: =M31*(1+$S31) -> 570115.03 | O31: =N31*(1+$S31) -> 584367.91 | Q31: =+Assumptions!H131/(1+S31)^(Assumptions!$D$16+1) -> 434510.2 | S31: =Assumptions!G131 -> 0.025
B32: =Assumptions!C257 -> Management Fees | D32: =Assumptions!D257 -> 0.03 | E32: =G32/Beds -> 672.79078 | F32: =Assumptions!V257 -> 679110.02 | G32: =G17*$S$32 -> 835241.3 | H32: =H17*$S$32 -> 860244.39 | I32: =I17*$S$32 -> 885997.56 | J32: =J17*$S$32 -> 912523.3 | K32: =K17*$S$32 -> 939844.78 | L32: =L17*$S$32 -> 967985.89 | M32: =M17*$S$32 -> 996971.2 | N32: =N17*$S$32 -> 1026826 | O32: =O17*$S$32 -> 1057576.5 | Q32: =Q17*$S$32 -> 742121.82 | S32: =Assumptions!D257 -> 0.03
B34: Total Commercial Operating Expenses | E34: =G34/Beds -> 5.8769622 | F34: =Assumptions!V270 -> 7296 | G34: =Assumptions!H270 -> 7296 | H34: =G34*(1+$S34) -> 7478.4 | I34: =H34*(1+$S34) -> 7665.36 | J34: =I34*(1+$S34) -> 7856.994 | K34: =J34*(1+$S34) -> 8053.4188 | L34: =K34*(1+$S34) -> 8254.7543 | M34: =L34*(1+$S34) -> 8461.1232 | N34: =M34*(1+$S34) -> 8672.6513 | O34: =N34*(1+$S34) -> 8889.4675 | Q34: =Assumptions!H270 -> 7296 | S34: =Assumptions!G265 -> 0.025
A36: TOTAL OPERATING EXPENSES | E36: =G36/Beds -> 6258.8179 | F36: =SUM(F20:F35) -> 7176711 | G36: =SUM(G20:G35) -> 7770057.7 | H36: =SUM(H20:H35) -> 7962556.3 | I36: =SUM(I20:I35) -> 8159992.2 | J36: =SUM(J20:J35) -> 8362492.8 | K36: =SUM(K20:K35) -> 8593688.5 | L36: =SUM(L20:L35) -> 8806713.2 | M36: =SUM(M20:M35) -> 9025204.2 | ... O36: =SUM(O20:O35) -> 9479152.3 | Q36: =SUM(Q20:Q35) -> 7033956.8
A38: NET OPERATING INCOME | E38: =G38/Beds -> 16167.541 | F38: =F17-F36 -> 15460290 | G38: =G17-G36 -> 20071319 | H38: =H17-H36 -> 20712257 | I38: =I17-I36 -> 21373260 | J38: =J17-J36 -> 22054950 | K38: =K17-K36 -> 22734471 | L38: =L17-L36 -> 23459483 | M38: =M17-M36 -> 24207169 | ... O38: =O17-O36 -> 25773398 | Q38: =Q17-Q36 -> 17703437
A40: CAPITAL
B41: Commercial Capital Reserves | E41: =G41/Beds -> 0 | F41: =Assumptions!V277 -> 0 | G41: =Assumptions!H277 -> 0 | H41: =G41*(1+$S41) -> 0 | I41: =H41*(1+$S41) -> 0 | J41: =I41*(1+$S41) -> 0 | K41: =J41*(1+$S41) -> 0 | L41: =K41*(1+$S41) -> 0 | M41: =L41*(1+$S41) -> 0 | N41: =M41*(1+$S41) -> 0 | O41: =N41*(1+$S41) -> 0 | Q41: =+Assumptions!H277/(1+S41)^(Assumptions!$D$16+1) -> 0 | R41: =+Q41*(1+S41)^4 -> 0 | S41: =Assumptions!G277 -> 0.03
B42: Residential Capital Reserve | E42: =G42/Beds -> 140.6886 | F42: =Assumptions!V281 -> 169571.79 | G42: =Assumptions!H281 -> 174658.95 | H42: =G42*(1+$S42) -> 179898.72 | I42: =H42*(1+$S42) -> 185295.68 | J42: =I42*(1+$S42) -> 190854.55 | K42: =J42*(1+$S42) -> 196580.18 | L42: =K42*(1+$S42) -> 202477.59 | M42: =L42*(1+$S42) -> 208551.92 | N42: =M42*(1+$S42) -> 214808.48 | O42: =N42*(1+$S42) -> 221252.73 | Q42: =+Assumptions!H281/(1+S42)^(Assumptions!$D$16+1) -> 155182.21 | R42: =+Q42*(1+S42)^4 -> 174658.95 | S42: =Assumptions!G281 -> 0.03
A43: TOTAL CAPITAL | E43: =G43/Beds -> 140.6886 | F43: =SUM(F41:F42) -> 169571.79 | G43: =SUM(G41:G42) -> 174658.95 | H43: =SUM(H41:H42) -> 179898.72 | I43: =SUM(I41:I42) -> 185295.68 | J43: =SUM(J41:J42) -> 190854.55 | K43: =SUM(K41:K42) -> 196580.18 | L43: =SUM(L41:L42) -> 202477.59 | M43: =SUM(M41:M42) -> 208551.92 | ... O43: =SUM(O41:O42) -> 221252.73 | Q43: =SUM(Q41:Q42) -> 155182.21
A45: NET OPERATING INCOME (LESS RESERVES) | E45: =G45/Beds -> 16026.853 | F45: =F38-F43 -> 15290718 | G45: =G38-G43 -> 19896660 | H45: =H38-H43 -> 20532358 | I45: =I38-I43 -> 21187964 | J45: =J38-J43 -> 21864096 | K45: =K38-K43 -> 22537891 | L45: =L38-L43 -> 23257005 | M45: =M38-M43 -> 23998617 | ... O45: =O38-O43 -> 25552145 | Q45: =Q38-Q43 -> 17548255
C46: RETURN ON COST | F46: =(F$45+F$30)/'Development Summary'!$I$36 -> 0.063990223 | G46: =(G$45+G$30)/'Development Summary'!$I$36 -> 0.083265659 | H46: =(H$45+H$30)/'Development Summary'!$I$36 -> 0.085925997 | I46: =(I$45+I$30)/'Development Summary'!$I$36 -> 0.088669646 | J46: =(J$45+J$30)/'Development Summary'!$I$36 -> 0.091499195 | K46: =(K$45+K$30)/'Development Summary'!$I$36 -> 0.094318963 | L46: =(L$45+L$30)/'Development Summary'!$I$36 -> 0.097328391 | M46: =(M$45+M$30)/'Development Summary'!$I$36 -> 0.10043197 | ... O46: =(O$45+O$30)/'Development Summary'!$I$36 -> 0.10693334 | Q46: =(Q$45+Q$30)/('Development Summary'!$I$36-7311231) -> 0.075755688
G47: ="*Stabilization of property reached in Yr. "&'Executive Summary'!$K$7 -> *Stabilization of property reached in Yr.
O49: Including Inflation | Q49: =(Q$45+Q$30)/('Development Summary'!$I$36) -> 0.073437805
O51: Excluding Design Contingency & Escalation | Q51: 0.078224655

Sheet Assumptions
B1: ='Executive Summary'!$E$5&" ASSUMPTIONS" -> VERVE Chapel Hill ASSUMPTIONS
C4: ASSUMPTIONS | F4: UNIT MIX
C5: Residential Assumptions | G5: Unit Name | H5: Unit Type | I5: Avg Unit SF | J5: Avg Bed SF | K5: Beds Per Unit | L5: Total # of Units | M5: Total # of Beds | N5: % of Total Units | O5: % of Total Beds | P5: Current Year Per Bed Input | Q5: Current Year Rent PSF | R5: Year 1 Rent/Bed | S5: Year 1 Rent/Unit | T5: Year 1 Rent PSF | U5: Total SF
C6: Units | D6: =+$L$37 -> 461.33501 | F6: =NOT(ISBLANK(K6))*OFFSET(F6,-1,0)+1 -> 1 | G6: S1 | H6: STUDIO | I6: 414 | J6: =IFERROR((I6/K6),"") -> 414 | K6: =IFERROR(IF(H6="Studio",1,LEFT(H6,1)),"") -> 1 | L6: 14.669417 | M6: =IFERROR(L6*K6,"") -> 14.669417 | N6: =IFERROR($L6/$L$22,"") -> 0.031797753 | O6: =IFERROR($M6/$M$22,"") -> 0.011816284 | P6: 1925 | Q6: =+IFERROR((P6*K6)/I6,"") -> 4.6497585 | R6: =IFERROR(P6*(1+$D$17)*(1+$D$18)*(1+$D$19),"") -> 2103.4995 | S6: =IFERROR(P6*K6*(1+$D$17)*(1+$D$18)*(1+$D$19),"") -> 2103.4995 | T6: =IFERROR(S6/I6,0) -> 5.0809166 | U6: =IFERROR(I6*L6,"") -> 6073.1385
C7: Beds | D7: =+$M$37 -> 1241.4577 | F7: =NOT(ISBLANK(K7))*OFFSET(F7,-1,0)+1 -> 2 | G7: S1 AFF | H7: STUDIO | I7: 414 | J7: =IFERROR((I7/K7),"") -> 414 | K7: =IFERROR(IF(H7="Studio",1,LEFT(H7,1)),"") -> 1 | L7: 13.84005 | M7: =IFERROR(L7*K7,"") -> 13.84005 | N7: =IFERROR($L7/$L$22,"") -> 0.03 | O7: =IFERROR($M7/$M$22,"") -> 0.011148225 | P7: 1215 | Q7: =+IFERROR((P7*K7)/I7,"") -> 2.9347826 | R7: =IFERROR(P7*(1+$D$17)*(1+$D$18)*(1+$D$19),"") -> 1327.6633 | S7: =IFERROR(P7*K7*(1+$D$17)*(1+$D$18)*(1+$D$19),"") -> 1327.6633 | T7: =IFERROR(S7/I7,0) -> 3.2069162 | U7: =IFERROR(I7*L7,"") -> 5729.7809
C8: Residential Vacancy (YR 1) | D8: 0.2 | F8: =NOT(ISBLANK(K8))*OFFSET(F8,-1,0)+1 -> 3 | G8: A1 | H8: 1BR/1BA | I8: 500 | J8: =IFERROR((I8/K8),"") -> 500 | K8: =IFERROR(IF(H8="Studio",1,LEFT(H8,1)),"") -> 1 | L8: 56.137733 | M8: =IFERROR(L8*K8,"") -> 56.137733 | N8: =IFERROR($L8/$L$22,"") -> 0.12168539 | O8: =IFERROR($M8/$M$22,"") -> 0.045219207 | P8: 2075 | Q8: =+IFERROR((P8*K8)/I8,"") -> 4.15 | R8: =IFERROR(P8*(1+$D$17)*(1+$D$18)*(1+$D$19),"") -> 2267.4085 | S8: =IFERROR(P8*K8*(1+$D$17)*(1+$D$18)*(1+$D$19),"") -> 2267.4085 | T8: =IFERROR(S8/I8,0) -> 4.5348171 | U8: =IFERROR(I8*L8,"") -> 28068.866
C9: Residential Vacancy (YR 2) | D9: 0.05 | F9: =NOT(ISBLANK(K9))*OFFSET(F9,-1,0)+1 -> 4 | G9: A1 AFF | H9: 1BR/1BA | I9: 500 | J9: =IFERROR((I9/K9),"") -> 500 | K9: =IFERROR(IF(H9="Studio",1,LEFT(H9,1)),"") -> 1 | L9: 13.84005 | M9: =IFERROR(L9*K9,"") -> 13.84005 | N9: =IFERROR($L9/$L$22,"") -> 0.03 | O9: =IFERROR($M9/$M$22,"") -> 0.011148225 | P9: 1301 | Q9: =+IFERROR((P9*K9)/I9,"") -> 2.602 | R9: =IFERROR(P9*(1+$D$17)*(1+$D$18)*(1+$D$19),"") -> 1421.6378 | S9: =IFERROR(P9*K9*(1+$D$17)*(1+$D$18)*(1+$D$19),"") -> 1421.6378 | T9: =IFERROR(S9/I9,0) -> 2.8432757 | U9: =IFERROR(I9*L9,"") -> 6920.0252
C10: Max Leased Units (YR 1) | D10: =ROUNDDOWN($D$6*(1-$D$8),0) -> 369 | F10: =NOT(ISBLANK(K10))*OFFSET(F10,-1,0)+1 -> 5 | G10: B1 | H10: 2BR/2BA | I10: 750 | J10: =IFERROR((I10/K10),"") -> 375 | K10: =IFERROR(IF(H10="Studio",1,LEFT(H10,1)),"") -> 2 | L10: 102.78959 | M10: =IFERROR(L10*K10,"") -> 205.57918 | N10: =IFERROR($L10/$L$22,"") -> 0.22280899 | O10: =IFERROR($M10/$M$22,"") -> 0.16559499 | P10: 1675 | Q10: =+IFERROR((P10*K10)/I10,"") -> 4.4666667 | R10: =IFERROR(P10*(1+$D$17)*(1+$D$18)*(1+$D$19),"") -> 1830.3177 | S10: =IFERROR(P10*K10*(1+$D$17)*(1+$D$18)*(1+$D$19),"") -> 3660.6354 | T10: =IFERROR(S10/I10,0) -> 4.8808473 | U10: =IFERROR(I10*L10,"") -> 77092.191
C11: Max Leased Units (YR 2) | D11: =ROUNDDOWN($D$6*(1-$D$9),0) -> 438 | F11: 6 | G11: B1 AFF | H11: 2BR/2BA | I11: 750 | J11: =IFERROR((I11/K11),"") -> 375 | K11: =IFERROR(IF(H11="Studio",1,LEFT(H11,1)),"") -> 2 | L11: 13.84005 | M11: =IFERROR(L11*K11,"") -> 27.680101 | N11: =IFERROR($L11/$L$22,"") -> 0.03 | O11: =IFERROR($M11/$M$22,"") -> 0.022296451 | P11: 846 | Q11: =+IFERROR((P11*K11)/I11,"") -> 2.256 | R11: =IFERROR(P11*(1+$D$17)*(1+$D$18)*(1+$D$19),"") -> 924.44704 | S11: =IFERROR(P11*K11*(1+$D$17)*(1+$D$18)*(1+$D$19),"") -> 1848.8941 | T11: =IFERROR(S11/I11,0) -> 2.4651921 | U11: =IFERROR(I11*L11,"") -> 10380.038
C12: Max Leased Beds (YR 1) | D12: =ROUNDDOWN($D$7*(1-$D$8),0) -> 993 | F12: 7 | G12: C1 | H12: 3BR/3BA | I12: 1050 | J12: =IFERROR((I12/K12),"") -> 350 | K12: =IFERROR(IF(H12="Studio",1,LEFT(H12,1)),"") -> 3 | L12: 70.547972 | M12: =IFERROR(L12*K12,"") -> 211.64392 | N12: =IFERROR($L12/$L$22,"") -> 0.15292135 | O12: =IFERROR($M12/$M$22,"") -> 0.17048017 | P12: 1600 | Q12: =+IFERROR((P12*K12)/I12,"") -> 4.5714286 | R12: =IFERROR(P12*(1+$D$17)*(1+$D$18)*(1+$D$19),"") -> 1748.3632 | S12: =IFERROR(P12*K12*(1+$D$17)*(1+$D$18)*(1+$D$19),"") -> 5245.0896 | T12: =IFERROR(S12/I12,0) -> 4.9953234 | U12: =IFERROR(I12*L12,"") -> 74075.371
C13: Max Leased Beds (YR 2) | D13: =ROUNDDOWN($D$7*(1-$D$9),0) -> 1179 | F13: 8 | G13: C1 AFF | H13: 3BR/3BA | I13: 1050 | J13: =IFERROR((I13/K13),"") -> 350 | K13: =IFERROR(IF(H13="Studio",1,LEFT(H13,1)),"") -> 3 | L13: 4.6133501 | M13: =IFERROR(L13*K13,"") -> 13.84005 | N13: =IFERROR($L13/$L$22,"") -> 0.01 | O13: =IFERROR($M13/$M$22,"") -> 0.011148225 | P13: 651.33333 | Q13: =+IFERROR((P13*K13)/I13,"") -> 1.8609524 | R13: =IFERROR(P13*(1+$D$17)*(1+$D$18)*(1+$D$19),"") -> 711.72952 | S13: =IFERROR(P13*K13*(1+$D$17)*(1+$D$18)*(1+$D$19),"") -> 2135.1886 | T13: =IFERROR(S13/I13,0) -> 2.0335129 | U13: =IFERROR(I13*L13,"") -> 4844.0176
C14: Leasing Start | D14: =Development!$N$9 -> 32 | F14: 9 | G14: D1 | H14: 4BR/4BA | I14: 1260 | J14: =IFERROR((I14/K14),"") -> 315 | K14: =IFERROR(IF(H14="Studio",1,LEFT(H14,1)),"") -> 4 | L14: 171.0568 | M14: =IFERROR(L14*K14,"") -> 684.22721 | N14: =IFERROR($L14/$L$22,"") -> 0.37078652 | O14: =IFERROR($M14/$M$22,"") -> 0.55114823 | P14: 1550 | Q14: =+IFERROR((P14*K14)/I14,"") -> 4.9206349 | R14: =IFERROR(P14*(1+$D$17)*(1+$D$18)*(1+$D$19),"") -> 1693.7269 | S14: =IFERROR(P14*K14*(1+$D$17)*(1+$D$18)*(1+$D$19),"") -> 6774.9074 | T14: =IFERROR(S14/I14,0) -> 5.3769106 | U14: =IFERROR(I14*L14,"") -> 215531.57
C15: Residential Lease-Up Period (Year 1) | D15: 1
C16: Years Trending | D16: =+COUNTIF(D17:D19,">0%") -> 3
C17: Rent Trending - Year 1 | D17: 0.03
C18: Rent Trending - Year 2 | D18: 0.03
C19: Rent Trending - Year 3 | D19: 0.03
C20: OpEx Trending - All Years | D20: 0.025
C21: Residential Parking Spaces | D21: 624
C22: Residential Parking Rent / Space | D22: 175 | I22: =SUMPRODUCT(I$6:I$21,$L$6:$L$21)/$L22 -> 929.29213 | J22: =SUMPRODUCT(J$6:J$21,$M$6:$M$21)/$M22 -> 345.33194 | K22: =M22/L22 -> 2.6910112 | L22: =SUM(L6:L21) -> 461.33501 | M22: =SUM(M6:M21) -> 1241.4577 | N22: =$L22/$L$22 -> 1 | O22: =$L22/$L$22 -> 1 | P22: =SUMPRODUCT(P$6:P$21,$O$6:$O$21) -> 1575.1688 | Q22: =SUMPRODUCT(Q6:Q21,O6:O21) -> 4.6063697 | R22: =SUMPRODUCT(R$6:R$21,$O$6:$O$21) -> 1721.2294 | S22: =SUMPRODUCT(S$6:S$21,$L$6:$L$21)/$L22 -> 4631.8478 | T22: =IFERROR(S22/I22,0) -> 4.9842752 | U22: =+SUM(U6:U21) -> 428715 | AC22: Total Parking | AD22: 629
C23: Move-in Fee Concessions | D23: 0.3 | F23: UNIT MIX SUMMARY | AC23: Guest Spaces | AD23: 5
C24: Pet Rent | D24: =10%*(1-D9) -> 0.095 | AC24: Commercial Spaces | AD24: 0
C25: Non-Refundable Security Deposit | D25: 350 | F25: =OFFSET(F25,-1,0)+1 -> 1 | H25: STUDIO | I25: =SUMPRODUCT(I$6:I$14,$L$6:$L$14,--($H$6:$H$14=$H25))/$L25 -> 414 | J25: =SUMPRODUCT(J$6:J$14,$L$6:$L$14,--($H$6:$H$14=$H25))/$L25 -> 414 | K25: =SUMIF($H$6:$H$15,$H25,M$6:M$15)/SUMIF($H$6:$H$15,$H25,$L$6:$L$15) -> 1 | L25: =SUMIF($H$6:$H$15,H25,L$6:L$15) -> 28.509467 | M25: =SUMIF($H$6:$H$15,H25,M$6:M$15) -> 28.509467 | N25: =$L25/$L$37 -> 0.061797753 | O25: =$M25/$M$37 -> 0.022964509 | P25: =SUMPRODUCT(P$6:P$15,$L$6:$L$15,--($H$6:$H$15=H25))/$L25 -> 1580.3273 | Q25: =IFERROR((P25*K25)/I25,0) -> 3.8172156 | R25: {=SUMPRODUCT(R$6:R$15,$L$6:$L$15,--($H$6:$H$15=H25))/$L25} -> 1726.8663 | S25: =SUMPRODUCT(S$6:S$15,$L$6:$L$15,--($H$6:$H$15=H25))/$L25 -> 1726.8663 | T25: =IFERROR(S25/I25,0) -> 4.1711746 | U25: =+I25*L25 -> 11802.919 | AC25: Other Spaces
C26: Storage Assumptions | D26: 0 | F26: =OFFSET(F26,-1,0)+1 -> 2 | H26: 1BR/1BA | I26: =SUMPRODUCT(I$6:I$14,$L$6:$L$14,--($H$6:$H$14=$H26))/$L26 -> 500 | J26: =SUMPRODUCT(J$6:J$14,$L$6:$L$14,--($H$6:$H$14=$H26))/$L26 -> 500 | K26: =SUMIF($H$6:$H$15,$H26,M$6:M$15)/SUMIF($H$6:$H$15,$H26,$L$6:$L$15) -> 1 | L26: =SUMIF($H$6:$H$15,H26,L$6:L$15) -> 69.977783 | M26: =SUMIF($H$6:$H$15,H26,M$6:M$15) -> 69.977783 | N26: =$L26/$L$37 -> 0.15168539 | O26: =$M26/$M$37 -> 0.056367432 | P26: =SUMPRODUCT(P$6:P$15,$L$6:$L$15,--($H$6:$H$15=H26))/$L26 -> 1921.92 | Q26: =IFERROR((P26*K26)/I26,0) -> 3.84384 | R26: {=SUMPRODUCT(R$6:R$15,$L$6:$L$15,--($H$6:$H$15=H26))/$L26} -> 2100.1339 | S26: =SUMPRODUCT(S$6:S$15,$L$6:$L$15,--($H$6:$H$15=H26))/$L26 -> 2100.1339 | T26: =IFERROR(S26/I26,0) -> 4.2002678 | U26: =+I26*L26 -> 34988.892 | AC26: Residential Spaces | AD26: =AD22-AD23-AD24-AD25 -> 624
C27: Half Height Lockers | D27: 35 | F27: =OFFSET(F27,-1,0)+1 -> 3 | H27: 2BR/2BA | I27: =SUMPRODUCT(I$6:I$14,$L$6:$L$14,--($H$6:$H$14=$H27))/$L27 -> 750 | J27: =SUMPRODUCT(J$6:J$14,$L$6:$L$14,--($H$6:$H$14=$H27))/$L27 -> 375 | K27: =SUMIF($H$6:$H$15,$H27,M$6:M$15)/SUMIF($H$6:$H$15,$H27,$L$6:$L$15) -> 2 | L27: =SUMIF($H$6:$H$15,H27,L$6:L$15) -> 116.62964 | M27: =SUMIF($H$6:$H$15,H27,M$6:M$15) -> 233.25928 | N27: =$L27/$L$37 -> 0.25280899 | O27: =$M27/$M$37 -> 0.18789144 | P27: =SUMPRODUCT(P$6:P$15,$L$6:$L$15,--($H$6:$H$15=H27))/$L27 -> 1576.6253 | Q27: =IFERROR((P27*K27)/I27,0) -> 4.2043342 | R27: {=SUMPRODUCT(R$6:R$15,$L$6:$L$15,--($H$6:$H$15=H27))/$L27} -> 1722.8211 | S27: =SUMPRODUCT(S$6:S$15,$L$6:$L$15,--($H$6:$H$15=H27))/$L27 -> 3445.6421 | T27: =IFERROR(S27/I27,0) -> 4.5941895 | U27: =+I27*L27 -> 87472.229
C28: Full Height Lockers | D28: 75 | F28: =OFFSET(F28,-1,0)+1 -> 4 | H28: 3BR/3BA | I28: =SUMPRODUCT(I$6:I$14,$L$6:$L$14,--($H$6:$H$14=$H28))/$L28 -> 1050 | J28: =SUMPRODUCT(J$6:J$14,$L$6:$L$14,--($H$6:$H$14=$H28))/$L28 -> 350 | K28: =SUMIF($H$6:$H$15,$H28,M$6:M$15)/SUMIF($H$6:$H$15,$H28,$L$6:$L$15) -> 3 | L28: =SUMIF($H$6:$H$15,H28,L$6:L$15) -> 75.161322 | M28: =SUMIF($H$6:$H$15,H28,M$6:M$15) -> 225.48397 | N28: =$L28/$L$37 -> 0.16292135 | O28: =$M28/$M$37 -> 0.18162839 | P28: =SUMPRODUCT(P$6:P$15,$L$6:$L$15,--($H$6:$H$15=H28))/$L28 -> 1541.7715 | Q28: =IFERROR((P28*K28)/I28,0) -> 4.4050614 | R28: {=SUMPRODUCT(R$6:R$15,$L$6:$L$15,--($H$6:$H$15=H28))/$L28} -> 1684.7353 | S28: =SUMPRODUCT(S$6:S$15,$L$6:$L$15,--($H$6:$H$15=H28))/$L28 -> 5054.206 | T28: =IFERROR(S28/I28,0) -> 4.8135295 | U28: =+I28*L28 -> 78919.389
C29: Annual Renewal | D29: 0.3 | F29: 5 | H29: 4BR/4BA | I29: {=SUMPRODUCT(I$6:I$15,$L$6:$L$15,--($H$6:$H$15=$H29))/$L29} -> 1260 | J29: {=SUMPRODUCT(J$6:J$15,$L$6:$L$15,--($H$6:$H$15=$H29))/$L29} -> 315 | K29: =SUMIF($H$6:$H$15,$H29,M$6:M$15)/SUMIF($H$6:$H$15,$H29,$L$6:$L$15) -> 4 | L29: =SUMIF($H$6:$H$15,H29,L$6:L$15) -> 171.0568 | M29: =SUMIF($H$6:$H$15,H29,M$6:M$15) -> 684.22721 | N29: =$L29/$L$37 -> 0.37078652 | O29: =$M29/$M$37 -> 0.55114823 | P29: =SUMPRODUCT(P$6:P$15,$L$6:$L$15,--($H$6:$H$15=H29))/$L29 -> 1550 | Q29: =IFERROR((P29*K29)/I29,0) -> 4.9206349 | R29: {=SUMPRODUCT(R$6:R$15,$L$6:$L$15,--($H$6:$H$15=H29))/$L29} -> 1693.7269 | S29: =SUMPRODUCT(S$6:S$15,$L$6:$L$15,--($H$6:$H$15=H29))/$L29 -> 6774.9074 | T29: =IFERROR(S29/I29,0) -> 5.3769106 | U29: =+I29*L29 -> 215531.57
C30: Premium Units | D30: 0.1
C31: (Per Month - Per Bed) | D31: 100
F34: =IF((ISBLANK(H34))," ",OFFSET(F34,-1,0)+1)
C35: Commercial Assumptions | F35: =IF((ISBLANK(H35))," ",OFFSET(F35,-1,0)+1)
C36: Commercial Leasing Start | D36: 4 | F36: =IF((ISBLANK(H36))," ",OFFSET(F36,-1,0)+1) | I36: {=IFERROR(SUMPRODUCT(I$6:I$20,$L$6:$L$20,--($H$6:$H$20=$H36))/$L36,"")} | J36: {=IFERROR(SUMPRODUCT(J$6:J$20,$L$6:$L$20,--($H$6:$H$20=$H36))/$L36,"")} | K36: =IFERROR(SUMIF($H$6:$H$21,$H36,M$6:M$21)/SUMIF($H$6:$H$21,$H36,$L$6:$L$21),"") | L36: =IF(ISBLANK(H36)," ",(IFERROR(SUMIF($H$6:$H$21,H36,L$6:L$21),""))) | M36: =IF(ISBLANK(H36)," ",(IFERROR(SUMIF($H$6:$H$21,H36,M$6:M$21),""))) | N36: =IFERROR($L36/$L$37,"") | O36: =IFERROR($M36/$M$37,"") | P36: {=IFERROR(SUMPRODUCT(P$6:P$21,$L$6:$L$21,--($H$6:$H$21=H36))/$L36,"")} | Q36: =IF(ISBLANK(H36)," ",(IFERROR((P36*K36)/I36,0))) | R36: {=IFERROR(SUMPRODUCT(R$6:R$21,$L$6:$L$21,--($H$6:$H$21=H36))/$L36,"")} | S36: {=IFERROR(SUMPRODUCT(S$6:S$21,$L$6:$L$21,--($H$6:$H$21=H36))/$L36,"")} | T36: =IF(ISBLANK(H36)," ",IFERROR(S36/I36,0)) | U36: =IFERROR(I36*L36,"")
C37: Commercial Vacancy | D37: 0.1 | F37: =MAX(F23:F36) -> 5 | I37: =SUMPRODUCT(I$24:I$36,$L$24:$L$36)/$L37 -> 929.29213 | J37: =SUMPRODUCT(J$24:J$36,$M$24:$M$36)/$M37 -> 345.33194 | K37: =M37/L37 -> 2.6910112 | L37: =IFERROR(SUM(L$24:L$36),"") -> 461.33501 | M37: =IFERROR(SUM(M$24:M$36),"") -> 1241.4577 | N37: =$L37/$L$37 -> 1 | O37: =$L37/$L$37 -> 1 | P37: =IFERROR(SUMPRODUCT(P$24:P$36,$O$24:$O$36),"") -> 1575.1688 | Q37: =IFERROR(SUMPRODUCT(Q24:Q36,O24:O36),"") -> 4.6063697 | R37: =IFERROR(SUMPRODUCT(R$24:R$36,$O$24:$O$36),"") -> 1721.2294 | S37: =IFERROR(SUMPRODUCT(S$24:S$36,$L$24:$L$36)/$L37,0) -> 4631.8478 | T37: =IFERROR(S37/I37,0) -> 4.9842752 | U37: =+SUM(U24:U36) -> 428715
C38: CAM Reimbursement | D38: 0.85
C39: Commercial Parking Spaces | D39: =+$X$24 -> 0
C40: Commercial Parking Rent / Space | D40: 0 | F40: COMMERCIAL UNITS
G41: Suite | H41: Tenant Name | I41: Total SF | J41: Mix | K41: Duration (Years) | L41: Rent/ SF/ YR | M41: Current Rent/Yr | N41: Year 1 Rent/Yr | O41: TI (PSF) | P41: LC (%)
C42: Utility Assumptions
C43: Water & Sewer Recapture | D43: 0 | F43: =OFFSET(F43,-1,0)+1 -> 1 | G43: Retail | H43: TBD | I43: 1824 | J43: =IFERROR(I43/$I$45,0) -> 1 | K43: 10 | L43: 32 | M43: =L43*I43 -> 58368 | N43: =M43*(1+$D$17)*(1+$D$18)*(1+$D$19) -> 63780.29 | O43: 75 | P43: =6%+3% -> 0.09
C44: Electric Recapture | D44: 0.95
C45: Gas Recapture | D45: 0 | F45: =+MAX(F42:F44) -> 1 | I45: =SUM(I42:I44) -> 1824 | L45: =IFERROR(M45/I45,0) -> 32 | M45: =SUM(M42:M44) -> 58368 | N45: =SUM(N42:N44) -> 63780.29 | O45: =IFERROR(SUMPRODUCT(O42:O44,$I42:$I44)/$I45,0) -> 75 | P45: =IFERROR(SUMPRODUCT(P42:P44,M42:M44)/M45,0) -> 0.09
H49: YEAR 2 | I49: 0 | J49: 1 | K49: =+J49+1 -> 2 | L49: =+K49+1 -> 3 | M49: =+L49+1 -> 4 | N49: =+M49+1 -> 5 | O49: =+N49+1 -> 6 | P49: =+O49+1 -> 7 | Q49: =+P49+1 -> 8 | R49: =+Q49+1 -> 9 | ... U49: =+T49+1 -> 12 | V49: TOTAL
H50: GROSS POTENTIAL | I50: 1 | J50: 1 | K50: 1 | L50: 1 | M50: 1 | N50: 1 | O50: 1 | P50: 1 | Q50: 1 | R50: 1 | S50: 1 | T50: 1 | U50: 1 | V50: INTERIM INCOME
I51: =EOMONTH(StartDate-1,$D$14-1) -> 47695 | J51: =+I52+1 -> 47696 | K51: =+J52+1 -> 47727 | L51: =+K52+1 -> 47757 | M51: =+L52+1 -> 47788 | N51: =+M52+1 -> 47818 | O51: =+N52+1 -> 47849 | P51: =+O52+1 -> 47880 | Q51: =+P52+1 -> 47908 | ... U51: =+T52+1 -> 48030
I52: =EOMONTH(StartDate-1,$D$14-1) -> 47695 | J52: =EOMONTH(J51,0) -> 47726 | K52: =EOMONTH(K51,0) -> 47756 | L52: =EOMONTH(L51,0) -> 47787 | M52: =EOMONTH(M51,0) -> 47817 | N52: =EOMONTH(N51,0) -> 47848 | O52: =EOMONTH(O51,0) -> 47879 | P52: =EOMONTH(P51,0) -> 47907 | Q52: =EOMONTH(Q51,0) -> 47938 | ... U52: =EOMONTH(U51,0) -> 48060
B53: EFFECTIVE GROSS REVENUE
C54: Units Leased | I54: =D10 -> 369 | J54: =IF(J$49<=($D$15-2),ROUNDUP($D$10/$D$15,0),IF(J$49=($D$15-1),$D$10-SUM($G$56:I$56),0)) -> 0 | K54: =IF(K$49<=($D$15-2),ROUNDUP($D$10/$D$15,0),IF(K$49=($D$15-1),$D$10-SUM($G$56:J$56),0)) -> 0 | L54: =IF(L$49<=($D$15-2),ROUNDUP($D$10/$D$15,0),IF(L$49=($D$15-1),$D$10-SUM($G$56:K$56),0)) -> 0 | M54: =IF(M$49<=($D$15-2),ROUNDUP($D$10/$D$15,0),IF(M$49=($D$15-1),$D$10-SUM($G$56:L$56),0)) -> 0 | N54: =IF(N$49<=($D$15-2),ROUNDUP($D$10/$D$15,0),IF(N$49=($D$15-1),$D$10-SUM($G$56:M$56),0)) -> 0 | O54: =IF(O$49<=($D$15-2),ROUNDUP($D$10/$D$15,0),IF(O$49=($D$15-1),$D$10-SUM($G$56:N$56),0)) -> 0 | P54: =IF(P$49<=($D$15-2),ROUNDUP($D$10/$D$15,0),IF(P$49=($D$15-1),$D$10-SUM($G$56:O$56),0)) -> 0 | Q54: =IF(Q$49<=($D$15-2),ROUNDUP($D$10/$D$15,0),IF(Q$49=($D$15-1),$D$10-SUM($G$56:P$56),0)) -> 0 | ... U54: =IF(U$49<=($D$15-2),ROUNDUP($D$10/$D$15,0),IF(U$49=($D$15-1),$D$10-SUM($G$56:T$56),0)) -> 0 | V54: =+SUM(I54:U54) -> 369
C55: Units Occupied | I55: 0 | J55: =+I54+I55 -> 369 | K55: =+J54+J55 -> 369 | L55: =+K54+K55 -> 369 | M55: =+L54+L55 -> 369 | N55: =+M54+M55 -> 369 | O55: =+N54+N55 -> 369 | P55: =+O54+O55 -> 369 | Q55: =+P54+P55 -> 369 | ... U55: =+T54+T55 -> 369
C56: Beds Leased | I56: =ROUNDDOWN($D$7*(1-$D$8),0) -> 993 | J56: =IF(J$49<=($D$15-2),ROUNDUP($D$10/$D$15,0),IF(J$49=($D$15-1),$D$10-SUM($G$56:I$56),0)) -> 0 | K56: =IF(K$49<=($D$15-2),ROUNDUP($D$10/$D$15,0),IF(K$49=($D$15-1),$D$10-SUM($G$56:J$56),0)) -> 0 | L56: =IF(L$49<=($D$15-2),ROUNDUP($D$10/$D$15,0),IF(L$49=($D$15-1),$D$10-SUM($G$56:K$56),0)) -> 0 | M56: =IF(M$49<=($D$15-2),ROUNDUP($D$10/$D$15,0),IF(M$49=($D$15-1),$D$10-SUM($G$56:L$56),0)) -> 0 | N56: =IF(N$49<=($D$15-2),ROUNDUP($D$10/$D$15,0),IF(N$49=($D$15-1),$D$10-SUM($G$56:M$56),0)) -> 0 | O56: =IF(O$49<=($D$15-2),ROUNDUP($D$10/$D$15,0),IF(O$49=($D$15-1),$D$10-SUM($G$56:N$56),0)) -> 0 | P56: =IF(P$49<=($D$15-2),ROUNDUP($D$10/$D$15,0),IF(P$49=($D$15-1),$D$10-SUM($G$56:O$56),0)) -> 0 | Q56: =IF(Q$49<=($D$15-2),ROUNDUP($D$10/$D$15,0),IF(Q$49=($D$15-1),$D$10-SUM($G$56:P$56),0)) -> 0 | ... U56: =IF(U$49<=($D$15-2),ROUNDUP($D$10/$D$15,0),IF(U$49=($D$15-1),$D$10-SUM($G$56:T$56),0)) -> 0 | V56: =+SUM(I56:U56) -> 993
C57: Beds Occupied | I57: 0 | J57: =+I56+I57 -> 993 | K57: =+J56+J57 -> 993 | L57: =+K56+K57 -> 993 | M57: =+L56+L57 -> 993 | N57: =+M56+M57 -> 993 | O57: =+N56+N57 -> 993 | P57: =+O56+O57 -> 993 | Q57: =+P56+P57 -> 993 | ... U57: =+T56+T57 -> 993
C58: Residential Income | H58: =+($S$37)*Units*12*(1+$G$60) -> 26411263 | I58: 0 | J58: =+$D$7*$R$37 -> 2136833.6 | K58: =+$D$7*$R$37 -> 2136833.6 | L58: =+$D$7*$R$37 -> 2136833.6 | M58: =+$D$7*$R$37 -> 2136833.6 | N58: =+$D$7*$R$37 -> 2136833.6 | O58: =+$D$7*$R$37 -> 2136833.6 | P58: =+$D$7*$R$37 -> 2136833.6 | Q58: =+$D$7*$R$37 -> 2136833.6 | ... U58: =+$D$7*$R$37 -> 2136833.6 | V58: =+SUM(I58:U58) -> 25642003
C59: Premium Units | D59: =D30 -> 0.1 | H59: =+$D$30*Beds*$D$31*12*(1+$D$17)*(1+$D$18)*(1+$D$19)*(1+G104) -> 167672.59 | I59: 0 | J59: =$D$7*$D$30*$D$31*(1+$D$17)*(1+$D$18)*(1+$D$19) -> 13565.744 | K59: =$D$7*$D$30*$D$31*(1+$D$17)*(1+$D$18)*(1+$D$19) -> 13565.744 | L59: =$D$7*$D$30*$D$31*(1+$D$17)*(1+$D$18)*(1+$D$19) -> 13565.744 | M59: =$D$7*$D$30*$D$31*(1+$D$17)*(1+$D$18)*(1+$D$19) -> 13565.744 | N59: =$D$7*$D$30*$D$31*(1+$D$17)*(1+$D$18)*(1+$D$19) -> 13565.744 | O59: =$D$7*$D$30*$D$31*(1+$D$17)*(1+$D$18)*(1+$D$19) -> 13565.744 | P59: =$D$7*$D$30*$D$31*(1+$D$17)*(1+$D$18)*(1+$D$19) -> 13565.744 | Q59: =$D$7*$D$30*$D$31*(1+$D$17)*(1+$D$18)*(1+$D$19) -> 13565.744 | ... U59: =$D$7*$D$30*$D$31*(1+$D$17)*(1+$D$18)*(1+$D$19) -> 13565.744 | V59: =+SUM(I59:U59) -> 162788.92
C60: Gross Potential Rent | G60: 0.03 | H60: =SUM(H58:H59) -> 26578935 | I60: 0 | J60: =+SUM(J58:J59) -> 2150399.3 | K60: =+SUM(K58:K59) -> 2150399.3 | L60: =+SUM(L58:L59) -> 2150399.3 | M60: =+SUM(M58:M59) -> 2150399.3 | N60: =+SUM(N58:N59) -> 2150399.3 | O60: =+SUM(O58:O59) -> 2150399.3 | P60: =+SUM(P58:P59) -> 2150399.3 | Q60: =+SUM(Q58:Q59) -> 2150399.3 | ... U60: =+SUM(U58:U59) -> 2150399.3 | V60: =+SUM(I60:U60) -> 25804792
C61: General Vacancy Loss | G61: =D9 -> 0.05 | H61: =+-$H60*$G$61 -> -1328946.8 | I61: 0 | J61: =-J60*$D$8 -> -430079.86 | K61: =-K60*$D$8 -> -430079.86 | L61: =-L60*$D$8 -> -430079.86 | M61: =-M60*$D$8 -> -430079.86 | N61: =-N60*$D$8 -> -430079.86 | O61: =-O60*$D$8 -> -430079.86 | P61: =-P60*$D$8 -> -430079.86 | Q61: =-Q60*$D$8 -> -430079.86 | ... U61: =-U60*$D$8 -> -430079.86 | V61: =+SUM(I61:U61) -> -5160958.3
C62: Collection/ Bad Debt Expense | D62: Input as a % of Scheduled Rent before concessions | G62: 0.0075 | H62: =+-SUM(H60:H61)*$G$62 -> -189374.91 | I62: 0 | J62: =-SUM(J60:J61)*$G$62 -> -12902.396 | K62: =-SUM(K60:K61)*$G$62 -> -12902.396 | L62: =-SUM(L60:L61)*$G$62 -> -12902.396 | M62: =-SUM(M60:M61)*$G$62 -> -12902.396 | N62: =-SUM(N60:N61)*$G$62 -> -12902.396 | O62: =-SUM(O60:O61)*$G$62 -> -12902.396 | P62: =-SUM(P60:P61)*$G$62 -> -12902.396 | Q62: =-SUM(Q60:Q61)*$G$62 -> -12902.396 | ... U62: =-SUM(U60:U61)*$G$62 -> -12902.396 | V62: =+SUM(I62:U62) -> -154828.75
B63: Total Residential Revenues | H63: =+SUM(H60:H62 ) -> 25060614 | I63: 0 | J63: =+SUM(J60:J62 ) -> 1707417 | K63: =+SUM(K60:K62 ) -> 1707417 | L63: =+SUM(L60:L62 ) -> 1707417 | M63: =+SUM(M60:M62 ) -> 1707417 | N63: =+SUM(N60:N62 ) -> 1707417 | O63: =+SUM(O60:O62 ) -> 1707417 | P63: =+SUM(P60:P62 ) -> 1707417 | Q63: =+SUM(Q60:Q62 ) -> 1707417 | ... U63: =+SUM(U60:U62 ) -> 1707417 | V63: =+SUM(I63:U63) -> 20489005
B65: OTHER RESIDENTIAL REVENUES
C66: Parking Spaces Leased | I66: =IF(I$49<=($D$15-2),ROUND($D$21/$D$15,0),IF(I$49=($D$15-1),$D$21-SUM($G$66:H$66),0))*(1-$D$8) -> 499.2 | J66: =IF(J$49<=($D$15-2),ROUND($D$21/$D$15,0),IF(J$49=($D$15-1),$D$21-SUM($G$66:I$66),0)) -> 0 | K66: =IF(K$49<=($D$15-2),ROUND($D$21/$D$15,0),IF(K$49=($D$15-1),$D$21-SUM($G$66:J$66),0)) -> 0 | L66: =IF(L$49<=($D$15-2),ROUND($D$21/$D$15,0),IF(L$49=($D$15-1),$D$21-SUM($G$66:K$66),0)) -> 0 | M66: =IF(M$49<=($D$15-2),ROUND($D$21/$D$15,0),IF(M$49=($D$15-1),$D$21-SUM($G$66:L$66),0)) -> 0 | N66: =IF(N$49<=($D$15-2),ROUND($D$21/$D$15,0),IF(N$49=($D$15-1),$D$21-SUM($G$66:M$66),0)) -> 0 | O66: =IF(O$49<=($D$15-2),ROUND($D$21/$D$15,0),IF(O$49=($D$15-1),$D$21-SUM($G$66:N$66),0)) -> 0 | P66: =IF(P$49<=($D$15-2),ROUND($D$21/$D$15,0),IF(P$49=($D$15-1),$D$21-SUM($G$66:O$66),0)) -> 0 | Q66: =IF(Q$49<=($D$15-2),ROUND($D$21/$D$15,0),IF(Q$49=($D$15-1),$D$21-SUM($G$66:P$66),0)) -> 0 | ... U66: =IF(U$49<=($D$15-2),ROUND($D$21/$D$15,0),IF(U$49=($D$15-1),$D$21-SUM($G$66:T$66),0)) -> 0 | V66: =+SUM(I66:U66) -> 499.2
C67: Parking Spaces Occupied | I67: 0 | J67: =+I66+I67 -> 499.2 | K67: =+J66+J67 -> 499.2 | L67: =+K66+K67 -> 499.2 | M67: =+L66+L67 -> 499.2 | N67: =+M66+M67 -> 499.2 | O67: =+N66+N67 -> 499.2 | P67: =+O66+O67 -> 499.2 | Q67: =+P66+P67 -> 499.2 | ... U67: =+T66+T67 -> 499.2
C68: Parking Income | D68: =D22 -> 175 | E68: $ Amount | F68: Per Month | G68: 0.03 | H68: =+$D$21*$D68*12*(1+$G$68)*((1+$D$17)*(1+$D$18)*(1+$D$19)) -> 1474866.7 | I68: 0 | J68: =+J67*($D$22*((1+$D$17)*(1+$D$18)*(1+$D$19))) -> 95460.631 | K68: =+K67*($D$22*((1+$D$17)*(1+$D$18)*(1+$D$19))) -> 95460.631 | L68: =+L67*($D$22*((1+$D$17)*(1+$D$18)*(1+$D$19))) -> 95460.631 | M68: =+M67*($D$22*((1+$D$17)*(1+$D$18)*(1+$D$19))) -> 95460.631 | N68: =+N67*($D$22*((1+$D$17)*(1+$D$18)*(1+$D$19))) -> 95460.631 | O68: =+O67*($D$22*((1+$D$17)*(1+$D$18)*(1+$D$19))) -> 95460.631 | P68: =+P67*($D$22*((1+$D$17)*(1+$D$18)*(1+$D$19))) -> 95460.631 | Q68: =+Q67*($D$22*((1+$D$17)*(1+$D$18)*(1+$D$19))) -> 95460.631 | ... U68: =+U67*($D$22*((1+$D$17)*(1+$D$18)*(1+$D$19))) -> 95460.631 | V68: =+SUM(I68:U68) -> 1145527.6
I69: 0
C70: Recoveries - Util/Admin | D70: 68 | E70: $Amt/Bed | F70: Per Year | G70: 0.03 | H70: =+D70*Beds*(1+$D$17)*(1+$D$18)*(1+$D$19)*(1+G70) -> 95014.468 | I70: 0 | J70: =$D70*$D$12/12*(1+$D$17)*(1+$D$18)*(1+$D$19) -> 6148.7748 | K70: =$D70*$D$12/12*(1+$D$17)*(1+$D$18)*(1+$D$19) -> 6148.7748 | L70: =$D70*$D$12/12*(1+$D$17)*(1+$D$18)*(1+$D$19) -> 6148.7748 | M70: =$D70*$D$12/12*(1+$D$17)*(1+$D$18)*(1+$D$19) -> 6148.7748 | N70: =$D70*$D$12/12*(1+$D$17)*(1+$D$18)*(1+$D$19) -> 6148.7748 | O70: =$D70*$D$12/12*(1+$D$17)*(1+$D$18)*(1+$D$19) -> 6148.7748 | P70: =$D70*$D$12/12*(1+$D$17)*(1+$D$18)*(1+$D$19) -> 6148.7748 | Q70: =$D70*$D$12/12*(1+$D$17)*(1+$D$18)*(1+$D$19) -> 6148.7748 | ... U70: =$D70*$D$12/12*(1+$D$17)*(1+$D$18)*(1+$D$19) -> 6148.7748 | V70: =+SUM(I70:U70) -> 73785.298
C71: Recoveries - Water/Sewer | D71: =+$D$252*$D$43 -> 0 | E71: $Amt/Bed | F71: Per Year | G71: 0.025 | H71: =+D71*Beds*(1+G250)^($D$16+1) -> 0 | I71: 0 | J71: =+$D71*(1+$G71)^$D$16*$I$56/12 -> 0 | K71: =+$D71*(1+$G71)^$D$16*$I$56/12 -> 0 | L71: =+$D71*(1+$G71)^$D$16*$I$56/12 -> 0 | M71: =+$D71*(1+$G71)^$D$16*$I$56/12 -> 0 | N71: =+$D71*(1+$G71)^$D$16*$I$56/12 -> 0 | O71: =+$D71*(1+$G71)^$D$16*$I$56/12 -> 0 | P71: =+$D71*(1+$G71)^$D$16*$I$56/12 -> 0 | Q71: =+$D71*(1+$G71)^$D$16*$I$56/12 -> 0 | ... U71: =+$D71*(1+$G71)^$D$16*$I$56/12 -> 0 | V71: =+SUM(I71:U71) -> 0
C72: Recoveries - Electric | D72: =+$D$246*$D$44 -> 389.5 | E72: $Amt/Bed | F72: Per Year | G72: 0.025 | H72: =+D72*Beds*(1+G251)^($D$16+1) -> 533746.27 | I72: 0 | J72: =+$D72*(1+$G72)^$D$16*$I$56/12 -> 34709.396 | K72: =+$D72*(1+$G72)^$D$16*$I$56/12 -> 34709.396 | L72: =+$D72*(1+$G72)^$D$16*$I$56/12 -> 34709.396 | M72: =+$D72*(1+$G72)^$D$16*$I$56/12 -> 34709.396 | N72: =+$D72*(1+$G72)^$D$16*$I$56/12 -> 34709.396 | O72: =+$D72*(1+$G72)^$D$16*$I$56/12 -> 34709.396 | P72: =+$D72*(1+$G72)^$D$16*$I$56/12 -> 34709.396 | Q72: =+$D72*(1+$G72)^$D$16*$I$56/12 -> 34709.396 | ... U72: =+$D72*(1+$G72)^$D$16*$I$56/12 -> 34709.396 | V72: =+SUM(I72:U72) -> 416512.76
C73: Recoveries - Gas | D73: =+D248*D45 -> 0 | E73: $Amt/Bed | F73: Per Year | G73: 0.025 | H73: =+D73*Beds*(1+G252)^($D$16+1) -> 0 | I73: 0 | J73: =+$D73*(1+$G73)^$D$16*$I$56/12 -> 0 | K73: =+$D73*(1+$G73)^$D$16*$I$56/12 -> 0 | L73: =+$D73*(1+$G73)^$D$16*$I$56/12 -> 0 | M73: =+$D73*(1+$G73)^$D$16*$I$56/12 -> 0 | N73: =+$D73*(1+$G73)^$D$16*$I$56/12 -> 0 | O73: =+$D73*(1+$G73)^$D$16*$I$56/12 -> 0 | P73: =+$D73*(1+$G73)^$D$16*$I$56/12 -> 0 | Q73: =+$D73*(1+$G73)^$D$16*$I$56/12 -> 0 | ... U73: =+$D73*(1+$G73)^$D$16*$I$56/12 -> 0 | V73: =+SUM(I73:U73) -> 0
C74: Recoveries - Bulk Service | D74: 0 | E74: $Amt/Bed | F74: Per Year | G74: 0.03 | H74: =+D74*Beds*(1+$D$17)*(1+$D$18)*(1+$D$19)*(1+G74) -> 0 | I74: 0 | J74: =$D74*$D$12/12*(1+$D$17)*(1+$D$18)*(1+$D$19) -> 0 | K74: =$D74*$D$12/12*(1+$D$17)*(1+$D$18)*(1+$D$19) -> 0 | L74: =$D74*$D$12/12*(1+$D$17)*(1+$D$18)*(1+$D$19) -> 0 | M74: =$D74*$D$12/12*(1+$D$17)*(1+$D$18)*(1+$D$19) -> 0 | N74: =$D74*$D$12/12*(1+$D$17)*(1+$D$18)*(1+$D$19) -> 0 | O74: =$D74*$D$12/12*(1+$D$17)*(1+$D$18)*(1+$D$19) -> 0 | P74: =$D74*$D$12/12*(1+$D$17)*(1+$D$18)*(1+$D$19) -> 0 | Q74: =$D74*$D$12/12*(1+$D$17)*(1+$D$18)*(1+$D$19) -> 0 | ... U74: =$D74*$D$12/12*(1+$D$17)*(1+$D$18)*(1+$D$19) -> 0 | V74: =+SUM(I74:U74) -> 0
C75: Recoveries - Property Taxes | D75: 0 | E75: $Amt/Bed | F75: Per Year | G75: 0.03 | H75: =+D75*Beds*(1+$D$17)*(1+$D$18)*(1+$D$19)*(1+G75) -> 0 | I75: 0 | J75: =$D75*$D$12/12*(1+$D$17)*(1+$D$18)*(1+$D$19) -> 0 | K75: =$D75*$D$12/12*(1+$D$17)*(1+$D$18)*(1+$D$19) -> 0 | L75: =$D75*$D$12/12*(1+$D$17)*(1+$D$18)*(1+$D$19) -> 0 | M75: =$D75*$D$12/12*(1+$D$17)*(1+$D$18)*(1+$D$19) -> 0 | N75: =$D75*$D$12/12*(1+$D$17)*(1+$D$18)*(1+$D$19) -> 0 | O75: =$D75*$D$12/12*(1+$D$17)*(1+$D$18)*(1+$D$19) -> 0 | P75: =$D75*$D$12/12*(1+$D$17)*(1+$D$18)*(1+$D$19) -> 0 | Q75: =$D75*$D$12/12*(1+$D$17)*(1+$D$18)*(1+$D$19) -> 0 | ... U75: =$D75*$D$12/12*(1+$D$17)*(1+$D$18)*(1+$D$19) -> 0 | V75: =+SUM(I75:U75) -> 0
C76: Recoveries - Valet Waste | D76: 0 | E76: $Amt/Bed | F76: Per Year | G76: 0.03 | H76: =+D76*Beds*(1+$D$17)*(1+$D$18)*(1+$D$19)*(1+G76) -> 0 | I76: 0 | J76: =$D76*$D$12/12*(1+$D$17)*(1+$D$18)*(1+$D$19) -> 0 | K76: =$D76*$D$12/12*(1+$D$17)*(1+$D$18)*(1+$D$19) -> 0 | L76: =$D76*$D$12/12*(1+$D$17)*(1+$D$18)*(1+$D$19) -> 0 | M76: =$D76*$D$12/12*(1+$D$17)*(1+$D$18)*(1+$D$19) -> 0 | N76: =$D76*$D$12/12*(1+$D$17)*(1+$D$18)*(1+$D$19) -> 0 | O76: =$D76*$D$12/12*(1+$D$17)*(1+$D$18)*(1+$D$19) -> 0 | P76: =$D76*$D$12/12*(1+$D$17)*(1+$D$18)*(1+$D$19) -> 0 | Q76: =$D76*$D$12/12*(1+$D$17)*(1+$D$18)*(1+$D$19) -> 0 | ... U76: =$D76*$D$12/12*(1+$D$17)*(1+$D$18)*(1+$D$19) -> 0 | V76: =+SUM(I76:U76) -> 0
C77: Credit Reporting Recovery | D77: 4 | E77: $Amt/Bed | F77: Per Year | G77: 0.03 | H77: =+D77*Beds*(1+$D$17)*(1+$D$18)*(1+$D$19)*(1+G77) -> 5589.0863 | I77: 0 | J77: =$D77*$D$12/12*(1+$D$17)*(1+$D$18)*(1+$D$19) -> 361.69264 | K77: =$D77*$D$12/12*(1+$D$17)*(1+$D$18)*(1+$D$19) -> 361.69264 | L77: =$D77*$D$12/12*(1+$D$17)*(1+$D$18)*(1+$D$19) -> 361.69264 | M77: =$D77*$D$12/12*(1+$D$17)*(1+$D$18)*(1+$D$19) -> 361.69264 | N77: =$D77*$D$12/12*(1+$D$17)*(1+$D$18)*(1+$D$19) -> 361.69264 | O77: =$D77*$D$12/12*(1+$D$17)*(1+$D$18)*(1+$D$19) -> 361.69264 | P77: =$D77*$D$12/12*(1+$D$17)*(1+$D$18)*(1+$D$19) -> 361.69264 | Q77: =$D77*$D$12/12*(1+$D$17)*(1+$D$18)*(1+$D$19) -> 361.69264 | ... U77: =$D77*$D$12/12*(1+$D$17)*(1+$D$18)*(1+$D$19) -> 361.69264 | V77: =+SUM(I77:U77) -> 4340.3116
C78: Misc. Resident Fees | D78: 0 | E78: $Amt/Bed | F78: Per Year | G78: 0.03 | H78: =+D78*Beds*(1+$D$17)*(1+$D$18)*(1+$D$19)*(1+G78) -> 0 | I78: 0 | J78: =$D78*$D$12/12*(1+$D$17)*(1+$D$18)*(1+$D$19) -> 0 | K78: =$D78*$D$12/12*(1+$D$17)*(1+$D$18)*(1+$D$19) -> 0 | L78: =$D78*$D$12/12*(1+$D$17)*(1+$D$18)*(1+$D$19) -> 0 | M78: =$D78*$D$12/12*(1+$D$17)*(1+$D$18)*(1+$D$19) -> 0 | N78: =$D78*$D$12/12*(1+$D$17)*(1+$D$18)*(1+$D$19) -> 0 | O78: =$D78*$D$12/12*(1+$D$17)*(1+$D$18)*(1+$D$19) -> 0 | P78: =$D78*$D$12/12*(1+$D$17)*(1+$D$18)*(1+$D$19) -> 0 | Q78: =$D78*$D$12/12*(1+$D$17)*(1+$D$18)*(1+$D$19) -> 0 | ... U78: =$D78*$D$12/12*(1+$D$17)*(1+$D$18)*(1+$D$19) -> 0 | V78: =+SUM(I78:U78) -> 0
I79: 0
C80: Utility Income | D80: =+H80/Beds -> 510.97176 | E80: $Amt/Bed | F80: Per Year | G80: 0.03 | H80: =SUM(H70:H79) -> 634349.82 | I80: 0 | J80: =SUM(J70:J79) -> 41219.864 | K80: =SUM(K70:K79) -> 41219.864 | L80: =SUM(L70:L79) -> 41219.864 | M80: =SUM(M70:M79) -> 41219.864 | N80: =SUM(N70:N79) -> 41219.864 | O80: =SUM(O70:O79) -> 41219.864 | P80: =SUM(P70:P79) -> 41219.864 | Q80: =SUM(Q70:Q79) -> 41219.864 | ... U80: =SUM(U70:U79) -> 41219.864 | V80: =+SUM(I80:U80) -> 494638.37
C82: Administration Fees | D82: 93 | E82: $Amt/Bed | F82: Per Year | G82: 0.03 | H82: =+D82*Beds*(1+$D$17)*(1+$D$18)*(1+$D$19)*(1+G82) -> 129946.26 | I82: 0 | J82: =$D82*$D$12/12*(1+$D$17)*(1+$D$18)*(1+$D$19) -> 8409.3538 | K82: =$D82*$D$12/12*(1+$D$17)*(1+$D$18)*(1+$D$19) -> 8409.3538 | L82: =$D82*$D$12/12*(1+$D$17)*(1+$D$18)*(1+$D$19) -> 8409.3538 | M82: =$D82*$D$12/12*(1+$D$17)*(1+$D$18)*(1+$D$19) -> 8409.3538 | N82: =$D82*$D$12/12*(1+$D$17)*(1+$D$18)*(1+$D$19) -> 8409.3538 | O82: =$D82*$D$12/12*(1+$D$17)*(1+$D$18)*(1+$D$19) -> 8409.3538 | P82: =$D82*$D$12/12*(1+$D$17)*(1+$D$18)*(1+$D$19) -> 8409.3538 | Q82: =$D82*$D$12/12*(1+$D$17)*(1+$D$18)*(1+$D$19) -> 8409.3538 | ... U82: =$D82*$D$12/12*(1+$D$17)*(1+$D$18)*(1+$D$19) -> 8409.3538 | V82: =+SUM(I82:U82) -> 100912.25
C83: Application Fees | D83: 31 | E83: $Amt/Bed | F83: Per Year | G83: 0.03 | H83: =+D83*Beds*(1+$D$17)*(1+$D$18)*(1+$D$19)*(1+G83) -> 43315.419 | I83: 0 | J83: =$D83*$D$12/12*(1+$D$17)*(1+$D$18)*(1+$D$19) -> 2803.1179 | K83: =$D83*$D$12/12*(1+$D$17)*(1+$D$18)*(1+$D$19) -> 2803.1179 | L83: =$D83*$D$12/12*(1+$D$17)*(1+$D$18)*(1+$D$19) -> 2803.1179 | M83: =$D83*$D$12/12*(1+$D$17)*(1+$D$18)*(1+$D$19) -> 2803.1179 | N83: =$D83*$D$12/12*(1+$D$17)*(1+$D$18)*(1+$D$19) -> 2803.1179 | O83: =$D83*$D$12/12*(1+$D$17)*(1+$D$18)*(1+$D$19) -> 2803.1179 | P83: =$D83*$D$12/12*(1+$D$17)*(1+$D$18)*(1+$D$19) -> 2803.1179 | Q83: =$D83*$D$12/12*(1+$D$17)*(1+$D$18)*(1+$D$19) -> 2803.1179 | ... U83: =$D83*$D$12/12*(1+$D$17)*(1+$D$18)*(1+$D$19) -> 2803.1179 | V83: =+SUM(I83:U83) -> 33637.415
C84: Administration & Application Fees | D84: =+H84/Beds -> 139.56309 | E84: $Amt/Bed | F84: Per Year | G84: 0.03 | H84: =SUM(H82:H83) -> 173261.68 | I84: 0 | J84: =SUM(J82:J83) -> 11212.472 | K84: =SUM(K82:K83) -> 11212.472 | L84: =SUM(L82:L83) -> 11212.472 | M84: =SUM(M82:M83) -> 11212.472 | N84: =SUM(N82:N83) -> 11212.472 | O84: =SUM(O82:O83) -> 11212.472 | P84: =SUM(P82:P83) -> 11212.472 | Q84: =SUM(Q82:Q83) -> 11212.472 | ... U84: =SUM(U82:U83) -> 11212.472 | V84: =+SUM(I84:U84) -> 134549.66
C86: Pet Deposit (Non-Refundable) | D86: =+D25*D24 -> 33.25 | E86: $Amt/Bed | F86: Per Year | G86: 0.03 | H86: =+D86*(1-D29)*D13*(1+D17)*(1+D18)*(1+D19)*(1+G86) -> 30885.34 | I86: 0 | J86: =$D86*($D$12)*((1+$D$17)*(1+$D$18)*(1+$D$19)) -> 36078.841 | K86: =$D86*K$56 -> 0 | L86: =$D86*L$56 -> 0 | M86: =$D86*M$56 -> 0 | N86: =$D86*N$56 -> 0 | O86: =$D86*O$56 -> 0 | P86: =$D86*P$56 -> 0 | Q86: =$D86*Q$56 -> 0 | R86: =$D86*R$56 -> 0 | ... U86: =$D86*U$56 -> 0 | V86: =+SUM(I86:U86) -> 36078.841
C88: Storage Fees | D88: =+$D$26*0.5*SUM($D$27:$D$28)*12 -> 0 | E88: $Amt/Bed | F88: Per Year | G88: 0.03 | H88: =+D88*$D$13*(1+$D$17)*(1+$D$18)*(1+$D$19)*(1+G88) -> 0 | I88: 0 | J88: =+$D88*$D$12/12*(1+$D$17)*(1+$D$18)*(1+$D$19) -> 0 | K88: =+$D88*$D$12/12*(1+$D$17)*(1+$D$18)*(1+$D$19) -> 0 | L88: =+$D88*$D$12/12*(1+$D$17)*(1+$D$18)*(1+$D$19) -> 0 | M88: =+$D88*$D$12/12*(1+$D$17)*(1+$D$18)*(1+$D$19) -> 0 | N88: =+$D88*$D$12/12*(1+$D$17)*(1+$D$18)*(1+$D$19) -> 0 | O88: =+$D88*$D$12/12*(1+$D$17)*(1+$D$18)*(1+$D$19) -> 0 | P88: =+$D88*$D$12/12*(1+$D$17)*(1+$D$18)*(1+$D$19) -> 0 | Q88: =+$D88*$D$12/12*(1+$D$17)*(1+$D$18)*(1+$D$19) -> 0 | ... U88: =+$D88*$D$12/12*(1+$D$17)*(1+$D$18)*(1+$D$19) -> 0 | V88: =+SUM(I88:U88) -> 0
C89: Cancel / Termination Fees | D89: 2 | E89: $Amt/Bed | F89: Per Year | G89: 0.03 | H89: =+D89*$D$13*(1+$D$17)*(1+$D$18)*(1+$D$19)*(1+G89) -> 2653.9498 | I89: 0 | J89: =$D89*$D$12/12*(1+$D$17)*(1+$D$18)*(1+$D$19) -> 180.84632 | K89: =$D89*$D$12/12*(1+$D$17)*(1+$D$18)*(1+$D$19) -> 180.84632 | L89: =$D89*$D$12/12*(1+$D$17)*(1+$D$18)*(1+$D$19) -> 180.84632 | M89: =$D89*$D$12/12*(1+$D$17)*(1+$D$18)*(1+$D$19) -> 180.84632 | N89: =$D89*$D$12/12*(1+$D$17)*(1+$D$18)*(1+$D$19) -> 180.84632 | O89: =$D89*$D$12/12*(1+$D$17)*(1+$D$18)*(1+$D$19) -> 180.84632 | P89: =$D89*$D$12/12*(1+$D$17)*(1+$D$18)*(1+$D$19) -> 180.84632 | Q89: =$D89*$D$12/12*(1+$D$17)*(1+$D$18)*(1+$D$19) -> 180.84632 | ... U89: =$D89*$D$12/12*(1+$D$17)*(1+$D$18)*(1+$D$19) -> 180.84632 | V89: =+SUM(I89:U89) -> 2170.1558
C90: Late Fees | D90: 22 | E90: $Amt/Bed | F90: Per Year | G90: 0.03 | H90: =+D90*$D$13*(1+$D$17)*(1+$D$18)*(1+$D$19)*(1+G90) -> 29193.448 | I90: 0 | J90: =$D90*$D$12/12*(1+$D$17)*(1+$D$18)*(1+$D$19) -> 1989.3095 | K90: =$D90*$D$12/12*(1+$D$17)*(1+$D$18)*(1+$D$19) -> 1989.3095 | L90: =$D90*$D$12/12*(1+$D$17)*(1+$D$18)*(1+$D$19) -> 1989.3095 | M90: =$D90*$D$12/12*(1+$D$17)*(1+$D$18)*(1+$D$19) -> 1989.3095 | N90: =$D90*$D$12/12*(1+$D$17)*(1+$D$18)*(1+$D$19) -> 1989.3095 | O90: =$D90*$D$12/12*(1+$D$17)*(1+$D$18)*(1+$D$19) -> 1989.3095 | P90: =$D90*$D$12/12*(1+$D$17)*(1+$D$18)*(1+$D$19) -> 1989.3095 | Q90: =$D90*$D$12/12*(1+$D$17)*(1+$D$18)*(1+$D$19) -> 1989.3095 | ... U90: =$D90*$D$12/12*(1+$D$17)*(1+$D$18)*(1+$D$19) -> 1989.3095 | V90: =+SUM(I90:U90) -> 23871.714
C91: Resident Fines / Move Out Charges | D91: 11 | E91: $Amt/Bed | F91: Per Year | G91: 0.03 | H91: =+D91*$D$13*(1+$D$17)*(1+$D$18)*(1+$D$19)*(1+G91) -> 14596.724 | I91: 0 | J91: =$D91*$D$12/12*(1+$D$17)*(1+$D$18)*(1+$D$19) -> 994.65475 | K91: =$D91*$D$12/12*(1+$D$17)*(1+$D$18)*(1+$D$19) -> 994.65475 | L91: =$D91*$D$12/12*(1+$D$17)*(1+$D$18)*(1+$D$19) -> 994.65475 | M91: =$D91*$D$12/12*(1+$D$17)*(1+$D$18)*(1+$D$19) -> 994.65475 | N91: =$D91*$D$12/12*(1+$D$17)*(1+$D$18)*(1+$D$19) -> 994.65475 | O91: =$D91*$D$12/12*(1+$D$17)*(1+$D$18)*(1+$D$19) -> 994.65475 | P91: =$D91*$D$12/12*(1+$D$17)*(1+$D$18)*(1+$D$19) -> 994.65475 | Q91: =$D91*$D$12/12*(1+$D$17)*(1+$D$18)*(1+$D$19) -> 994.65475 | ... U91: =$D91*$D$12/12*(1+$D$17)*(1+$D$18)*(1+$D$19) -> 994.65475 | V91: =+SUM(I91:U91) -> 11935.857
C92: Pet Fees | D92: 23 | E92: $Amt/Bed | F92: Per Year | G92: 0.03 | H92: =+D92*$D$13*(1+$D$17)*(1+$D$18)*(1+$D$19)*(1+G92) -> 30520.422 | I92: 0 | J92: =+$D92*$D$12/12*(1+$D$17)*(1+$D$18)*(1+$D$19) -> 2079.7327 | K92: =+$D92*$D$12/12*(1+$D$17)*(1+$D$18)*(1+$D$19) -> 2079.7327 | L92: =+$D92*$D$12/12*(1+$D$17)*(1+$D$18)*(1+$D$19) -> 2079.7327 | M92: =+$D92*$D$12/12*(1+$D$17)*(1+$D$18)*(1+$D$19) -> 2079.7327 | N92: =+$D92*$D$12/12*(1+$D$17)*(1+$D$18)*(1+$D$19) -> 2079.7327 | O92: =+$D92*$D$12/12*(1+$D$17)*(1+$D$18)*(1+$D$19) -> 2079.7327 | P92: =+$D92*$D$12/12*(1+$D$17)*(1+$D$18)*(1+$D$19) -> 2079.7327 | Q92: =+$D92*$D$12/12*(1+$D$17)*(1+$D$18)*(1+$D$19) -> 2079.7327 | ... U92: =+$D92*$D$12/12*(1+$D$17)*(1+$D$18)*(1+$D$19) -> 2079.7327 | V92: =+SUM(I92:U92) -> 24956.792
C93: Move In/Redec Charges | D93: 0 | E93: $Amt/Bed | F93: Per Year | G93: 0.03 | H93: =+D93*$D$13*(1+$D$17)*(1+$D$18)*(1+$D$19)*(1+G93) -> 0 | I93: 0 | J93: =$D93*$D$12/12*(1+$D$17)*(1+$D$18)*(1+$D$19) -> 0 | K93: =$D93*$D$12/12*(1+$D$17)*(1+$D$18)*(1+$D$19) -> 0 | L93: =$D93*$D$12/12*(1+$D$17)*(1+$D$18)*(1+$D$19) -> 0 | M93: =$D93*$D$12/12*(1+$D$17)*(1+$D$18)*(1+$D$19) -> 0 | N93: =$D93*$D$12/12*(1+$D$17)*(1+$D$18)*(1+$D$19) -> 0 | O93: =$D93*$D$12/12*(1+$D$17)*(1+$D$18)*(1+$D$19) -> 0 | P93: =$D93*$D$12/12*(1+$D$17)*(1+$D$18)*(1+$D$19) -> 0 | Q93: =$D93*$D$12/12*(1+$D$17)*(1+$D$18)*(1+$D$19) -> 0 | ... U93: =$D93*$D$12/12*(1+$D$17)*(1+$D$18)*(1+$D$19) -> 0 | V93: =+SUM(I93:U93) -> 0
C94: Move Out Charges | D94: 0 | E94: $Amt/Bed | F94: Per Year | G94: 0.03 | H94: =+D94*$D$13*(1+$D$17)*(1+$D$18)*(1+$D$19)*(1+G94) -> 0 | I94: 0 | J94: =$D94*$D$12/12*(1+$D$17)*(1+$D$18)*(1+$D$19) -> 0 | K94: =$D94*$D$12/12*(1+$D$17)*(1+$D$18)*(1+$D$19) -> 0 | L94: =$D94*$D$12/12*(1+$D$17)*(1+$D$18)*(1+$D$19) -> 0 | M94: =$D94*$D$12/12*(1+$D$17)*(1+$D$18)*(1+$D$19) -> 0 | N94: =$D94*$D$12/12*(1+$D$17)*(1+$D$18)*(1+$D$19) -> 0 | O94: =$D94*$D$12/12*(1+$D$17)*(1+$D$18)*(1+$D$19) -> 0 | P94: =$D94*$D$12/12*(1+$D$17)*(1+$D$18)*(1+$D$19) -> 0 | Q94: =$D94*$D$12/12*(1+$D$17)*(1+$D$18)*(1+$D$19) -> 0 | ... U94: =$D94*$D$12/12*(1+$D$17)*(1+$D$18)*(1+$D$19) -> 0 | V94: =+SUM(I94:U94) -> 0
C95: Transfer Fees | D95: 4 | E95: $Amt/Bed | F95: Per Year | G95: 0.03 | H95: =+D95*$D$13*(1+$D$17)*(1+$D$18)*(1+$D$19)*(1+G95) -> 5307.8995 | I95: 0 | J95: =$D95*$D$12/12*(1+$D$17)*(1+$D$18)*(1+$D$19) -> 361.69264 | K95: =$D95*$D$12/12*(1+$D$17)*(1+$D$18)*(1+$D$19) -> 361.69264 | L95: =$D95*$D$12/12*(1+$D$17)*(1+$D$18)*(1+$D$19) -> 361.69264 | M95: =$D95*$D$12/12*(1+$D$17)*(1+$D$18)*(1+$D$19) -> 361.69264 | N95: =$D95*$D$12/12*(1+$D$17)*(1+$D$18)*(1+$D$19) -> 361.69264 | O95: =$D95*$D$12/12*(1+$D$17)*(1+$D$18)*(1+$D$19) -> 361.69264 | P95: =$D95*$D$12/12*(1+$D$17)*(1+$D$18)*(1+$D$19) -> 361.69264 | Q95: =$D95*$D$12/12*(1+$D$17)*(1+$D$18)*(1+$D$19) -> 361.69264 | ... U95: =$D95*$D$12/12*(1+$D$17)*(1+$D$18)*(1+$D$19) -> 361.69264 | V95: =+SUM(I95:U95) -> 4340.3116
C96: Payment Proc. Fees | D96: 0 | E96: $Amt/Bed | F96: Per Year | G96: 0.03 | H96: =+D96*$D$13*(1+$D$17)*(1+$D$18)*(1+$D$19)*(1+G96) -> 0 | I96: 0 | J96: =$D96*$D$12/12*(1+$D$17)*(1+$D$18)*(1+$D$19) -> 0 | K96: =$D96*$D$12/12*(1+$D$17)*(1+$D$18)*(1+$D$19) -> 0 | L96: =$D96*$D$12/12*(1+$D$17)*(1+$D$18)*(1+$D$19) -> 0 | M96: =$D96*$D$12/12*(1+$D$17)*(1+$D$18)*(1+$D$19) -> 0 | N96: =$D96*$D$12/12*(1+$D$17)*(1+$D$18)*(1+$D$19) -> 0 | O96: =$D96*$D$12/12*(1+$D$17)*(1+$D$18)*(1+$D$19) -> 0 | P96: =$D96*$D$12/12*(1+$D$17)*(1+$D$18)*(1+$D$19) -> 0 | Q96: =$D96*$D$12/12*(1+$D$17)*(1+$D$18)*(1+$D$19) -> 0 | ... U96: =$D96*$D$12/12*(1+$D$17)*(1+$D$18)*(1+$D$19) -> 0 | V96: =+SUM(I96:U96) -> 0
C97: MTM & Rent Premiums | D97: 40 | E97: $Amt/Bed | F97: Per Year | G97: 0.03 | H97: =+D97*$D$13*(1+$D$17)*(1+$D$18)*(1+$D$19)*(1+G97) -> 53078.995 | I97: 0 | J97: =$D97*$D$12/12*(1+$D$17)*(1+$D$18)*(1+$D$19) -> 3616.9264 | K97: =$D97*$D$12/12*(1+$D$17)*(1+$D$18)*(1+$D$19) -> 3616.9264 | L97: =$D97*$D$12/12*(1+$D$17)*(1+$D$18)*(1+$D$19) -> 3616.9264 | M97: =$D97*$D$12/12*(1+$D$17)*(1+$D$18)*(1+$D$19) -> 3616.9264 | N97: =$D97*$D$12/12*(1+$D$17)*(1+$D$18)*(1+$D$19) -> 3616.9264 | O97: =$D97*$D$12/12*(1+$D$17)*(1+$D$18)*(1+$D$19) -> 3616.9264 | P97: =$D97*$D$12/12*(1+$D$17)*(1+$D$18)*(1+$D$19) -> 3616.9264 | Q97: =$D97*$D$12/12*(1+$D$17)*(1+$D$18)*(1+$D$19) -> 3616.9264 | ... U97: =$D97*$D$12/12*(1+$D$17)*(1+$D$18)*(1+$D$19) -> 3616.9264 | V97: =+SUM(I97:U97) -> 43403.116
C98: Eviction/Legal Fees | D98: 1 | E98: $Amt/Bed | F98: Per Year | G98: 0.03 | H98: =+D98*$D$13*(1+$D$17)*(1+$D$18)*(1+$D$19)*(1+G98) -> 1326.9749 | I98: 0 | J98: =$D98*$D$12/12*(1+$D$17)*(1+$D$18)*(1+$D$19) -> 90.423159 | K98: =$D98*$D$12/12*(1+$D$17)*(1+$D$18)*(1+$D$19) -> 90.423159 | L98: =$D98*$D$12/12*(1+$D$17)*(1+$D$18)*(1+$D$19) -> 90.423159 | M98: =$D98*$D$12/12*(1+$D$17)*(1+$D$18)*(1+$D$19) -> 90.423159 | N98: =$D98*$D$12/12*(1+$D$17)*(1+$D$18)*(1+$D$19) -> 90.423159 | O98: =$D98*$D$12/12*(1+$D$17)*(1+$D$18)*(1+$D$19) -> 90.423159 | P98: =$D98*$D$12/12*(1+$D$17)*(1+$D$18)*(1+$D$19) -> 90.423159 | Q98: =$D98*$D$12/12*(1+$D$17)*(1+$D$18)*(1+$D$19) -> 90.423159 | ... U98: =$D98*$D$12/12*(1+$D$17)*(1+$D$18)*(1+$D$19) -> 90.423159 | V98: =+SUM(I98:U98) -> 1085.0779
C99: NSF Fees | D99: 4 | E99: $Amt/Bed | F99: Per Year | G99: 0.03 | H99: =+D99*$D$13*(1+$D$17)*(1+$D$18)*(1+$D$19)*(1+G99) -> 5307.8995 | I99: 0 | J99: =$D99*$D$12/12*(1+$D$17)*(1+$D$18)*(1+$D$19) -> 361.69264 | K99: =$D99*$D$12/12*(1+$D$17)*(1+$D$18)*(1+$D$19) -> 361.69264 | L99: =$D99*$D$12/12*(1+$D$17)*(1+$D$18)*(1+$D$19) -> 361.69264 | M99: =$D99*$D$12/12*(1+$D$17)*(1+$D$18)*(1+$D$19) -> 361.69264 | N99: =$D99*$D$12/12*(1+$D$17)*(1+$D$18)*(1+$D$19) -> 361.69264 | O99: =$D99*$D$12/12*(1+$D$17)*(1+$D$18)*(1+$D$19) -> 361.69264 | P99: =$D99*$D$12/12*(1+$D$17)*(1+$D$18)*(1+$D$19) -> 361.69264 | Q99: =$D99*$D$12/12*(1+$D$17)*(1+$D$18)*(1+$D$19) -> 361.69264 | ... U99: =$D99*$D$12/12*(1+$D$17)*(1+$D$18)*(1+$D$19) -> 361.69264 | V99: =+SUM(I99:U99) -> 4340.3116
C100: Resident Insurance Premiums (Revenue) - Expense within G&A Line Item | D100: 156 | E100: $Amt/Bed | F100: Per Year | G100: 0.03 | H100: =+D100*$D$13*(1+$D$17)*(1+$D$18)*(1+$D$19)*(1+G100) -> 207008.08 | I100: 0 | J100: =$D100*$D$12/12*(1+$D$17)*(1+$D$18)*(1+$D$19) -> 14106.013 | K100: =$D100*$D$12/12*(1+$D$17)*(1+$D$18)*(1+$D$19) -> 14106.013 | L100: =$D100*$D$12/12*(1+$D$17)*(1+$D$18)*(1+$D$19) -> 14106.013 | M100: =$D100*$D$12/12*(1+$D$17)*(1+$D$18)*(1+$D$19) -> 14106.013 | N100: =$D100*$D$12/12*(1+$D$17)*(1+$D$18)*(1+$D$19) -> 14106.013 | O100: =$D100*$D$12/12*(1+$D$17)*(1+$D$18)*(1+$D$19) -> 14106.013 | P100: =$D100*$D$12/12*(1+$D$17)*(1+$D$18)*(1+$D$19) -> 14106.013 | Q100: =$D100*$D$12/12*(1+$D$17)*(1+$D$18)*(1+$D$19) -> 14106.013 | ... U100: =$D100*$D$12/12*(1+$D$17)*(1+$D$18)*(1+$D$19) -> 14106.013 | V100: =+SUM(I100:U100) -> 169272.15
C101: Bike Storage Fee | D101: 0 | E101: $Amt/Bed | F101: Per Year | G101: 0.03 | H101: =+D101*$D$13*(1+$D$17)*(1+$D$18)*(1+$D$19)*(1+G101) -> 0 | I101: 0 | J101: =$D101*$D$12/12*(1+$D$17)*(1+$D$18)*(1+$D$19) -> 0 | K101: =$D101*$D$12/12*(1+$D$17)*(1+$D$18)*(1+$D$19) -> 0 | L101: =$D101*$D$12/12*(1+$D$17)*(1+$D$18)*(1+$D$19) -> 0 | M101: =$D101*$D$12/12*(1+$D$17)*(1+$D$18)*(1+$D$19) -> 0 | N101: =$D101*$D$12/12*(1+$D$17)*(1+$D$18)*(1+$D$19) -> 0 | O101: =$D101*$D$12/12*(1+$D$17)*(1+$D$18)*(1+$D$19) -> 0 | P101: =$D101*$D$12/12*(1+$D$17)*(1+$D$18)*(1+$D$19) -> 0 | Q101: =$D101*$D$12/12*(1+$D$17)*(1+$D$18)*(1+$D$19) -> 0 | ... U101: =$D101*$D$12/12*(1+$D$17)*(1+$D$18)*(1+$D$19) -> 0 | V101: =+SUM(I101:U101) -> 0
C102: Admin / Guest Unit Revenue | D102: 0 | E102: $Amt/Bed | F102: Per Year | G102: 0.03 | H102: =+D102*$D$13*(1+$D$17)*(1+$D$18)*(1+$D$19)*(1+G102) -> 0 | I102: 0 | J102: =$D102*$D$12/12*(1+$D$17)*(1+$D$18)*(1+$D$19) -> 0 | K102: =$D102*$D$12/12*(1+$D$17)*(1+$D$18)*(1+$D$19) -> 0 | L102: =$D102*$D$12/12*(1+$D$17)*(1+$D$18)*(1+$D$19) -> 0 | M102: =$D102*$D$12/12*(1+$D$17)*(1+$D$18)*(1+$D$19) -> 0 | N102: =$D102*$D$12/12*(1+$D$17)*(1+$D$18)*(1+$D$19) -> 0 | O102: =$D102*$D$12/12*(1+$D$17)*(1+$D$18)*(1+$D$19) -> 0 | P102: =$D102*$D$12/12*(1+$D$17)*(1+$D$18)*(1+$D$19) -> 0 | Q102: =$D102*$D$12/12*(1+$D$17)*(1+$D$18)*(1+$D$19) -> 0 | ... U102: =$D102*$D$12/12*(1+$D$17)*(1+$D$18)*(1+$D$19) -> 0 | V102: =+SUM(I102:U102) -> 0
C103: Pet Rent | D103: 40 | E103: $Amt/Bed | F103: Per Year | G103: 0.03 | H103: =+D103*$D$13*(1+$D$17)*(1+$D$18)*(1+$D$19)*(1+G103) -> 53078.995 | I103: 0 | J103: =+$D103*($D$24*$D$12)/12*(1+$D$17)*(1+$D$18)*(1+$D$19) -> 343.60801 | K103: =+$D103*($D$24*$D$12)/12*(1+$D$17)*(1+$D$18)*(1+$D$19) -> 343.60801 | L103: =+$D103*($D$24*$D$12)/12*(1+$D$17)*(1+$D$18)*(1+$D$19) -> 343.60801 | M103: =+$D103*($D$24*$D$12)/12*(1+$D$17)*(1+$D$18)*(1+$D$19) -> 343.60801 | N103: =+$D103*($D$24*$D$12)/12*(1+$D$17)*(1+$D$18)*(1+$D$19) -> 343.60801 | O103: =+$D103*($D$24*$D$12)/12*(1+$D$17)*(1+$D$18)*(1+$D$19) -> 343.60801 | P103: =+$D103*($D$24*$D$12)/12*(1+$D$17)*(1+$D$18)*(1+$D$19) -> 343.60801 | Q103: =+$D103*($D$24*$D$12)/12*(1+$D$17)*(1+$D$18)*(1+$D$19) -> 343.60801 | ... U103: =+$D103*($D$24*$D$12)/12*(1+$D$17)*(1+$D$18)*(1+$D$19) -> 343.60801 | V103: =+SUM(I103:U103) -> 4123.2961
C104: Misc. Resident Fees | D104: 0 | E104: $Amt/Bed | F104: Per Year | G104: 0.03 | H104: =+D104*$D$13*(1+$D$17)*(1+$D$18)*(1+$D$19)*(1+G104) -> 0 | I104: 0 | J104: =$D104*$D$12/12*(1+$D$17)*(1+$D$18)*(1+$D$19) -> 0 | K104: =$D104*$D$12/12*(1+$D$17)*(1+$D$18)*(1+$D$19) -> 0 | L104: =$D104*$D$12/12*(1+$D$17)*(1+$D$18)*(1+$D$19) -> 0 | M104: =$D104*$D$12/12*(1+$D$17)*(1+$D$18)*(1+$D$19) -> 0 | N104: =$D104*$D$12/12*(1+$D$17)*(1+$D$18)*(1+$D$19) -> 0 | O104: =$D104*$D$12/12*(1+$D$17)*(1+$D$18)*(1+$D$19) -> 0 | P104: =$D104*$D$12/12*(1+$D$17)*(1+$D$18)*(1+$D$19) -> 0 | Q104: =$D104*$D$12/12*(1+$D$17)*(1+$D$18)*(1+$D$19) -> 0 | ... U104: =$D104*$D$12/12*(1+$D$17)*(1+$D$18)*(1+$D$19) -> 0 | V104: =+SUM(I104:U104) -> 0
C106: Other Income | D106: =H106/Beds -> 323.872 | E106: $Amt/Bed | F106: Per Year | G106: 0.03 | H106: =SUM(H88:H105) -> 402073.39 | I106: 0 | J106: =SUM(J88:J105) -> 24124.899 | K106: =SUM(K88:K105) -> 24124.899 | L106: =SUM(L88:L105) -> 24124.899 | M106: =SUM(M88:M105) -> 24124.899 | N106: =SUM(N88:N105) -> 24124.899 | O106: =SUM(O88:O105) -> 24124.899 | P106: =SUM(P88:P105) -> 24124.899 | Q106: =SUM(Q88:Q105) -> 24124.899 | ... V106: =SUM(V88:V105) -> 289498.79
B108: Total Other Residential Revenues | H108: =SUM(H68,H80,H84,H86,H106) -> 2715437 | I108: 0 | J108: =SUM(J68,J80,J84,J86,J106) -> 208096.71 | K108: =SUM(K68,K80,K84,K86,K106) -> 172017.87 | L108: =SUM(L68,L80,L84,L86,L106) -> 172017.87 | M108: =SUM(M68,M80,M84,M86,M106) -> 172017.87 | N108: =SUM(N68,N80,N84,N86,N106) -> 172017.87 | O108: =SUM(O68,O80,O84,O86,O106) -> 172017.87 | P108: =SUM(P68,P80,P84,P86,P106) -> 172017.87 | Q108: =SUM(Q68,Q80,Q84,Q86,Q106) -> 172017.87 | ... U108: =SUM(U68,U80,U84,U86,U106) -> 172017.87 | V108: =+SUM(I108:U108) -> 2100293.2
V109: =+SUM(I109:U109) -> 0
B110: EFFECTIVE GROSS RESIDENTIAL REVENUE | H110: =+H63+H108 -> 27776051 | I110: 0 | J110: =+J63+J108 -> 1915513.7 | K110: =+K63+K108 -> 1879434.9 | L110: =+L63+L108 -> 1879434.9 | M110: =+M63+M108 -> 1879434.9 | N110: =+N63+N108 -> 1879434.9 | O110: =+O63+O108 -> 1879434.9 | P110: =+P63+P108 -> 1879434.9 | Q110: =+Q63+Q108 -> 1879434.9 | ... U110: =+U63+U108 -> 1879434.9 | V110: =+SUM(I110:U110) -> 22589298
B112: COMMERCIAL REVENUES
C114: Commercial Rent | D114: =+M43 -> 58368 | E114: $ Amount | F114: Per Year | G114: 0.03 | H114: =IF(D114>0,D114*(1+$G$114),0)*(1+$D$17)*(1+$D$18)*(1+$D$19) -> 65693.698 | I114: 0 | J114: =+IF(J49>=$D$36,$M$45/12,0)*(1+$D$17)*(1+$D$18)*(1+$D$19) -> 0 | K114: =+IF(K49>=$D$36,$M$45/12,0)*(1+$D$17)*(1+$D$18)*(1+$D$19) -> 0 | L114: =+IF(L49>=$D$36,$M$45/12,0)*(1+$D$17)*(1+$D$18)*(1+$D$19) -> 0 | M114: =+IF(M49>=$D$36,$M$45/12,0)*(1+$D$17)*(1+$D$18)*(1+$D$19) -> 5315.0241 | N114: =+IF(N49>=$D$36,$M$45/12,0)*(1+$D$17)*(1+$D$18)*(1+$D$19) -> 5315.0241 | O114: =+IF(O49>=$D$36,$M$45/12,0)*(1+$D$17)*(1+$D$18)*(1+$D$19) -> 5315.0241 | P114: =+IF(P49>=$D$36,$M$45/12,0)*(1+$D$17)*(1+$D$18)*(1+$D$19) -> 5315.0241 | Q114: =+IF(Q49>=$D$36,$M$45/12,0)*(1+$D$17)*(1+$D$18)*(1+$D$19) -> 5315.0241 | ... U114: =+IF(U49>=$D$36,$M$45/12,0)*(1+$D$17)*(1+$D$18)*(1+$D$19) -> 5315.0241 | V114: =+SUM(I114:U114) -> 47835.217
C115: Commercial Vacancy Loss | G115: =+D37 -> 0.1 | H115: =-$G115*H114 -> -6569.3698 | I115: 0 | J115: =+-$G$115*J114 -> 0 | K115: =+-$G$115*K114 -> 0 | L115: =+-$G$115*L114 -> 0 | M115: =+-$G$115*M114 -> -531.50241 | N115: =+-$G$115*N114 -> -531.50241 | O115: =+-$G$115*O114 -> -531.50241 | P115: =+-$G$115*P114 -> -531.50241 | Q115: =+-$G$115*Q114 -> -531.50241 | ... U115: =+-$G$115*U114 -> -531.50241 | V115: =+SUM(I115:U115) -> -4783.5217
...

Sheet Development
D1: ='Executive Summary'!$E$5& " DEVELOPMENT" -> VERVE Chapel Hill DEVELOPMENT | T1: Detailed | AI1: Calcs | AJ1: 0 | AK1: 1 | AL1: =+AK1+1 -> 2 | AM1: =+AL1+1 -> 3 | AN1: =+AM1+1 -> 4 | AO1: =+AN1+1 -> 5 | AP1: =+AO1+1 -> 6 | AQ1: =+AP1+1 -> 7 | AR1: =+AQ1+1 -> 8 | AS1: =+AR1+1 -> 9 | ... EZ1: =+EY1+1 -> 120
AJ2: 0 | AK2: 1 | AL2: 1 | AM2: 1 | AN2: 1 | AO2: 1 | AP2: 1 | AQ2: 1 | AR2: 1 | AS2: 1 | AT2: 1 | AU2: 1 | AV2: 1 | AW2: =+AK2+1 -> 2 | AX2: =+AL2+1 -> 2 | AY2: =+AM2+1 -> 2 | AZ2: =+AN2+1 -> 2 | BA2: =+AO2+1 -> 2 | BB2: =+AP2+1 -> 2 | BC2: =+AQ2+1 -> 2 | BD2: =+AR2+1 -> 2 | ... EZ2: =+EN2+1 -> 10
AJ3: =StartDate-1 -> 46752 | AK3: =EOMONTH(StartDate,0) -> 46783 | AL3: =EOMONTH(AK3,1) -> 46812 | AM3: =EOMONTH(AL3,1) -> 46843 | AN3: =EOMONTH(AM3,1) -> 46873 | AO3: =EOMONTH(AN3,1) -> 46904 | AP3: =EOMONTH(AO3,1) -> 46934 | AQ3: =EOMONTH(AP3,1) -> 46965 | AR3: =EOMONTH(AQ3,1) -> 46996 | AS3: =EOMONTH(AR3,1) -> 47026 | ... EZ3: =EOMONTH(EY3,1) -> 50405
D5: FACTOR CALCULATION METRICS | J5: PROJECT TIMING
M6: Start Dates | N6: Start Month | O6: Duration Months | P6: End Month
D7: Area Measures | J7: Land Acquisition Date | M7: =+StartDate -> 46753 | N7: 1 | O7: 1 | P7: =MAX(0,N7+O7-1) -> 1
E8: Amount | H8: 1 | J8: Construction Phase | M8: =DATE(YEAR(M7),MONTH(M7)+O7,DAY(M7)) -> 46784 | N8: =P7+1 -> 2 | O8: 30 | P8: =MAX(0,N8+O8-1) -> 31
E9: Total Units | H9: =+Units -> 461.33501 | J9: Lease-up Phase (Delivery Year) | M9: =DATE(YEAR(M8),MONTH(M8)+O8,DAY(M8)) -> 47696 | N9: =+P8+1 -> 32 | O9: 12 | P9: =MAX(0,N9+O9-1) -> 43
E10: Total Beds | H10: =Assumptions!$M$22 -> 1241.4577 | J10: Lease-up Phase (Year 2) | M10: =DATE(YEAR(M9),MONTH(M9)+O9,DAY(M9)) -> 48061 | N10: =+P9+1 -> 44 | O10: 12 | P10: =MAX(0,N10+O10-1) -> 55
E11: Gross Res SF | H11: 502832 | J11: Operations Phase | M11: =DATE(YEAR(M10),MONTH(M10)+O10,DAY(M10)) -> 48427 | N11: =P10+1 -> 56 | O11: =120-N11+1 -> 65 | P11: =MAX(0,N11+O11-1) -> 120
E12: Amenity and Leasing SF | H12: 20325 | J12: Last Month of Construction Loan | M12: =+M10-1 -> 48060 | N12: =+N10 -> 44 | P12: =+N11-1 -> 55
E13: Commercial SF | H13: 1824
E14: Parking SF | H14: 232842
E15: Total Gross SF | H15: =SUM(H11:H14) -> 757823
E16: Total Net SF | H16: =+Assumptions!U22 -> 428715
E17: Total FAR SF | H17: 0 | J17: DISPLAY PARAMETERS
E18: Land SF | H18: =+H285 -> 338897 | J18: Amounts display per this Metric in Summary | P18: Total Units
E19: Land Acres | H19: =H18/43560 -> 7.7800046 | J19: Building Type | P19: Mid-Rise
D20: % of Costs
E21: % of Land Costs | H21: =IFERROR(G40,0) -> 25587500
E22: % of Construction Costs | H22: =IFERROR(G81,0) -> 1.6084708e+08 | I22: Excludes Site Work & HC Contingency
E23: % of Hard Costs | H23: =IFERROR(SUM(G69,G81),0) -> 1.6162208e+08 | I23: Excludes HC Contingency
E24: % of Soft Costs | H24: =IFERROR(G246-G215-G231-G238-G244,0) -> 21291596 | I24: Excludes SC Contingency, Dev Fee, CM Fee, and Const. Interest
E25: % of Const. Financing Costs | H25: =IFERROR(G225,0) -> 9958874.8
E26: % of Total Project Costs | H26: =IFERROR(G256-G238,0) -> 2.2976343e+08 | I26: Excludes Developer Fee
E27: % of Total Hard & Soft Costs | H27: =IFERROR(SUM(H23:H24),0) -> 1.8291367e+08 | I27: See above Exclusions
E28: TBD 1 | H28: 0
D29: % of Loan
E30: % of Construction Loan | H30: =IFERROR($G$267,0) -> 1.5532008e+08
U33: Duration | V33: Distribution | W33: Midpoint Begin After | X33: Midpoint End After | Y33: Midpoint PeriodPercentage | Z33: 2 (balanced), or 3 (backload) | AA33: Ratio Peak /Trough | AB33: m | AC33: r | AD33: i | AE33: a1 | AF33: b1 | AG33: a2 | AH33: b2
D34: ACQUISITION COSTS | G34: Total Budget | H34: Unit Price | I34: Factor | J34: Units | K34: Cost/Bed | L34: Cost/GSF | M34: Cost/NSF | N34: Start Date | O34: Start Month | P34: Months | Q34: End Month | R34: Distribution | S34: Comments / Description | U34: DISTRIBUTION CALCULATIONS
D35: 1 | E35: Land Costs
E37: =IF(ISBLANK(F37)," ",OFFSET(E37,-1,0)+1) -> 1 | F37: Purchase Price - Magma Equities | G37: =H37*J37 -> 25000000 | H37: 25000000 | I37: Amount | J37: =INDEX(FACTOR_VALUES,MATCH(I37,FACTOR_NAMES,0),1) -> 1 | K37: =+$G37/Beds -> 20137.617 | L37: =+$G37/$H$15 -> 32.989234 | M37: =+$G37/$H$16 -> 58.313798 | N37: =EOMONTH($M$7,O37-2)+1 -> 46753 | O37: =$N$7 -> 1 | P37: 1 | Q37: =O37-1+P37 -> 1 | R37: Flat | U37: =+P37 -> 1 | V37: =+R37 -> Flat | W37: =INT(U37*AB37)+O37-1 -> 0 | X37: =(U37-INT(U37*(1-AB37)))+O37-1 -> 1 | Y37: =(AB37-(W37-O37+1)/U37)*(AF37+AE37*(2*(W37-O37+1)/U37+(AB37-(W37-O37+1)/U37)))+((X37-O37+1)/U37-AB37)*(AH37+AG37*(2*AB37+((X37-O37+1)/U37-AB37))) -> 1 | Z37: =IF(V37="curve-front",1,IF(V37="curve-end",3,2)) -> 2 | AA37: =IF(OR(V37="curve-front",V37="curve-mid",V37="curve-end"),2.5,1) -> 1 | AB37: =Z37/4 -> 0.5 | AC37: =AA37-1 -> 0 | AD37: =1/U37 -> 1 | AE37: =AC37/(AB37*(2+AC37)) -> 0 | AF37: =2/(2+AC37) -> 1 | AG37: =-AC37/(2+AC37)/(1-AB37) -> 0 | AH37: =2*(1-AB37+AC37)/(2+AC37)/(1-AB37) -> 1 | AJ37: =IF(AND(AJ$1>=$O37,AJ$1<=$Q37),$G37*IF(AJ$1<=$W37,$AD37*($AF37+$AE37*(2*INT((AJ$1-$O37))/$U37+$AD37)),IF(AJ$1<=$X37,$Y37,IF(AJ$1<=$U37+$O37,$AD37*($AH37+$AG37*(2*INT((AJ$1-$O37))/$U37+$AD37)),0))),0) -> 0 | AK37: =IF(AND(AK$1>=$O37,AK$1<=$Q37),$G37*IF(AK$1<=$W37,$AD37*($AF37+$AE37*(2*INT((AK$1-$O37))/$U37+$AD37)),IF(AK$1<=$X37,$Y37,IF(AK$1<=$U37+$O37,$AD37*($AH37+$AG37*(2*INT((AK$1-$O37))/$U37+$AD37)),0))),0) -> 25000000 | AL37: =IF(AND(AL$1>=$O37,AL$1<=$Q37),$G37*IF(AL$1<=$W37,$AD37*($AF37+$AE37*(2*INT((AL$1-$O37))/$U37+$AD37)),IF(AL$1<=$X37,$Y37,IF(AL$1<=$U37+$O37,$AD37*($AH37+$AG37*(2*INT((AL$1-$O37))/$U37+$AD37)),0))),0) -> 0 | AM37: =IF(AND(AM$1>=$O37,AM$1<=$Q37),$G37*IF(AM$1<=$W37,$AD37*($AF37+$AE37*(2*INT((AM$1-$O37))/$U37+$AD37)),IF(AM$1<=$X37,$Y37,IF(AM$1<=$U37+$O37,$AD37*($AH37+$AG37*(2*INT((AM$1-$O37))/$U37+$AD37)),0))),0) -> 0 | AN37: =IF(AND(AN$1>=$O37,AN$1<=$Q37),$G37*IF(AN$1<=$W37,$AD37*($AF37+$AE37*(2*INT((AN$1-$O37))/$U37+$AD37)),IF(AN$1<=$X37,$Y37,IF(AN$1<=$U37+$O37,$AD37*($AH37+$AG37*(2*INT((AN$1-$O37))/$U37+$AD37)),0))),0) -> 0 | AO37: =IF(AND(AO$1>=$O37,AO$1<=$Q37),$G37*IF(AO$1<=$W37,$AD37*($AF37+$AE37*(2*INT((AO$1-$O37))/$U37+$AD37)),IF(AO$1<=$X37,$Y37,IF(AO$1<=$U37+$O37,$AD37*($AH37+$AG37*(2*INT((AO$1-$O37))/$U37+$AD37)),0))),0) -> 0 | AP37: =IF(AND(AP$1>=$O37,AP$1<=$Q37),$G37*IF(AP$1<=$W37,$AD37*($AF37+$AE37*(2*INT((AP$1-$O37))/$U37+$AD37)),IF(AP$1<=$X37,$Y37,IF(AP$1<=$U37+$O37,$AD37*($AH37+$AG37*(2*INT((AP$1-$O37))/$U37+$AD37)),0))),0) -> 0 | AQ37: =IF(AND(AQ$1>=$O37,AQ$1<=$Q37),$G37*IF(AQ$1<=$W37,$AD37*($AF37+$AE37*(2*INT((AQ$1-$O37))/$U37+$AD37)),IF(AQ$1<=$X37,$Y37,IF(AQ$1<=$U37+$O37,$AD37*($AH37+$AG37*(2*INT((AQ$1-$O37))/$U37+$AD37)),0))),0) -> 0 | ... EZ37: =IF(AND(EZ$1>=$O37,EZ$1<=$Q37),$G37*IF(EZ$1<=$W37,$AD37*($AF37+$AE37*(2*INT((EZ$1-$O37))/$U37+$AD37)),IF(EZ$1<=$X37,$Y37,IF(EZ$1<=$U37+$O37,$AD37*($AH37+$AG37*(2*INT((EZ$1-$O37))/$U37+$AD37)),0))),0) -> 0
E38: =IF(ISBLANK(F38)," ",OFFSET(E38,-1,0)+1) -> 2 | F38: Ground Lease During Construction - Birgel Family | G38: =H38*J38 -> 587500 | H38: =+(Assumptions!D128/12)*(Development!O8) -> 587500 | I38: Amount | J38: =INDEX(FACTOR_VALUES,MATCH(I38,FACTOR_NAMES,0),1) -> 1 | K38: =+$G38/Beds -> 473.234 | L38: =+$G38/$H$15 -> 0.77524699 | M38: =+$G38/$H$16 -> 1.3703743 | N38: =EOMONTH($M$7,O38-2)+1 -> 46753 | O38: =$N$7 -> 1 | P38: 1 | Q38: =O38-1+P38 -> 1 | R38: Flat | U38: =+P38 -> 1 | V38: =+R38 -> Flat | W38: =INT(U38*AB38)+O38-1 -> 0 | X38: =(U38-INT(U38*(1-AB38)))+O38-1 -> 1 | Y38: =(AB38-(W38-O38+1)/U38)*(AF38+AE38*(2*(W38-O38+1)/U38+(AB38-(W38-O38+1)/U38)))+((X38-O38+1)/U38-AB38)*(AH38+AG38*(2*AB38+((X38-O38+1)/U38-AB38))) -> 1 | Z38: =IF(V38="curve-front",1,IF(V38="curve-end",3,2)) -> 2 | AA38: =IF(OR(V38="curve-front",V38="curve-mid",V38="curve-end"),2.5,1) -> 1 | AB38: =Z38/4 -> 0.5 | AC38: =AA38-1 -> 0 | AD38: =1/U38 -> 1 | AE38: =AC38/(AB38*(2+AC38)) -> 0 | AF38: =2/(2+AC38) -> 1 | AG38: =-AC38/(2+AC38)/(1-AB38) -> 0 | AH38: =2*(1-AB38+AC38)/(2+AC38)/(1-AB38) -> 1 | AJ38: =IF(AND(AJ$1>=$O38,AJ$1<=$Q38),$G38*IF(AJ$1<=$W38,$AD38*($AF38+$AE38*(2*INT((AJ$1-$O38))/$U38+$AD38)),IF(AJ$1<=$X38,$Y38,IF(AJ$1<=$U38+$O38,$AD38*($AH38+$AG38*(2*INT((AJ$1-$O38))/$U38+$AD38)),0))),0) -> 0 | AK38: =IF(AND(AK$1>=$O38,AK$1<=$Q38),$G38*IF(AK$1<=$W38,$AD38*($AF38+$AE38*(2*INT((AK$1-$O38))/$U38+$AD38)),IF(AK$1<=$X38,$Y38,IF(AK$1<=$U38+$O38,$AD38*($AH38+$AG38*(2*INT((AK$1-$O38))/$U38+$AD38)),0))),0) -> 587500 | AL38: =IF(AND(AL$1>=$O38,AL$1<=$Q38),$G38*IF(AL$1<=$W38,$AD38*($AF38+$AE38*(2*INT((AL$1-$O38))/$U38+$AD38)),IF(AL$1<=$X38,$Y38,IF(AL$1<=$U38+$O38,$AD38*($AH38+$AG38*(2*INT((AL$1-$O38))/$U38+$AD38)),0))),0) -> 0 | AM38: =IF(AND(AM$1>=$O38,AM$1<=$Q38),$G38*IF(AM$1<=$W38,$AD38*($AF38+$AE38*(2*INT((AM$1-$O38))/$U38+$AD38)),IF(AM$1<=$X38,$Y38,IF(AM$1<=$U38+$O38,$AD38*($AH38+$AG38*(2*INT((AM$1-$O38))/$U38+$AD38)),0))),0) -> 0 | AN38: =IF(AND(AN$1>=$O38,AN$1<=$Q38),$G38*IF(AN$1<=$W38,$AD38*($AF38+$AE38*(2*INT((AN$1-$O38))/$U38+$AD38)),IF(AN$1<=$X38,$Y38,IF(AN$1<=$U38+$O38,$AD38*($AH38+$AG38*(2*INT((AN$1-$O38))/$U38+$AD38)),0))),0) -> 0 | AO38: =IF(AND(AO$1>=$O38,AO$1<=$Q38),$G38*IF(AO$1<=$W38,$AD38*($AF38+$AE38*(2*INT((AO$1-$O38))/$U38+$AD38)),IF(AO$1<=$X38,$Y38,IF(AO$1<=$U38+$O38,$AD38*($AH38+$AG38*(2*INT((AO$1-$O38))/$U38+$AD38)),0))),0) -> 0 | AP38: =IF(AND(AP$1>=$O38,AP$1<=$Q38),$G38*IF(AP$1<=$W38,$AD38*($AF38+$AE38*(2*INT((AP$1-$O38))/$U38+$AD38)),IF(AP$1<=$X38,$Y38,IF(AP$1<=$U38+$O38,$AD38*($AH38+$AG38*(2*INT((AP$1-$O38))/$U38+$AD38)),0))),0) -> 0 | AQ38: =IF(AND(AQ$1>=$O38,AQ$1<=$Q38),$G38*IF(AQ$1<=$W38,$AD38*($AF38+$AE38*(2*INT((AQ$1-$O38))/$U38+$AD38)),IF(AQ$1<=$X38,$Y38,IF(AQ$1<=$U38+$O38,$AD38*($AH38+$AG38*(2*INT((AQ$1-$O38))/$U38+$AD38)),0))),0) -> 0 | ... EZ38: =IF(AND(EZ$1>=$O38,EZ$1<=$Q38),$G38*IF(EZ$1<=$W38,$AD38*($AF38+$AE38*(2*INT((EZ$1-$O38))/$U38+$AD38)),IF(EZ$1<=$X38,$Y38,IF(EZ$1<=$U38+$O38,$AD38*($AH38+$AG38*(2*INT((EZ$1-$O38))/$U38+$AD38)),0))),0) -> 0
E40: ="Total "&E35 -> Total Land Costs | G40: =IFERROR(SUM(G36:G39),"") -> 25587500 | K40: =SUM(K36:K39) -> 20610.851 | L40: =SUM(L36:L39) -> 33.764481 | M40: =SUM(M36:M39) -> 59.684172 | AJ40: =SUM(AJ36:AJ39) -> 0 | AK40: =SUM(AK36:AK39) -> 25587500 | AL40: =SUM(AL36:AL39) -> 0 | AM40: =SUM(AM36:AM39) -> 0 | AN40: =SUM(AN36:AN39) -> 0 | AO40: =SUM(AO36:AO39) -> 0 | AP40: =SUM(AP36:AP39) -> 0 | AQ40: =SUM(AQ36:AQ39) -> 0 | ... EZ40: =SUM(EZ36:EZ39) -> 0
D42: 2 | E42: Closing Costs
E44: =OFFSET(E44,-1,0)+1 -> 1 | F44: NC Transfer Tax | G44: =H44*J44 -> 51175 | H44: 0.002 | I44: % of Land Costs | J44: =INDEX(FACTOR_VALUES,MATCH(I44,FACTOR_NAMES,0),1) -> 25587500 | K44: =+$G44/Beds -> 41.221702 | L44: =+$G44/$H$15 -> 0.067528961 | M44: =+$G44/$H$16 -> 0.11936834 | N44: =+$N$37 -> 46753 | O44: =$N$7 -> 1 | P44: 1 | Q44: =O44-1+P44 -> 1 | R44: Flat | U44: =+P44 -> 1 | V44: =+R44 -> Flat | W44: =INT(U44*AB44)+O44-1 -> 0 | X44: =(U44-INT(U44*(1-AB44)))+O44-1 -> 1 | Y44: =(AB44-(W44-O44+1)/U44)*(AF44+AE44*(2*(W44-O44+1)/U44+(AB44-(W44-O44+1)/U44)))+((X44-O44+1)/U44-AB44)*(AH44+AG44*(2*AB44+((X44-O44+1)/U44-AB44))) -> 1 | Z44: =IF(V44="curve-front",1,IF(V44="curve-end",3,2)) -> 2 | AA44: =IF(OR(V44="curve-front",V44="curve-mid",V44="curve-end"),2.5,1) -> 1 | AB44: =Z44/4 -> 0.5 | AC44: =AA44-1 -> 0 | AD44: =1/U44 -> 1 | AE44: =AC44/(AB44*(2+AC44)) -> 0 | AF44: =2/(2+AC44) -> 1 | AG44: =-AC44/(2+AC44)/(1-AB44) -> 0 | AH44: =2*(1-AB44+AC44)/(2+AC44)/(1-AB44) -> 1 | AJ44: =IF(AND(AJ$1>=$O44,AJ$1<=$Q44),$G44*IF(AJ$1<=$W44,$AD44*($AF44+$AE44*(2*INT((AJ$1-$O44))/$U44+$AD44)),IF(AJ$1<=$X44,$Y44,IF(AJ$1<=$U44+$O44,$AD44*($AH44+$AG44*(2*INT((AJ$1-$O44))/$U44+$AD44)),0))),0) -> 0 | AK44: =IF(AND(AK$1>=$O44,AK$1<=$Q44),$G44*IF(AK$1<=$W44,$AD44*($AF44+$AE44*(2*INT((AK$1-$O44))/$U44+$AD44)),IF(AK$1<=$X44,$Y44,IF(AK$1<=$U44+$O44,$AD44*($AH44+$AG44*(2*INT((AK$1-$O44))/$U44+$AD44)),0))),0) -> 51175 | AL44: =IF(AND(AL$1>=$O44,AL$1<=$Q44),$G44*IF(AL$1<=$W44,$AD44*($AF44+$AE44*(2*INT((AL$1-$O44))/$U44+$AD44)),IF(AL$1<=$X44,$Y44,IF(AL$1<=$U44+$O44,$AD44*($AH44+$AG44*(2*INT((AL$1-$O44))/$U44+$AD44)),0))),0) -> 0 | AM44: =IF(AND(AM$1>=$O44,AM$1<=$Q44),$G44*IF(AM$1<=$W44,$AD44*($AF44+$AE44*(2*INT((AM$1-$O44))/$U44+$AD44)),IF(AM$1<=$X44,$Y44,IF(AM$1<=$U44+$O44,$AD44*($AH44+$AG44*(2*INT((AM$1-$O44))/$U44+$AD44)),0))),0) -> 0 | AN44: =IF(AND(AN$1>=$O44,AN$1<=$Q44),$G44*IF(AN$1<=$W44,$AD44*($AF44+$AE44*(2*INT((AN$1-$O44))/$U44+$AD44)),IF(AN$1<=$X44,$Y44,IF(AN$1<=$U44+$O44,$AD44*($AH44+$AG44*(2*INT((AN$1-$O44))/$U44+$AD44)),0))),0) -> 0 | AO44: =IF(AND(AO$1>=$O44,AO$1<=$Q44),$G44*IF(AO$1<=$W44,$AD44*($AF44+$AE44*(2*INT((AO$1-$O44))/$U44+$AD44)),IF(AO$1<=$X44,$Y44,IF(AO$1<=$U44+$O44,$AD44*($AH44+$AG44*(2*INT((AO$1-$O44))/$U44+$AD44)),0))),0) -> 0 | AP44: =IF(AND(AP$1>=$O44,AP$1<=$Q44),$G44*IF(AP$1<=$W44,$AD44*($AF44+$AE44*(2*INT((AP$1-$O44))/$U44+$AD44)),IF(AP$1<=$X44,$Y44,IF(AP$1<=$U44+$O44,$AD44*($AH44+$AG44*(2*INT((AP$1-$O44))/$U44+$AD44)),0))),0) -> 0 | AQ44: =IF(AND(AQ$1>=$O44,AQ$1<=$Q44),$G44*IF(AQ$1<=$W44,$AD44*($AF44+$AE44*(2*INT((AQ$1-$O44))/$U44+$AD44)),IF(AQ$1<=$X44,$Y44,IF(AQ$1<=$U44+$O44,$AD44*($AH44+$AG44*(2*INT((AQ$1-$O44))/$U44+$AD44)),0))),0) -> 0 | ... EZ44: =IF(AND(EZ$1>=$O44,EZ$1<=$Q44),$G44*IF(EZ$1<=$W44,$AD44*($AF44+$AE44*(2*INT((EZ$1-$O44))/$U44+$AD44)),IF(EZ$1<=$X44,$Y44,IF(EZ$1<=$U44+$O44,$AD44*($AH44+$AG44*(2*INT((EZ$1-$O44))/$U44+$AD44)),0))),0) -> 0
E45: =OFFSET(E45,-1,0)+1 -> 2 | F45: Broker Commissions | G45: =H45*J45 -> 0 | H45: 0 | I45: % of Land Costs | J45: =INDEX(FACTOR_VALUES,MATCH(I45,FACTOR_NAMES,0),1) -> 25587500 | K45: =+$G45/Beds -> 0 | L45: =+$G45/$H$15 -> 0 | M45: =+$G45/$H$16 -> 0 | N45: =+$N$37 -> 46753 | O45: =$N$7 -> 1 | P45: 1 | Q45: =O45-1+P45 -> 1 | R45: Flat | U45: =+P45 -> 1 | V45: =+R45 -> Flat | W45: =INT(U45*AB45)+O45-1 -> 0 | X45: =(U45-INT(U45*(1-AB45)))+O45-1 -> 1 | Y45: =(AB45-(W45-O45+1)/U45)*(AF45+AE45*(2*(W45-O45+1)/U45+(AB45-(W45-O45+1)/U45)))+((X45-O45+1)/U45-AB45)*(AH45+AG45*(2*AB45+((X45-O45+1)/U45-AB45))) -> 1 | Z45: =IF(V45="curve-front",1,IF(V45="curve-end",3,2)) -> 2 | AA45: =IF(OR(V45="curve-front",V45="curve-mid",V45="curve-end"),2.5,1) -> 1 | AB45: =Z45/4 -> 0.5 | AC45: =AA45-1 -> 0 | AD45: =1/U45 -> 1 | AE45: =AC45/(AB45*(2+AC45)) -> 0 | AF45: =2/(2+AC45) -> 1 | AG45: =-AC45/(2+AC45)/(1-AB45) -> 0 | AH45: =2*(1-AB45+AC45)/(2+AC45)/(1-AB45) -> 1 | AJ45: =IF(AND(AJ$1>=$O45,AJ$1<=$Q45),$G45*IF(AJ$1<=$W45,$AD45*($AF45+$AE45*(2*INT((AJ$1-$O45))/$U45+$AD45)),IF(AJ$1<=$X45,$Y45,IF(AJ$1<=$U45+$O45,$AD45*($AH45+$AG45*(2*INT((AJ$1-$O45))/$U45+$AD45)),0))),0) -> 0 | AK45: =IF(AND(AK$1>=$O45,AK$1<=$Q45),$G45*IF(AK$1<=$W45,$AD45*($AF45+$AE45*(2*INT((AK$1-$O45))/$U45+$AD45)),IF(AK$1<=$X45,$Y45,IF(AK$1<=$U45+$O45,$AD45*($AH45+$AG45*(2*INT((AK$1-$O45))/$U45+$AD45)),0))),0) -> 0 | AL45: =IF(AND(AL$1>=$O45,AL$1<=$Q45),$G45*IF(AL$1<=$W45,$AD45*($AF45+$AE45*(2*INT((AL$1-$O45))/$U45+$AD45)),IF(AL$1<=$X45,$Y45,IF(AL$1<=$U45+$O45,$AD45*($AH45+$AG45*(2*INT((AL$1-$O45))/$U45+$AD45)),0))),0) -> 0 | AM45: =IF(AND(AM$1>=$O45,AM$1<=$Q45),$G45*IF(AM$1<=$W45,$AD45*($AF45+$AE45*(2*INT((AM$1-$O45))/$U45+$AD45)),IF(AM$1<=$X45,$Y45,IF(AM$1<=$U45+$O45,$AD45*($AH45+$AG45*(2*INT((AM$1-$O45))/$U45+$AD45)),0))),0) -> 0 | AN45: =IF(AND(AN$1>=$O45,AN$1<=$Q45),$G45*IF(AN$1<=$W45,$AD45*($AF45+$AE45*(2*INT((AN$1-$O45))/$U45+$AD45)),IF(AN$1<=$X45,$Y45,IF(AN$1<=$U45+$O45,$AD45*($AH45+$AG45*(2*INT((AN$1-$O45))/$U45+$AD45)),0))),0) -> 0 | AO45: =IF(AND(AO$1>=$O45,AO$1<=$Q45),$G45*IF(AO$1<=$W45,$AD45*($AF45+$AE45*(2*INT((AO$1-$O45))/$U45+$AD45)),IF(AO$1<=$X45,$Y45,IF(AO$1<=$U45+$O45,$AD45*($AH45+$AG45*(2*INT((AO$1-$O45))/$U45+$AD45)),0))),0) -> 0 | AP45: =IF(AND(AP$1>=$O45,AP$1<=$Q45),$G45*IF(AP$1<=$W45,$AD45*($AF45+$AE45*(2*INT((AP$1-$O45))/$U45+$AD45)),IF(AP$1<=$X45,$Y45,IF(AP$1<=$U45+$O45,$AD45*($AH45+$AG45*(2*INT((AP$1-$O45))/$U45+$AD45)),0))),0) -> 0 | AQ45: =IF(AND(AQ$1>=$O45,AQ$1<=$Q45),$G45*IF(AQ$1<=$W45,$AD45*($AF45+$AE45*(2*INT((AQ$1-$O45))/$U45+$AD45)),IF(AQ$1<=$X45,$Y45,IF(AQ$1<=$U45+$O45,$AD45*($AH45+$AG45*(2*INT((AQ$1-$O45))/$U45+$AD45)),0))),0) -> 0 | ... EZ45: =IF(AND(EZ$1>=$O45,EZ$1<=$Q45),$G45*IF(EZ$1<=$W45,$AD45*($AF45+$AE45*(2*INT((EZ$1-$O45))/$U45+$AD45)),IF(EZ$1<=$X45,$Y45,IF(EZ$1<=$U45+$O45,$AD45*($AH45+$AG45*(2*INT((EZ$1-$O45))/$U45+$AD45)),0))),0) -> 0
E46: =OFFSET(E46,-1,0)+1 -> 3 | F46: Title Search & Insurance | G46: =H46*J46 -> 150000 | H46: 150000 | I46: Amount | J46: =INDEX(FACTOR_VALUES,MATCH(I46,FACTOR_NAMES,0),1) -> 1 | K46: =+$G46/Beds -> 120.8257 | L46: =+$G46/$H$15 -> 0.1979354 | M46: =+$G46/$H$16 -> 0.34988279 | N46: =+$N$37 -> 46753 | O46: =$N$7 -> 1 | P46: 1 | Q46: =O46-1+P46 -> 1 | R46: Flat | S46: REQUEST NUMBER FROM JOSH AT FIRST AMERICAN | U46: =+P46 -> 1 | V46: =+R46 -> Flat | W46: =INT(U46*AB46)+O46-1 -> 0 | X46: =(U46-INT(U46*(1-AB46)))+O46-1 -> 1 | Y46: =(AB46-(W46-O46+1)/U46)*(AF46+AE46*(2*(W46-O46+1)/U46+(AB46-(W46-O46+1)/U46)))+((X46-O46+1)/U46-AB46)*(AH46+AG46*(2*AB46+((X46-O46+1)/U46-AB46))) -> 1 | Z46: =IF(V46="curve-front",1,IF(V46="curve-end",3,2)) -> 2 | AA46: =IF(OR(V46="curve-front",V46="curve-mid",V46="curve-end"),2.5,1) -> 1 | AB46: =Z46/4 -> 0.5 | AC46: =AA46-1 -> 0 | AD46: =1/U46 -> 1 | AE46: =AC46/(AB46*(2+AC46)) -> 0 | AF46: =2/(2+AC46) -> 1 | AG46: =-AC46/(2+AC46)/(1-AB46) -> 0 | AH46: =2*(1-AB46+AC46)/(2+AC46)/(1-AB46) -> 1 | AJ46: =IF(AND(AJ$1>=$O46,AJ$1<=$Q46),$G46*IF(AJ$1<=$W46,$AD46*($AF46+$AE46*(2*INT((AJ$1-$O46))/$U46+$AD46)),IF(AJ$1<=$X46,$Y46,IF(AJ$1<=$U46+$O46,$AD46*($AH46+$AG46*(2*INT((AJ$1-$O46))/$U46+$AD46)),0))),0) -> 0 | AK46: =IF(AND(AK$1>=$O46,AK$1<=$Q46),$G46*IF(AK$1<=$W46,$AD46*($AF46+$AE46*(2*INT((AK$1-$O46))/$U46+$AD46)),IF(AK$1<=$X46,$Y46,IF(AK$1<=$U46+$O46,$AD46*($AH46+$AG46*(2*INT((AK$1-$O46))/$U46+$AD46)),0))),0) -> 150000 | AL46: =IF(AND(AL$1>=$O46,AL$1<=$Q46),$G46*IF(AL$1<=$W46,$AD46*($AF46+$AE46*(2*INT((AL$1-$O46))/$U46+$AD46)),IF(AL$1<=$X46,$Y46,IF(AL$1<=$U46+$O46,$AD46*($AH46+$AG46*(2*INT((AL$1-$O46))/$U46+$AD46)),0))),0) -> 0 | AM46: =IF(AND(AM$1>=$O46,AM$1<=$Q46),$G46*IF(AM$1<=$W46,$AD46*($AF46+$AE46*(2*INT((AM$1-$O46))/$U46+$AD46)),IF(AM$1<=$X46,$Y46,IF(AM$1<=$U46+$O46,$AD46*($AH46+$AG46*(2*INT((AM$1-$O46))/$U46+$AD46)),0))),0) -> 0 | AN46: =IF(AND(AN$1>=$O46,AN$1<=$Q46),$G46*IF(AN$1<=$W46,$AD46*($AF46+$AE46*(2*INT((AN$1-$O46))/$U46+$AD46)),IF(AN$1<=$X46,$Y46,IF(AN$1<=$U46+$O46,$AD46*($AH46+$AG46*(2*INT((AN$1-$O46))/$U46+$AD46)),0))),0) -> 0 | AO46: =IF(AND(AO$1>=$O46,AO$1<=$Q46),$G46*IF(AO$1<=$W46,$AD46*($AF46+$AE46*(2*INT((AO$1-$O46))/$U46+$AD46)),IF(AO$1<=$X46,$Y46,IF(AO$1<=$U46+$O46,$AD46*($AH46+$AG46*(2*INT((AO$1-$O46))/$U46+$AD46)),0))),0) -> 0 | AP46: =IF(AND(AP$1>=$O46,AP$1<=$Q46),$G46*IF(AP$1<=$W46,$AD46*($AF46+$AE46*(2*INT((AP$1-$O46))/$U46+$AD46)),IF(AP$1<=$X46,$Y46,IF(AP$1<=$U46+$O46,$AD46*($AH46+$AG46*(2*INT((AP$1-$O46))/$U46+$AD46)),0))),0) -> 0 | AQ46: =IF(AND(AQ$1>=$O46,AQ$1<=$Q46),$G46*IF(AQ$1<=$W46,$AD46*($AF46+$AE46*(2*INT((AQ$1-$O46))/$U46+$AD46)),IF(AQ$1<=$X46,$Y46,IF(AQ$1<=$U46+$O46,$AD46*($AH46+$AG46*(2*INT((AQ$1-$O46))/$U46+$AD46)),0))),0) -> 0 | ... EZ46: =IF(AND(EZ$1>=$O46,EZ$1<=$Q46),$G46*IF(EZ$1<=$W46,$AD46*($AF46+$AE46*(2*INT((EZ$1-$O46))/$U46+$AD46)),IF(EZ$1<=$X46,$Y46,IF(EZ$1<=$U46+$O46,$AD46*($AH46+$AG46*(2*INT((EZ$1-$O46))/$U46+$AD46)),0))),0) -> 0
E47: =OFFSET(E47,-1,0)+1 -> 4 | F47: Other Closing Costs | G47: =H47*J47 -> 25000 | H47: 25000 | I47: Amount | J47: =INDEX(FACTOR_VALUES,MATCH(I47,FACTOR_NAMES,0),1) -> 1 | K47: =+$G47/Beds -> 20.137617 | L47: =+$G47/$H$15 -> 0.032989234 | M47: =+$G47/$H$16 -> 0.058313798 | N47: =+$N$37 -> 46753 | O47: =$N$7 -> 1 | P47: 1 | Q47: =O47-1+P47 -> 1 | R47: Flat | U47: =+P47 -> 1 | V47: =+R47 -> Flat | W47: =INT(U47*AB47)+O47-1 -> 0 | X47: =(U47-INT(U47*(1-AB47)))+O47-1 -> 1 | Y47: =(AB47-(W47-O47+1)/U47)*(AF47+AE47*(2*(W47-O47+1)/U47+(AB47-(W47-O47+1)/U47)))+((X47-O47+1)/U47-AB47)*(AH47+AG47*(2*AB47+((X47-O47+1)/U47-AB47))) -> 1 | Z47: =IF(V47="curve-front",1,IF(V47="curve-end",3,2)) -> 2 | AA47: =IF(OR(V47="curve-front",V47="curve-mid",V47="curve-end"),2.5,1) -> 1 | AB47: =Z47/4 -> 0.5 | AC47: =AA47-1 -> 0 | AD47: =1/U47 -> 1 | AE47: =AC47/(AB47*(2+AC47)) -> 0 | AF47: =2/(2+AC47) -> 1 | AG47: =-AC47/(2+AC47)/(1-AB47) -> 0 | AH47: =2*(1-AB47+AC47)/(2+AC47)/(1-AB47) -> 1 | AJ47: =IF(AND(AJ$1>=$O47,AJ$1<=$Q47),$G47*IF(AJ$1<=$W47,$AD47*($AF47+$AE47*(2*INT((AJ$1-$O47))/$U47+$AD47)),IF(AJ$1<=$X47,$Y47,IF(AJ$1<=$U47+$O47,$AD47*($AH47+$AG47*(2*INT((AJ$1-$O47))/$U47+$AD47)),0))),0) -> 0 | AK47: =IF(AND(AK$1>=$O47,AK$1<=$Q47),$G47*IF(AK$1<=$W47,$AD47*($AF47+$AE47*(2*INT((AK$1-$O47))/$U47+$AD47)),IF(AK$1<=$X47,$Y47,IF(AK$1<=$U47+$O47,$AD47*($AH47+$AG47*(2*INT((AK$1-$O47))/$U47+$AD47)),0))),0) -> 25000 | AL47: =IF(AND(AL$1>=$O47,AL$1<=$Q47),$G47*IF(AL$1<=$W47,$AD47*($AF47+$AE47*(2*INT((AL$1-$O47))/$U47+$AD47)),IF(AL$1<=$X47,$Y47,IF(AL$1<=$U47+$O47,$AD47*($AH47+$AG47*(2*INT((AL$1-$O47))/$U47+$AD47)),0))),0) -> 0 | AM47: =IF(AND(AM$1>=$O47,AM$1<=$Q47),$G47*IF(AM$1<=$W47,$AD47*($AF47+$AE47*(2*INT((AM$1-$O47))/$U47+$AD47)),IF(AM$1<=$X47,$Y47,IF(AM$1<=$U47+$O47,$AD47*($AH47+$AG47*(2*INT((AM$1-$O47))/$U47+$AD47)),0))),0) -> 0 | AN47: =IF(AND(AN$1>=$O47,AN$1<=$Q47),$G47*IF(AN$1<=$W47,$AD47*($AF47+$AE47*(2*INT((AN$1-$O47))/$U47+$AD47)),IF(AN$1<=$X47,$Y47,IF(AN$1<=$U47+$O47,$AD47*($AH47+$AG47*(2*INT((AN$1-$O47))/$U47+$AD47)),0))),0) -> 0 | AO47: =IF(AND(AO$1>=$O47,AO$1<=$Q47),$G47*IF(AO$1<=$W47,$AD47*($AF47+$AE47*(2*INT((AO$1-$O47))/$U47+$AD47)),IF(AO$1<=$X47,$Y47,IF(AO$1<=$U47+$O47,$AD47*($AH47+$AG47*(2*INT((AO$1-$O47))/$U47+$AD47)),0))),0) -> 0 | AP47: =IF(AND(AP$1>=$O47,AP$1<=$Q47),$G47*IF(AP$1<=$W47,$AD47*($AF47+$AE47*(2*INT((AP$1-$O47))/$U47+$AD47)),IF(AP$1<=$X47,$Y47,IF(AP$1<=$U47+$O47,$AD47*($AH47+$AG47*(2*INT((AP$1-$O47))/$U47+$AD47)),0))),0) -> 0 | AQ47: =IF(AND(AQ$1>=$O47,AQ$1<=$Q47),$G47*IF(AQ$1<=$W47,$AD47*($AF47+$AE47*(2*INT((AQ$1-$O47))/$U47+$AD47)),IF(AQ$1<=$X47,$Y47,IF(AQ$1<=$U47+$O47,$AD47*($AH47+$AG47*(2*INT((AQ$1-$O47))/$U47+$AD47)),0))),0) -> 0 | ... EZ47: =IF(AND(EZ$1>=$O47,EZ$1<=$Q47),$G47*IF(EZ$1<=$W47,$AD47*($AF47+$AE47*(2*INT((EZ$1-$O47))/$U47+$AD47)),IF(EZ$1<=$X47,$Y47,IF(EZ$1<=$U47+$O47,$AD47*($AH47+$AG47*(2*INT((EZ$1-$O47))/$U47+$AD47)),0))),0) -> 0
E49: ="Total "&E42 -> Total Closing Costs | G49: =SUM(G43:G48) -> 226175 | K49: =SUM(K43:K48) -> 182.18502 | L49: =SUM(L43:L48) -> 0.2984536 | M49: =SUM(M43:M48) -> 0.52756493 | AJ49: =0+(SUM(AJ43:AJ48)) -> 0 | AK49: =0+(SUM(AK43:AK48)) -> 226175 | AL49: =0+(SUM(AL43:AL48)) -> 0 | AM49: =0+(SUM(AM43:AM48)) -> 0 | AN49: =0+(SUM(AN43:AN48)) -> 0 | AO49: =0+(SUM(AO43:AO48)) -> 0 | AP49: =0+(SUM(AP43:AP48)) -> 0 | AQ49: =0+(SUM(AQ43:AQ48)) -> 0 | ... EZ49: =0+(SUM(EZ43:EZ48)) -> 0
D51: 3 | E51: Miscellaneous
E53: =OFFSET(E53,-1,0)+1 -> 1 | F53: Acquisition Fee | G53: =H53*J53 -> 250000 | H53: 250000 | I53: Amount | J53: =INDEX(FACTOR_VALUES,MATCH(I53,FACTOR_NAMES,0),1) -> 1 | K53: =+$G53/Beds -> 201.37617 | L53: =+$G53/$H$15 -> 0.32989234 | M53: =+$G53/$H$16 -> 0.58313798 | N53: =EOMONTH($M$7,O53-2)+1 -> 46753 | O53: =$N$7 -> 1 | P53: 1 | Q53: =O53-1+P53 -> 1 | R53: Flat | S53: $250K on all deals | U53: =+P53 -> 1 | V53: =+R53 -> Flat | W53: =INT(U53*AB53)+O53-1 -> 0 | X53: =(U53-INT(U53*(1-AB53)))+O53-1 -> 1 | Y53: =(AB53-(W53-O53+1)/U53)*(AF53+AE53*(2*(W53-O53+1)/U53+(AB53-(W53-O53+1)/U53)))+((X53-O53+1)/U53-AB53)*(AH53+AG53*(2*AB53+((X53-O53+1)/U53-AB53))) -> 1 | Z53: =IF(V53="curve-front",1,IF(V53="curve-end",3,2)) -> 2 | AA53: =IF(OR(V53="curve-front",V53="curve-mid",V53="curve-end"),2.5,1) -> 1 | AB53: =Z53/4 -> 0.5 | AC53: =AA53-1 -> 0 | AD53: =1/U53 -> 1 | AE53: =AC53/(AB53*(2+AC53)) -> 0 | AF53: =2/(2+AC53) -> 1 | AG53: =-AC53/(2+AC53)/(1-AB53) -> 0 | AH53: =2*(1-AB53+AC53)/(2+AC53)/(1-AB53) -> 1 | AJ53: =IF(AND(AJ$1>=$O53,AJ$1<=$Q53),$G53*IF(AJ$1<=$W53,$AD53*($AF53+$AE53*(2*INT((AJ$1-$O53))/$U53+$AD53)),IF(AJ$1<=$X53,$Y53,IF(AJ$1<=$U53+$O53,$AD53*($AH53+$AG53*(2*INT((AJ$1-$O53))/$U53+$AD53)),0))),0) -> 0 | AK53: =IF(AND(AK$1>=$O53,AK$1<=$Q53),$G53*IF(AK$1<=$W53,$AD53*($AF53+$AE53*(2*INT((AK$1-$O53))/$U53+$AD53)),IF(AK$1<=$X53,$Y53,IF(AK$1<=$U53+$O53,$AD53*($AH53+$AG53*(2*INT((AK$1-$O53))/$U53+$AD53)),0))),0) -> 250000 | AL53: =IF(AND(AL$1>=$O53,AL$1<=$Q53),$G53*IF(AL$1<=$W53,$AD53*($AF53+$AE53*(2*INT((AL$1-$O53))/$U53+$AD53)),IF(AL$1<=$X53,$Y53,IF(AL$1<=$U53+$O53,$AD53*($AH53+$AG53*(2*INT((AL$1-$O53))/$U53+$AD53)),0))),0) -> 0 | AM53: =IF(AND(AM$1>=$O53,AM$1<=$Q53),$G53*IF(AM$1<=$W53,$AD53*($AF53+$AE53*(2*INT((AM$1-$O53))/$U53+$AD53)),IF(AM$1<=$X53,$Y53,IF(AM$1<=$U53+$O53,$AD53*($AH53+$AG53*(2*INT((AM$1-$O53))/$U53+$AD53)),0))),0) -> 0 | AN53: =IF(AND(AN$1>=$O53,AN$1<=$Q53),$G53*IF(AN$1<=$W53,$AD53*($AF53+$AE53*(2*INT((AN$1-$O53))/$U53+$AD53)),IF(AN$1<=$X53,$Y53,IF(AN$1<=$U53+$O53,$AD53*($AH53+$AG53*(2*INT((AN$1-$O53))/$U53+$AD53)),0))),0) -> 0 | AO53: =IF(AND(AO$1>=$O53,AO$1<=$Q53),$G53*IF(AO$1<=$W53,$AD53*($AF53+$AE53*(2*INT((AO$1-$O53))/$U53+$AD53)),IF(AO$1<=$X53,$Y53,IF(AO$1<=$U53+$O53,$AD53*($AH53+$AG53*(2*INT((AO$1-$O53))/$U53+$AD53)),0))),0) -> 0 | AP53: =IF(AND(AP$1>=$O53,AP$1<=$Q53),$G53*IF(AP$1<=$W53,$AD53*($AF53+$AE53*(2*INT((AP$1-$O53))/$U53+$AD53)),IF(AP$1<=$X53,$Y53,IF(AP$1<=$U53+$O53,$AD53*($AH53+$AG53*(2*INT((AP$1-$O53))/$U53+$AD53)),0))),0) -> 0 | AQ53: =IF(AND(AQ$1>=$O53,AQ$1<=$Q53),$G53*IF(AQ$1<=$W53,$AD53*($AF53+$AE53*(2*INT((AQ$1-$O53))/$U53+$AD53)),IF(AQ$1<=$X53,$Y53,IF(AQ$1<=$U53+$O53,$AD53*($AH53+$AG53*(2*INT((AQ$1-$O53))/$U53+$AD53)),0))),0) -> 0 | ... EZ53: =IF(AND(EZ$1>=$O53,EZ$1<=$Q53),$G53*IF(EZ$1<=$W53,$AD53*($AF53+$AE53*(2*INT((EZ$1-$O53))/$U53+$AD53)),IF(EZ$1<=$X53,$Y53,IF(EZ$1<=$U53+$O53,$AD53*($AH53+$AG53*(2*INT((EZ$1-$O53))/$U53+$AD53)),0))),0) -> 0
E56: ="Total "&E51 -> Total Miscellaneous | G56: =SUM(G52:G55) -> 250000 | K56: =SUM(K52:K55) -> 201.37617 | L56: =SUM(L52:L55) -> 0.32989234 | M56: =SUM(M52:M55) -> 0.58313798 | AJ56: =+SUM(AJ53:AJ55) -> 0 | AK56: =+SUM(AK53:AK55) -> 250000 | AL56: =+SUM(AL53:AL55) -> 0 | AM56: =+SUM(AM53:AM55) -> 0 | AN56: =+SUM(AN53:AN55) -> 0 | AO56: =+SUM(AO53:AO55) -> 0 | AP56: =+SUM(AP53:AP55) -> 0 | AQ56: =+SUM(AQ53:AQ55) -> 0 | ... EZ56: =+SUM(EZ53:EZ55) -> 0
E58: ="TOTAL "&D34 -> TOTAL ACQUISITION COSTS | G58: =SUM(G40,G49,G56) -> 26063675 | K58: =SUM(K40,K49,K56) -> 20994.412 | L58: =SUM(L40,L49,L56) -> 34.392827 | M58: =SUM(M40,M49,M56) -> 60.794875 | AJ58: =SUM(AJ40,AJ49,AJ56) -> 0 | AK58: =SUM(AK40,AK49,AK56) -> 26063675 | AL58: =SUM(AL40,AL49,AL56) -> 0 | AM58: =SUM(AM40,AM49,AM56) -> 0 | AN58: =SUM(AN40,AN49,AN56) -> 0 | AO58: =SUM(AO40,AO49,AO56) -> 0 | AP58: =SUM(AP40,AP49,AP56) -> 0 | AQ58: =SUM(AQ40,AQ49,AQ56) -> 0 | ... EZ58: =SUM(EZ40,EZ49,EZ56) -> 0
K59: =+$G59/Units -> 0 | L59: =+$G59/$H$15 -> 0 | M59: =+$G59/$H$16 -> 0
D61: HARD COSTS | H61: Unit Price | I61: Factor | J61: Units | K61: Cost/Bed | L61: Cost/GSF | M61: Cost/NSF | N61: Start Date | O61: Start Month | P61: Months | Q61: End Month | R61: Distribution | S61: Comments / Description | U61: DISTRIBUTION CALCULATIONS
D62: 4 | E62: Site Work
E64: =OFFSET(E64,-1,0)+1 -> 1 | F64: Utility Relocation | G64: =H64*J64 -> 200000 | H64: 200000 | I64: Amount | J64: =INDEX(FACTOR_VALUES,MATCH(I64,FACTOR_NAMES,0),1) -> 1 | K64: =+$G64/Beds -> 161.10094 | L64: =+$G64/$H$15 -> 0.26391387 | M64: =+$G64/$H$16 -> 0.46651039 | N64: =EOMONTH($M$7,O64-2)+1 -> 46784 | O64: =$N$8 -> 2 | P64: 4 | Q64: =O64-1+P64 -> 5 | R64: Curve-End | U64: =+P64 -> 4 | V64: =+R64 -> Curve-End | W64: =INT(U64*AB64)+O64-1 -> 4 | X64: =(U64-INT(U64*(1-AB64)))+O64-1 -> 4 | Y64: =(AB64-(W64-O64+1)/U64)*(AF64+AE64*(2*(W64-O64+1)/U64+(AB64-(W64-O64+1)/U64)))+((X64-O64+1)/U64-AB64)*(AH64+AG64*(2*AB64+((X64-O64+1)/U64-AB64))) -> 0 | Z64: =IF(V64="curve-front",1,IF(V64="curve-end",3,2)) -> 3 | AA64: =IF(OR(V64="curve-front",V64="curve-mid",V64="curve-end"),2.5,1) -> 2.5 | AB64: =Z64/4 -> 0.75 | AC64: =AA64-1 -> 1.5 | AD64: =1/U64 -> 0.25 | AE64: =AC64/(AB64*(2+AC64)) -> 0.57142857 | AF64: =2/(2+AC64) -> 0.57142857 | AG64: =-AC64/(2+AC64)/(1-AB64) -> -1.7142857 | AH64: =2*(1-AB64+AC64)/(2+AC64)/(1-AB64) -> 4 | AJ64: =IF(AND(AJ$1>=$O64,AJ$1<=$Q64),$G64*IF(AJ$1<=$W64,$AD64*($AF64+$AE64*(2*INT((AJ$1-$O64))/$U64+$AD64)),IF(AJ$1<=$X64,$Y64,IF(AJ$1<=$U64+$O64,$AD64*($AH64+$AG64*(2*INT((AJ$1-$O64))/$U64+$AD64)),0))),0) -> 0 | AK64: =IF(AND(AK$1>=$O64,AK$1<=$Q64),$G64*IF(AK$1<=$W64,$AD64*($AF64+$AE64*(2*INT((AK$1-$O64))/$U64+$AD64)),IF(AK$1<=$X64,$Y64,IF(AK$1<=$U64+$O64,$AD64*($AH64+$AG64*(2*INT((AK$1-$O64))/$U64+$AD64)),0))),0) -> 0 | AL64: =IF(AND(AL$1>=$O64,AL$1<=$Q64),$G64*IF(AL$1<=$W64,$AD64*($AF64+$AE64*(2*INT((AL$1-$O64))/$U64+$AD64)),IF(AL$1<=$X64,$Y64,IF(AL$1<=$U64+$O64,$AD64*($AH64+$AG64*(2*INT((AL$1-$O64))/$U64+$AD64)),0))),0) -> 35714.286 | AM64: =IF(AND(AM$1>=$O64,AM$1<=$Q64),$G64*IF(AM$1<=$W64,$AD64*($AF64+$AE64*(2*INT((AM$1-$O64))/$U64+$AD64)),IF(AM$1<=$X64,$Y64,IF(AM$1<=$U64+$O64,$AD64*($AH64+$AG64*(2*INT((AM$1-$O64))/$U64+$AD64)),0))),0) -> 50000 | AN64: =IF(AND(AN$1>=$O64,AN$1<=$Q64),$G64*IF(AN$1<=$W64,$AD64*($AF64+$AE64*(2*INT((AN$1-$O64))/$U64+$AD64)),IF(AN$1<=$X64,$Y64,IF(AN$1<=$U64+$O64,$AD64*($AH64+$AG64*(2*INT((AN$1-$O64))/$U64+$AD64)),0))),0) -> 64285.714 | AO64: =IF(AND(AO$1>=$O64,AO$1<=$Q64),$G64*IF(AO$1<=$W64,$AD64*($AF64+$AE64*(2*INT((AO$1-$O64))/$U64+$AD64)),IF(AO$1<=$X64,$Y64,IF(AO$1<=$U64+$O64,$AD64*($AH64+$AG64*(2*INT((AO$1-$O64))/$U64+$AD64)),0))),0) -> 50000 | AP64: =IF(AND(AP$1>=$O64,AP$1<=$Q64),$G64*IF(AP$1<=$W64,$AD64*($AF64+$AE64*(2*INT((AP$1-$O64))/$U64+$AD64)),IF(AP$1<=$X64,$Y64,IF(AP$1<=$U64+$O64,$AD64*($AH64+$AG64*(2*INT((AP$1-$O64))/$U64+$AD64)),0))),0) -> 0 | AQ64: =IF(AND(AQ$1>=$O64,AQ$1<=$Q64),$G64*IF(AQ$1<=$W64,$AD64*($AF64+$AE64*(2*INT((AQ$1-$O64))/$U64+$AD64)),IF(AQ$1<=$X64,$Y64,IF(AQ$1<=$U64+$O64,$AD64*($AH64+$AG64*(2*INT((AQ$1-$O64))/$U64+$AD64)),0))),0) -> 0 | ... EZ64: =IF(AND(EZ$1>=$O64,EZ$1<=$Q64),$G64*IF(EZ$1<=$W64,$AD64*($AF64+$AE64*(2*INT((EZ$1-$O64))/$U64+$AD64)),IF(EZ$1<=$X64,$Y64,IF(EZ$1<=$U64+$O64,$AD64*($AH64+$AG64*(2*INT((EZ$1-$O64))/$U64+$AD64)),0))),0) -> 0
E65: =OFFSET(E65,-1,0)+1 -> 2 | F65: Temp. Lease Office Buildout + Misc Startup Costs | G65: =H65*J65 -> 375000 | H65: 375000 | I65: Amount | J65: =INDEX(FACTOR_VALUES,MATCH(I65,FACTOR_NAMES,0),1) -> 1 | K65: =+$G65/Beds -> 302.06426 | L65: =+$G65/$H$15 -> 0.4948385 | M65: =+$G65/$H$16 -> 0.87470697 | N65: =EOMONTH($M$7,O65-2)+1 -> 46966 | O65: =$N$9-24 -> 8 | P65: 3 | Q65: =O65-1+P65 -> 10 | R65: Flat | U65: =+P65 -> 3 | V65: =+R65 -> Flat | W65: =INT(U65*AB65)+O65-1 -> 8 | X65: =(U65-INT(U65*(1-AB65)))+O65-1 -> 9 | Y65: =(AB65-(W65-O65+1)/U65)*(AF65+AE65*(2*(W65-O65+1)/U65+(AB65-(W65-O65+1)/U65)))+((X65-O65+1)/U65-AB65)*(AH65+AG65*(2*AB65+((X65-O65+1)/U65-AB65))) -> 0.33333333 | Z65: =IF(V65="curve-front",1,IF(V65="curve-end",3,2)) -> 2 | AA65: =IF(OR(V65="curve-front",V65="curve-mid",V65="curve-end"),2.5,1) -> 1 | AB65: =Z65/4 -> 0.5 | AC65: =AA65-1 -> 0 | AD65: =1/U65 -> 0.33333333 | AE65: =AC65/(AB65*(2+AC65)) -> 0 | AF65: =2/(2+AC65) -> 1 | AG65: =-AC65/(2+AC65)/(1-AB65) -> 0 | AH65: =2*(1-AB65+AC65)/(2+AC65)/(1-AB65) -> 1 | AJ65: =IF(AND(AJ$1>=$O65,AJ$1<=$Q65),$G65*IF(AJ$1<=$W65,$AD65*($AF65+$AE65*(2*INT((AJ$1-$O65))/$U65+$AD65)),IF(AJ$1<=$X65,$Y65,IF(AJ$1<=$U65+$O65,$AD65*($AH65+$AG65*(2*INT((AJ$1-$O65))/$U65+$AD65)),0))),0) -> 0 | AK65: =IF(AND(AK$1>=$O65,AK$1<=$Q65),$G65*IF(AK$1<=$W65,$AD65*($AF65+$AE65*(2*INT((AK$1-$O65))/$U65+$AD65)),IF(AK$1<=$X65,$Y65,IF(AK$1<=$U65+$O65,$AD65*($AH65+$AG65*(2*INT((AK$1-$O65))/$U65+$AD65)),0))),0) -> 0 | AL65: =IF(AND(AL$1>=$O65,AL$1<=$Q65),$G65*IF(AL$1<=$W65,$AD65*($AF65+$AE65*(2*INT((AL$1-$O65))/$U65+$AD65)),IF(AL$1<=$X65,$Y65,IF(AL$1<=$U65+$O65,$AD65*($AH65+$AG65*(2*INT((AL$1-$O65))/$U65+$AD65)),0))),0) -> 0 | AM65: =IF(AND(AM$1>=$O65,AM$1<=$Q65),$G65*IF(AM$1<=$W65,$AD65*($AF65+$AE65*(2*INT((AM$1-$O65))/$U65+$AD65)),IF(AM$1<=$X65,$Y65,IF(AM$1<=$U65+$O65,$AD65*($AH65+$AG65*(2*INT((AM$1-$O65))/$U65+$AD65)),0))),0) -> 0 | AN65: =IF(AND(AN$1>=$O65,AN$1<=$Q65),$G65*IF(AN$1<=$W65,$AD65*($AF65+$AE65*(2*INT((AN$1-$O65))/$U65+$AD65)),IF(AN$1<=$X65,$Y65,IF(AN$1<=$U65+$O65,$AD65*($AH65+$AG65*(2*INT((AN$1-$O65))/$U65+$AD65)),0))),0) -> 0 | AO65: =IF(AND(AO$1>=$O65,AO$1<=$Q65),$G65*IF(AO$1<=$W65,$AD65*($AF65+$AE65*(2*INT((AO$1-$O65))/$U65+$AD65)),IF(AO$1<=$X65,$Y65,IF(AO$1<=$U65+$O65,$AD65*($AH65+$AG65*(2*INT((AO$1-$O65))/$U65+$AD65)),0))),0) -> 0 | AP65: =IF(AND(AP$1>=$O65,AP$1<=$Q65),$G65*IF(AP$1<=$W65,$AD65*($AF65+$AE65*(2*INT((AP$1-$O65))/$U65+$AD65)),IF(AP$1<=$X65,$Y65,IF(AP$1<=$U65+$O65,$AD65*($AH65+$AG65*(2*INT((AP$1-$O65))/$U65+$AD65)),0))),0) -> 0 | AQ65: =IF(AND(AQ$1>=$O65,AQ$1<=$Q65),$G65*IF(AQ$1<=$W65,$AD65*($AF65+$AE65*(2*INT((AQ$1-$O65))/$U65+$AD65)),IF(AQ$1<=$X65,$Y65,IF(AQ$1<=$U65+$O65,$AD65*($AH65+$AG65*(2*INT((AQ$1-$O65))/$U65+$AD65)),0))),0) -> 0 | ... EZ65: =IF(AND(EZ$1>=$O65,EZ$1<=$Q65),$G65*IF(EZ$1<=$W65,$AD65*($AF65+$AE65*(2*INT((EZ$1-$O65))/$U65+$AD65)),IF(EZ$1<=$X65,$Y65,IF(EZ$1<=$U65+$O65,$AD65*($AH65+$AG65*(2*INT((EZ$1-$O65))/$U65+$AD65)),0))),0) -> 0
E66: =OFFSET(E66,-1,0)+1 -> 3 | F66: Demo/Abatement | G66: =H66*J66 -> 100000 | H66: 100000 | I66: Amount | J66: =INDEX(FACTOR_VALUES,MATCH(I66,FACTOR_NAMES,0),1) -> 1 | K66: =+$G66/Beds -> 80.550469 | L66: =+$G66/$H$15 -> 0.13195693 | M66: =+$G66/$H$16 -> 0.23325519 | N66: =EOMONTH($M$7,O66-2)+1 -> 46784 | O66: =$N$8 -> 2 | P66: 4 | Q66: =O66-1+P66 -> 5 | R66: Curve-End | U66: =+P66 -> 4 | V66: =+R66 -> Curve-End | W66: =INT(U66*AB66)+O66-1 -> 4 | X66: =(U66-INT(U66*(1-AB66)))+O66-1 -> 4 | Y66: =(AB66-(W66-O66+1)/U66)*(AF66+AE66*(2*(W66-O66+1)/U66+(AB66-(W66-O66+1)/U66)))+((X66-O66+1)/U66-AB66)*(AH66+AG66*(2*AB66+((X66-O66+1)/U66-AB66))) -> 0 | Z66: =IF(V66="curve-front",1,IF(V66="curve-end",3,2)) -> 3 | AA66: =IF(OR(V66="curve-front",V66="curve-mid",V66="curve-end"),2.5,1) -> 2.5 | AB66: =Z66/4 -> 0.75 | AC66: =AA66-1 -> 1.5 | AD66: =1/U66 -> 0.25 | AE66: =AC66/(AB66*(2+AC66)) -> 0.57142857 | AF66: =2/(2+AC66) -> 0.57142857 | AG66: =-AC66/(2+AC66)/(1-AB66) -> -1.7142857 | AH66: =2*(1-AB66+AC66)/(2+AC66)/(1-AB66) -> 4 | AJ66: =IF(AND(AJ$1>=$O66,AJ$1<=$Q66),$G66*IF(AJ$1<=$W66,$AD66*($AF66+$AE66*(2*INT((AJ$1-$O66))/$U66+$AD66)),IF(AJ$1<=$X66,$Y66,IF(AJ$1<=$U66+$O66,$AD66*($AH66+$AG66*(2*INT((AJ$1-$O66))/$U66+$AD66)),0))),0) -> 0 | AK66: =IF(AND(AK$1>=$O66,AK$1<=$Q66),$G66*IF(AK$1<=$W66,$AD66*($AF66+$AE66*(2*INT((AK$1-$O66))/$U66+$AD66)),IF(AK$1<=$X66,$Y66,IF(AK$1<=$U66+$O66,$AD66*($AH66+$AG66*(2*INT((AK$1-$O66))/$U66+$AD66)),0))),0) -> 0 | AL66: =IF(AND(AL$1>=$O66,AL$1<=$Q66),$G66*IF(AL$1<=$W66,$AD66*($AF66+$AE66*(2*INT((AL$1-$O66))/$U66+$AD66)),IF(AL$1<=$X66,$Y66,IF(AL$1<=$U66+$O66,$AD66*($AH66+$AG66*(2*INT((AL$1-$O66))/$U66+$AD66)),0))),0) -> 17857.143 | AM66: =IF(AND(AM$1>=$O66,AM$1<=$Q66),$G66*IF(AM$1<=$W66,$AD66*($AF66+$AE66*(2*INT((AM$1-$O66))/$U66+$AD66)),IF(AM$1<=$X66,$Y66,IF(AM$1<=$U66+$O66,$AD66*($AH66+$AG66*(2*INT((AM$1-$O66))/$U66+$AD66)),0))),0) -> 25000 | AN66: =IF(AND(AN$1>=$O66,AN$1<=$Q66),$G66*IF(AN$1<=$W66,$AD66*($AF66+$AE66*(2*INT((AN$1-$O66))/$U66+$AD66)),IF(AN$1<=$X66,$Y66,IF(AN$1<=$U66+$O66,$AD66*($AH66+$AG66*(2*INT((AN$1-$O66))/$U66+$AD66)),0))),0) -> 32142.857 | AO66: =IF(AND(AO$1>=$O66,AO$1<=$Q66),$G66*IF(AO$1<=$W66,$AD66*($AF66+$AE66*(2*INT((AO$1-$O66))/$U66+$AD66)),IF(AO$1<=$X66,$Y66,IF(AO$1<=$U66+$O66,$AD66*($AH66+$AG66*(2*INT((AO$1-$O66))/$U66+$AD66)),0))),0) -> 25000 | AP66: =IF(AND(AP$1>=$O66,AP$1<=$Q66),$G66*IF(AP$1<=$W66,$AD66*($AF66+$AE66*(2*INT((AP$1-$O66))/$U66+$AD66)),IF(AP$1<=$X66,$Y66,IF(AP$1<=$U66+$O66,$AD66*($AH66+$AG66*(2*INT((AP$1-$O66))/$U66+$AD66)),0))),0) -> 0 | AQ66: =IF(AND(AQ$1>=$O66,AQ$1<=$Q66),$G66*IF(AQ$1<=$W66,$AD66*($AF66+$AE66*(2*INT((AQ$1-$O66))/$U66+$AD66)),IF(AQ$1<=$X66,$Y66,IF(AQ$1<=$U66+$O66,$AD66*($AH66+$AG66*(2*INT((AQ$1-$O66))/$U66+$AD66)),0))),0) -> 0 | ... EZ66: =IF(AND(EZ$1>=$O66,EZ$1<=$Q66),$G66*IF(EZ$1<=$W66,$AD66*($AF66+$AE66*(2*INT((EZ$1-$O66))/$U66+$AD66)),IF(EZ$1<=$X66,$Y66,IF(EZ$1<=$U66+$O66,$AD66*($AH66+$AG66*(2*INT((EZ$1-$O66))/$U66+$AD66)),0))),0) -> 0
E67: =OFFSET(E67,-1,0)+1 -> 4 | F67: Crane Easements | G67: =H67*J67 -> 100000 | H67: 100000 | I67: Amount | J67: =INDEX(FACTOR_VALUES,MATCH(I67,FACTOR_NAMES,0),1) -> 1 | K67: =+$G67/Beds -> 80.550469 | L67: =+$G67/$H$15 -> 0.13195693 | M67: =+$G67/$H$16 -> 0.23325519 | N67: =EOMONTH($M$7,O67-2)+1 -> 46753 | O67: =$N$7 -> 1 | P67: 1 | Q67: =O67-1+P67 -> 1 | R67: Curve-End | U67: =+P67 -> 1 | V67: =+R67 -> Curve-End | W67: =INT(U67*AB67)+O67-1 -> 0 | X67: =(U67-INT(U67*(1-AB67)))+O67-1 -> 1 | Y67: =(AB67-(W67-O67+1)/U67)*(AF67+AE67*(2*(W67-O67+1)/U67+(AB67-(W67-O67+1)/U67)))+((X67-O67+1)/U67-AB67)*(AH67+AG67*(2*AB67+((X67-O67+1)/U67-AB67))) -> 1 | Z67: =IF(V67="curve-front",1,IF(V67="curve-end",3,2)) -> 3 | AA67: =IF(OR(V67="curve-front",V67="curve-mid",V67="curve-end"),2.5,1) -> 2.5 | AB67: =Z67/4 -> 0.75 | AC67: =AA67-1 -> 1.5 | AD67: =1/U67 -> 1 | AE67: =AC67/(AB67*(2+AC67)) -> 0.57142857 | AF67: =2/(2+AC67) -> 0.57142857 | AG67: =-AC67/(2+AC67)/(1-AB67) -> -1.7142857 | AH67: =2*(1-AB67+AC67)/(2+AC67)/(1-AB67) -> 4 | AJ67: =IF(AND(AJ$1>=$O67,AJ$1<=$Q67),$G67*IF(AJ$1<=$W67,$AD67*($AF67+$AE67*(2*INT((AJ$1-$O67))/$U67+$AD67)),IF(AJ$1<=$X67,$Y67,IF(AJ$1<=$U67+$O67,$AD67*($AH67+$AG67*(2*INT((AJ$1-$O67))/$U67+$AD67)),0))),0) -> 0 | AK67: =IF(AND(AK$1>=$O67,AK$1<=$Q67),$G67*IF(AK$1<=$W67,$AD67*($AF67+$AE67*(2*INT((AK$1-$O67))/$U67+$AD67)),IF(AK$1<=$X67,$Y67,IF(AK$1<=$U67+$O67,$AD67*($AH67+$AG67*(2*INT((AK$1-$O67))/$U67+$AD67)),0))),0) -> 100000 | AL67: =IF(AND(AL$1>=$O67,AL$1<=$Q67),$G67*IF(AL$1<=$W67,$AD67*($AF67+$AE67*(2*INT((AL$1-$O67))/$U67+$AD67)),IF(AL$1<=$X67,$Y67,IF(AL$1<=$U67+$O67,$AD67*($AH67+$AG67*(2*INT((AL$1-$O67))/$U67+$AD67)),0))),0) -> 0 | AM67: =IF(AND(AM$1>=$O67,AM$1<=$Q67),$G67*IF(AM$1<=$W67,$AD67*($AF67+$AE67*(2*INT((AM$1-$O67))/$U67+$AD67)),IF(AM$1<=$X67,$Y67,IF(AM$1<=$U67+$O67,$AD67*($AH67+$AG67*(2*INT((AM$1-$O67))/$U67+$AD67)),0))),0) -> 0 | AN67: =IF(AND(AN$1>=$O67,AN$1<=$Q67),$G67*IF(AN$1<=$W67,$AD67*($AF67+$AE67*(2*INT((AN$1-$O67))/$U67+$AD67)),IF(AN$1<=$X67,$Y67,IF(AN$1<=$U67+$O67,$AD67*($AH67+$AG67*(2*INT((AN$1-$O67))/$U67+$AD67)),0))),0) -> 0 | AO67: =IF(AND(AO$1>=$O67,AO$1<=$Q67),$G67*IF(AO$1<=$W67,$AD67*($AF67+$AE67*(2*INT((AO$1-$O67))/$U67+$AD67)),IF(AO$1<=$X67,$Y67,IF(AO$1<=$U67+$O67,$AD67*($AH67+$AG67*(2*INT((AO$1-$O67))/$U67+$AD67)),0))),0) -> 0 | AP67: =IF(AND(AP$1>=$O67,AP$1<=$Q67),$G67*IF(AP$1<=$W67,$AD67*($AF67+$AE67*(2*INT((AP$1-$O67))/$U67+$AD67)),IF(AP$1<=$X67,$Y67,IF(AP$1<=$U67+$O67,$AD67*($AH67+$AG67*(2*INT((AP$1-$O67))/$U67+$AD67)),0))),0) -> 0 | AQ67: =IF(AND(AQ$1>=$O67,AQ$1<=$Q67),$G67*IF(AQ$1<=$W67,$AD67*($AF67+$AE67*(2*INT((AQ$1-$O67))/$U67+$AD67)),IF(AQ$1<=$X67,$Y67,IF(AQ$1<=$U67+$O67,$AD67*($AH67+$AG67*(2*INT((AQ$1-$O67))/$U67+$AD67)),0))),0) -> 0 | ... EZ67: =IF(AND(EZ$1>=$O67,EZ$1<=$Q67),$G67*IF(EZ$1<=$W67,$AD67*($AF67+$AE67*(2*INT((EZ$1-$O67))/$U67+$AD67)),IF(EZ$1<=$X67,$Y67,IF(EZ$1<=$U67+$O67,$AD67*($AH67+$AG67*(2*INT((EZ$1-$O67))/$U67+$AD67)),0))),0) -> 0
E69: ="Total "&E62 -> Total Site Work | G69: =SUM(G63:G68) -> 775000 | K69: =SUM(K63:K68) -> 624.26613 | L69: =SUM(L63:L68) -> 1.0226662 | M69: =SUM(M63:M68) -> 1.8077277 | AJ69: =SUM(AJ63:AJ68) -> 0 | AK69: =SUM(AK63:AK68) -> 100000 | AL69: =SUM(AL63:AL68) -> 53571.429 | AM69: =SUM(AM63:AM68) -> 75000 | AN69: =SUM(AN63:AN68) -> 96428.571 | AO69: =SUM(AO63:AO68) -> 75000 | AP69: =SUM(AP63:AP68) -> 0 | AQ69: =SUM(AQ63:AQ68) -> 0 | ... EZ69: =SUM(EZ63:EZ68) -> 0
D71: 5 | E71: Construction Costs
E73: =OFFSET(E73,-1,0)+1 -> 1 | F73: Sitework & Other | G73: =H73*J73 -> 11411195 | H73: 11411195 | I73: Amount | J73: =INDEX(FACTOR_VALUES,MATCH(I73,FACTOR_NAMES,0),1) -> 1 | K73: =+$G73/Beds -> 9191.7714 | L73: =+$G73/$H$15 -> 15.057864 | M73: =+$G73/$H$16 -> 26.617206 | N73: =EOMONTH($M$7,O73-2)+1 -> 46784 | O73: =$N$8 -> 2 | P73: =$O$8 -> 30 | Q73: =O73-1+P73 -> 31 | R73: Curve-End | U73: =+P73 -> 30 | V73: =+R73 -> Curve-End | W73: =INT(U73*AB73)+O73-1 -> 23 | X73: =(U73-INT(U73*(1-AB73)))+O73-1 -> 24 | Y73: =(AB73-(W73-O73+1)/U73)*(AF73+AE73*(2*(W73-O73+1)/U73+(AB73-(W73-O73+1)/U73)))+((X73-O73+1)/U73-AB73)*(AH73+AG73*(2*AB73+((X73-O73+1)/U73-AB73))) -> 0.046984127 | Z73: =IF(V73="curve-front",1,IF(V73="curve-end",3,2)) -> 3 | AA73: =IF(OR(V73="curve-front",V73="curve-mid",V73="curve-end"),2.5,1) -> 2.5 | AB73: =Z73/4 -> 0.75 | AC73: =AA73-1 -> 1.5 | AD73: =1/U73 -> 0.033333333 | AE73: =AC73/(AB73*(2+AC73)) -> 0.57142857 | AF73: =2/(2+AC73) -> 0.57142857 | AG73: =-AC73/(2+AC73)/(1-AB73) -> -1.7142857 | AH73: =2*(1-AB73+AC73)/(2+AC73)/(1-AB73) -> 4 | AJ73: =IF(AND(AJ$1>=$O73,AJ$1<=$Q73),$G73*IF(AJ$1<=$W73,$AD73*($AF73+$AE73*(2*INT((AJ$1-$O73))/$U73+$AD73)),IF(AJ$1<=$X73,$Y73,IF(AJ$1<=$U73+$O73,$AD73*($AH73+$AG73*(2*INT((AJ$1-$O73))/$U73+$AD73)),0))),0) -> 0 | AK73: =IF(AND(AK$1>=$O73,AK$1<=$Q73),$G73*IF(AK$1<=$W73,$AD73*($AF73+$AE73*(2*INT((AK$1-$O73))/$U73+$AD73)),IF(AK$1<=$X73,$Y73,IF(AK$1<=$U73+$O73,$AD73*($AH73+$AG73*(2*INT((AK$1-$O73))/$U73+$AD73)),0))),0) -> 0 | AL73: =IF(AND(AL$1>=$O73,AL$1<=$Q73),$G73*IF(AL$1<=$W73,$AD73*($AF73+$AE73*(2*INT((AL$1-$O73))/$U73+$AD73)),IF(AL$1<=$X73,$Y73,IF(AL$1<=$U73+$O73,$AD73*($AH73+$AG73*(2*INT((AL$1-$O73))/$U73+$AD73)),0))),0) -> 224601.31 | AM73: =IF(AND(AM$1>=$O73,AM$1<=$Q73),$G73*IF(AM$1<=$W73,$AD73*($AF73+$AE73*(2*INT((AM$1-$O73))/$U73+$AD73)),IF(AM$1<=$X73,$Y73,IF(AM$1<=$U73+$O73,$AD73*($AH73+$AG73*(2*INT((AM$1-$O73))/$U73+$AD73)),0))),0) -> 239091.71 | AN73: =IF(AND(AN$1>=$O73,AN$1<=$Q73),$G73*IF(AN$1<=$W73,$AD73*($AF73+$AE73*(2*INT((AN$1-$O73))/$U73+$AD73)),IF(AN$1<=$X73,$Y73,IF(AN$1<=$U73+$O73,$AD73*($AH73+$AG73*(2*INT((AN$1-$O73))/$U73+$AD73)),0))),0) -> 253582.12 | AO73: =IF(AND(AO$1>=$O73,AO$1<=$Q73),$G73*IF(AO$1<=$W73,$AD73*($AF73+$AE73*(2*INT((AO$1-$O73))/$U73+$AD73)),IF(AO$1<=$X73,$Y73,IF(AO$1<=$U73+$O73,$AD73*($AH73+$AG73*(2*INT((AO$1-$O73))/$U73+$AD73)),0))),0) -> 268072.53 | AP73: =IF(AND(AP$1>=$O73,AP$1<=$Q73),$G73*IF(AP$1<=$W73,$AD73*($AF73+$AE73*(2*INT((AP$1-$O73))/$U73+$AD73)),IF(AP$1<=$X73,$Y73,IF(AP$1<=$U73+$O73,$AD73*($AH73+$AG73*(2*INT((AP$1-$O73))/$U73+$AD73)),0))),0) -> 282562.93 | AQ73: =IF(AND(AQ$1>=$O73,AQ$1<=$Q73),$G73*IF(AQ$1<=$W73,$AD73*($AF73+$AE73*(2*INT((AQ$1-$O73))/$U73+$AD73)),IF(AQ$1<=$X73,$Y73,IF(AQ$1<=$U73+$O73,$AD73*($AH73+$AG73*(2*INT((AQ$1-$O73))/$U73+$AD73)),0))),0) -> 297053.34 | ... EZ73: =IF(AND(EZ$1>=$O73,EZ$1<=$Q73),$G73*IF(EZ$1<=$W73,$AD73*($AF73+$AE73*(2*INT((EZ$1-$O73))/$U73+$AD73)),IF(EZ$1<=$X73,$Y73,IF(EZ$1<=$U73+$O73,$AD73*($AH73+$AG73*(2*INT((EZ$1-$O73))/$U73+$AD73)),0))),0) -> 0
E74: =OFFSET(E74,-1,0)+1 -> 2 | F74: Residential | G74: =H74*J74 -> 113489794 | H74: 113489794 | I74: Amount | J74: =INDEX(FACTOR_VALUES,MATCH(I74,FACTOR_NAMES,0),1) -> 1 | K74: =+$G74/Beds -> 91416.561 | L74: =+$G74/$H$15 -> 149.75765 | M74: =+$G74/$H$16 -> 264.72084 | N74: =EOMONTH($M$7,O74-2)+1 -> 46784 | O74: =$N$8 -> 2 | P74: =$O$8 -> 30 | Q74: =O74-1+P74 -> 31 | R74: Curve-End | U74: =+P74 -> 30 | V74: =+R74 -> Curve-End | W74: =INT(U74*AB74)+O74-1 -> 23 | X74: =(U74-INT(U74*(1-AB74)))+O74-1 -> 24 | Y74: =(AB74-(W74-O74+1)/U74)*(AF74+AE74*(2*(W74-O74+1)/U74+(AB74-(W74-O74+1)/U74)))+((X74-O74+1)/U74-AB74)*(AH74+AG74*(2*AB74+((X74-O74+1)/U74-AB74))) -> 0.046984127 | Z74: =IF(V74="curve-front",1,IF(V74="curve-end",3,2)) -> 3 | AA74: =IF(OR(V74="curve-front",V74="curve-mid",V74="curve-end"),2.5,1) -> 2.5 | AB74: =Z74/4 -> 0.75 | AC74: =AA74-1 -> 1.5 | AD74: =1/U74 -> 0.033333333 | AE74: =AC74/(AB74*(2+AC74)) -> 0.57142857 | AF74: =2/(2+AC74) -> 0.57142857 | AG74: =-AC74/(2+AC74)/(1-AB74) -> -1.7142857 | AH74: =2*(1-AB74+AC74)/(2+AC74)/(1-AB74) -> 4 | AJ74: =IF(AND(AJ$1>=$O74,AJ$1<=$Q74),$G74*IF(AJ$1<=$W74,$AD74*($AF74+$AE74*(2*INT((AJ$1-$O74))/$U74+$AD74)),IF(AJ$1<=$X74,$Y74,IF(AJ$1<=$U74+$O74,$AD74*($AH74+$AG74*(2*INT((AJ$1-$O74))/$U74+$AD74)),0))),0) -> 0 | AK74: =IF(AND(AK$1>=$O74,AK$1<=$Q74),$G74*IF(AK$1<=$W74,$AD74*($AF74+$AE74*(2*INT((AK$1-$O74))/$U74+$AD74)),IF(AK$1<=$X74,$Y74,IF(AK$1<=$U74+$O74,$AD74*($AH74+$AG74*(2*INT((AK$1-$O74))/$U74+$AD74)),0))),0) -> 0 | AL74: =IF(AND(AL$1>=$O74,AL$1<=$Q74),$G74*IF(AL$1<=$W74,$AD74*($AF74+$AE74*(2*INT((AL$1-$O74))/$U74+$AD74)),IF(AL$1<=$X74,$Y74,IF(AL$1<=$U74+$O74,$AD74*($AH74+$AG74*(2*INT((AL$1-$O74))/$U74+$AD74)),0))),0) -> 2233767.4 | AM74: =IF(AND(AM$1>=$O74,AM$1<=$Q74),$G74*IF(AM$1<=$W74,$AD74*($AF74+$AE74*(2*INT((AM$1-$O74))/$U74+$AD74)),IF(AM$1<=$X74,$Y74,IF(AM$1<=$U74+$O74,$AD74*($AH74+$AG74*(2*INT((AM$1-$O74))/$U74+$AD74)),0))),0) -> 2377881.4 | AN74: =IF(AND(AN$1>=$O74,AN$1<=$Q74),$G74*IF(AN$1<=$W74,$AD74*($AF74+$AE74*(2*INT((AN$1-$O74))/$U74+$AD74)),IF(AN$1<=$X74,$Y74,IF(AN$1<=$U74+$O74,$AD74*($AH74+$AG74*(2*INT((AN$1-$O74))/$U74+$AD74)),0))),0) -> 2521995.4 | AO74: =IF(AND(AO$1>=$O74,AO$1<=$Q74),$G74*IF(AO$1<=$W74,$AD74*($AF74+$AE74*(2*INT((AO$1-$O74))/$U74+$AD74)),IF(AO$1<=$X74,$Y74,IF(AO$1<=$U74+$O74,$AD74*($AH74+$AG74*(2*INT((AO$1-$O74))/$U74+$AD74)),0))),0) -> 2666109.4 | AP74: =IF(AND(AP$1>=$O74,AP$1<=$Q74),$G74*IF(AP$1<=$W74,$AD74*($AF74+$AE74*(2*INT((AP$1-$O74))/$U74+$AD74)),IF(AP$1<=$X74,$Y74,IF(AP$1<=$U74+$O74,$AD74*($AH74+$AG74*(2*INT((AP$1-$O74))/$U74+$AD74)),0))),0) -> 2810223.5 | AQ74: =IF(AND(AQ$1>=$O74,AQ$1<=$Q74),$G74*IF(AQ$1<=$W74,$AD74*($AF74+$AE74*(2*INT((AQ$1-$O74))/$U74+$AD74)),IF(AQ$1<=$X74,$Y74,IF(AQ$1<=$U74+$O74,$AD74*($AH74+$AG74*(2*INT((AQ$1-$O74))/$U74+$AD74)),0))),0) -> 2954337.5 | ... EZ74: =IF(AND(EZ$1>=$O74,EZ$1<=$Q74),$G74*IF(EZ$1<=$W74,$AD74*($AF74+$AE74*(2*INT((EZ$1-$O74))/$U74+$AD74)),IF(EZ$1<=$X74,$Y74,IF(EZ$1<=$U74+$O74,$AD74*($AH74+$AG74*(2*INT((EZ$1-$O74))/$U74+$AD74)),0))),0) -> 0
E75: =OFFSET(E75,-1,0)+1 -> 3 | F75: Amenity & Leasing | G75: =H75*J75 -> 8742954 | H75: 8742954 | I75: Amount | J75: =INDEX(FACTOR_VALUES,MATCH(I75,FACTOR_NAMES,0),1) -> 1 | K75: =+$G75/Beds -> 7042.4904 | L75: =+$G75/$H$15 -> 11.536934 | M75: =+$G75/$H$16 -> 20.393394 | N75: =EOMONTH($M$7,O75-2)+1 -> 46784 | O75: =$N$8 -> 2 | P75: =$O$8 -> 30 | Q75: =O75-1+P75 -> 31 | R75: Curve-End | U75: =+P75 -> 30 | V75: =+R75 -> Curve-End | W75: =INT(U75*AB75)+O75-1 -> 23 | X75: =(U75-INT(U75*(1-AB75)))+O75-1 -> 24 | Y75: =(AB75-(W75-O75+1)/U75)*(AF75+AE75*(2*(W75-O75+1)/U75+(AB75-(W75-O75+1)/U75)))+((X75-O75+1)/U75-AB75)*(AH75+AG75*(2*AB75+((X75-O75+1)/U75-AB75))) -> 0.046984127 | Z75: =IF(V75="curve-front",1,IF(V75="curve-end",3,2)) -> 3 | AA75: =IF(OR(V75="curve-front",V75="curve-mid",V75="curve-end"),2.5,1) -> 2.5 | AB75: =Z75/4 -> 0.75 | AC75: =AA75-1 -> 1.5 | AD75: =1/U75 -> 0.033333333 | AE75: =AC75/(AB75*(2+AC75)) -> 0.57142857 | AF75: =2/(2+AC75) -> 0.57142857 | AG75: =-AC75/(2+AC75)/(1-AB75) -> -1.7142857 | AH75: =2*(1-AB75+AC75)/(2+AC75)/(1-AB75) -> 4 | AJ75: =IF(AND(AJ$1>=$O75,AJ$1<=$Q75),$G75*IF(AJ$1<=$W75,$AD75*($AF75+$AE75*(2*INT((AJ$1-$O75))/$U75+$AD75)),IF(AJ$1<=$X75,$Y75,IF(AJ$1<=$U75+$O75,$AD75*($AH75+$AG75*(2*INT((AJ$1-$O75))/$U75+$AD75)),0))),0) -> 0 | AK75: =IF(AND(AK$1>=$O75,AK$1<=$Q75),$G75*IF(AK$1<=$W75,$AD75*($AF75+$AE75*(2*INT((AK$1-$O75))/$U75+$AD75)),IF(AK$1<=$X75,$Y75,IF(AK$1<=$U75+$O75,$AD75*($AH75+$AG75*(2*INT((AK$1-$O75))/$U75+$AD75)),0))),0) -> 0 | AL75: =IF(AND(AL$1>=$O75,AL$1<=$Q75),$G75*IF(AL$1<=$W75,$AD75*($AF75+$AE75*(2*INT((AL$1-$O75))/$U75+$AD75)),IF(AL$1<=$X75,$Y75,IF(AL$1<=$U75+$O75,$AD75*($AH75+$AG75*(2*INT((AL$1-$O75))/$U75+$AD75)),0))),0) -> 172083.54 | AM75: =IF(AND(AM$1>=$O75,AM$1<=$Q75),$G75*IF(AM$1<=$W75,$AD75*($AF75+$AE75*(2*INT((AM$1-$O75))/$U75+$AD75)),IF(AM$1<=$X75,$Y75,IF(AM$1<=$U75+$O75,$AD75*($AH75+$AG75*(2*INT((AM$1-$O75))/$U75+$AD75)),0))),0) -> 183185.7 | AN75: =IF(AND(AN$1>=$O75,AN$1<=$Q75),$G75*IF(AN$1<=$W75,$AD75*($AF75+$AE75*(2*INT((AN$1-$O75))/$U75+$AD75)),IF(AN$1<=$X75,$Y75,IF(AN$1<=$U75+$O75,$AD75*($AH75+$AG75*(2*INT((AN$1-$O75))/$U75+$AD75)),0))),0) -> 194287.87 | AO75: =IF(AND(AO$1>=$O75,AO$1<=$Q75),$G75*IF(AO$1<=$W75,$AD75*($AF75+$AE75*(2*INT((AO$1-$O75))/$U75+$AD75)),IF(AO$1<=$X75,$Y75,IF(AO$1<=$U75+$O75,$AD75*($AH75+$AG75*(2*INT((AO$1-$O75))/$U75+$AD75)),0))),0) -> 205390.03 | AP75: =IF(AND(AP$1>=$O75,AP$1<=$Q75),$G75*IF(AP$1<=$W75,$AD75*($AF75+$AE75*(2*INT((AP$1-$O75))/$U75+$AD75)),IF(AP$1<=$X75,$Y75,IF(AP$1<=$U75+$O75,$AD75*($AH75+$AG75*(2*INT((AP$1-$O75))/$U75+$AD75)),0))),0) -> 216492.19 | AQ75: =IF(AND(AQ$1>=$O75,AQ$1<=$Q75),$G75*IF(AQ$1<=$W75,$AD75*($AF75+$AE75*(2*INT((AQ$1-$O75))/$U75+$AD75)),IF(AQ$1<=$X75,$Y75,IF(AQ$1<=$U75+$O75,$AD75*($AH75+$AG75*(2*INT((AQ$1-$O75))/$U75+$AD75)),0))),0) -> 227594.36 | ... EZ75: =IF(AND(EZ$1>=$O75,EZ$1<=$Q75),$G75*IF(EZ$1<=$W75,$AD75*($AF75+$AE75*(2*INT((EZ$1-$O75))/$U75+$AD75)),IF(EZ$1<=$X75,$Y75,IF(EZ$1<=$U75+$O75,$AD75*($AH75+$AG75*(2*INT((EZ$1-$O75))/$U75+$AD75)),0))),0) -> 0
E76: =OFFSET(E76,-1,0)+1 -> 4 | F76: Parking Structure | G76: =H76*J76 -> 23051358 | H76: 23051358 | I76: Amount | J76: =INDEX(FACTOR_VALUES,MATCH(I76,FACTOR_NAMES,0),1) -> 1 | K76: =+$G76/Beds -> 18567.977 | L76: =+$G76/$H$15 -> 30.417865 | M76: =+$G76/$H$16 -> 53.76849 | N76: =EOMONTH($M$7,O76-2)+1 -> 46784 | O76: =$N$8 -> 2 | P76: =$O$8 -> 30 | Q76: =O76-1+P76 -> 31 | R76: Curve-End | U76: =+P76 -> 30 | V76: =+R76 -> Curve-End | W76: =INT(U76*AB76)+O76-1 -> 23 | X76: =(U76-INT(U76*(1-AB76)))+O76-1 -> 24 | Y76: =(AB76-(W76-O76+1)/U76)*(AF76+AE76*(2*(W76-O76+1)/U76+(AB76-(W76-O76+1)/U76)))+((X76-O76+1)/U76-AB76)*(AH76+AG76*(2*AB76+((X76-O76+1)/U76-AB76))) -> 0.046984127 | Z76: =IF(V76="curve-front",1,IF(V76="curve-end",3,2)) -> 3 | AA76: =IF(OR(V76="curve-front",V76="curve-mid",V76="curve-end"),2.5,1) -> 2.5 | AB76: =Z76/4 -> 0.75 | AC76: =AA76-1 -> 1.5 | AD76: =1/U76 -> 0.033333333 | AE76: =AC76/(AB76*(2+AC76)) -> 0.57142857 | AF76: =2/(2+AC76) -> 0.57142857 | AG76: =-AC76/(2+AC76)/(1-AB76) -> -1.7142857 | AH76: =2*(1-AB76+AC76)/(2+AC76)/(1-AB76) -> 4 | AJ76: =IF(AND(AJ$1>=$O76,AJ$1<=$Q76),$G76*IF(AJ$1<=$W76,$AD76*($AF76+$AE76*(2*INT((AJ$1-$O76))/$U76+$AD76)),IF(AJ$1<=$X76,$Y76,IF(AJ$1<=$U76+$O76,$AD76*($AH76+$AG76*(2*INT((AJ$1-$O76))/$U76+$AD76)),0))),0) -> 0 | AK76: =IF(AND(AK$1>=$O76,AK$1<=$Q76),$G76*IF(AK$1<=$W76,$AD76*($AF76+$AE76*(2*INT((AK$1-$O76))/$U76+$AD76)),IF(AK$1<=$X76,$Y76,IF(AK$1<=$U76+$O76,$AD76*($AH76+$AG76*(2*INT((AK$1-$O76))/$U76+$AD76)),0))),0) -> 0 | AL76: =IF(AND(AL$1>=$O76,AL$1<=$Q76),$G76*IF(AL$1<=$W76,$AD76*($AF76+$AE76*(2*INT((AL$1-$O76))/$U76+$AD76)),IF(AL$1<=$X76,$Y76,IF(AL$1<=$U76+$O76,$AD76*($AH76+$AG76*(2*INT((AL$1-$O76))/$U76+$AD76)),0))),0) -> 453709.27 | AM76: =IF(AND(AM$1>=$O76,AM$1<=$Q76),$G76*IF(AM$1<=$W76,$AD76*($AF76+$AE76*(2*INT((AM$1-$O76))/$U76+$AD76)),IF(AM$1<=$X76,$Y76,IF(AM$1<=$U76+$O76,$AD76*($AH76+$AG76*(2*INT((AM$1-$O76))/$U76+$AD76)),0))),0) -> 482980.83 | AN76: =IF(AND(AN$1>=$O76,AN$1<=$Q76),$G76*IF(AN$1<=$W76,$AD76*($AF76+$AE76*(2*INT((AN$1-$O76))/$U76+$AD76)),IF(AN$1<=$X76,$Y76,IF(AN$1<=$U76+$O76,$AD76*($AH76+$AG76*(2*INT((AN$1-$O76))/$U76+$AD76)),0))),0) -> 512252.4 | AO76: =IF(AND(AO$1>=$O76,AO$1<=$Q76),$G76*IF(AO$1<=$W76,$AD76*($AF76+$AE76*(2*INT((AO$1-$O76))/$U76+$AD76)),IF(AO$1<=$X76,$Y76,IF(AO$1<=$U76+$O76,$AD76*($AH76+$AG76*(2*INT((AO$1-$O76))/$U76+$AD76)),0))),0) -> 541523.97 | AP76: =IF(AND(AP$1>=$O76,AP$1<=$Q76),$G76*IF(AP$1<=$W76,$AD76*($AF76+$AE76*(2*INT((AP$1-$O76))/$U76+$AD76)),IF(AP$1<=$X76,$Y76,IF(AP$1<=$U76+$O76,$AD76*($AH76+$AG76*(2*INT((AP$1-$O76))/$U76+$AD76)),0))),0) -> 570795.53 | AQ76: =IF(AND(AQ$1>=$O76,AQ$1<=$Q76),$G76*IF(AQ$1<=$W76,$AD76*($AF76+$AE76*(2*INT((AQ$1-$O76))/$U76+$AD76)),IF(AQ$1<=$X76,$Y76,IF(AQ$1<=$U76+$O76,$AD76*($AH76+$AG76*(2*INT((AQ$1-$O76))/$U76+$AD76)),0))),0) -> 600067.1 | ... EZ76: =IF(AND(EZ$1>=$O76,EZ$1<=$Q76),$G76*IF(EZ$1<=$W76,$AD76*($AF76+$AE76*(2*INT((EZ$1-$O76))/$U76+$AD76)),IF(EZ$1<=$X76,$Y76,IF(EZ$1<=$U76+$O76,$AD76*($AH76+$AG76*(2*INT((EZ$1-$O76))/$U76+$AD76)),0))),0) -> 0
E77: =OFFSET(E77,-1,0)+1 -> 5 | F77: Commercial | G77: =H77*J77 -> 471504 | H77: 471504 | I77: Amount | J77: =INDEX(FACTOR_VALUES,MATCH(I77,FACTOR_NAMES,0),1) -> 1 | K77: =+$G77/Beds -> 379.79868 | L77: =+$G77/$H$15 -> 0.62218222 | M77: =+$G77/$H$16 -> 1.0998076 | N77: =EOMONTH($M$7,O77-2)+1 -> 46784 | O77: =$N$8 -> 2 | P77: =$O$8 -> 30 | Q77: =O77-1+P77 -> 31 | R77: Curve-End | U77: =+P77 -> 30 | V77: =+R77 -> Curve-End | W77: =INT(U77*AB77)+O77-1 -> 23 | X77: =(U77-INT(U77*(1-AB77)))+O77-1 -> 24 | Y77: =(AB77-(W77-O77+1)/U77)*(AF77+AE77*(2*(W77-O77+1)/U77+(AB77-(W77-O77+1)/U77)))+((X77-O77+1)/U77-AB77)*(AH77+AG77*(2*AB77+((X77-O77+1)/U77-AB77))) -> 0.046984127 | Z77: =IF(V77="curve-front",1,IF(V77="curve-end",3,2)) -> 3 | AA77: =IF(OR(V77="curve-front",V77="curve-mid",V77="curve-end"),2.5,1) -> 2.5 | AB77: =Z77/4 -> 0.75 | AC77: =AA77-1 -> 1.5 | AD77: =1/U77 -> 0.033333333 | AE77: =AC77/(AB77*(2+AC77)) -> 0.57142857 | AF77: =2/(2+AC77) -> 0.57142857 | AG77: =-AC77/(2+AC77)/(1-AB77) -> -1.7142857 | AH77: =2*(1-AB77+AC77)/(2+AC77)/(1-AB77) -> 4 | AJ77: =IF(AND(AJ$1>=$O77,AJ$1<=$Q77),$G77*IF(AJ$1<=$W77,$AD77*($AF77+$AE77*(2*INT((AJ$1-$O77))/$U77+$AD77)),IF(AJ$1<=$X77,$Y77,IF(AJ$1<=$U77+$O77,$AD77*($AH77+$AG77*(2*INT((AJ$1-$O77))/$U77+$AD77)),0))),0) -> 0 | AK77: =IF(AND(AK$1>=$O77,AK$1<=$Q77),$G77*IF(AK$1<=$W77,$AD77*($AF77+$AE77*(2*INT((AK$1-$O77))/$U77+$AD77)),IF(AK$1<=$X77,$Y77,IF(AK$1<=$U77+$O77,$AD77*($AH77+$AG77*(2*INT((AK$1-$O77))/$U77+$AD77)),0))),0) -> 0 | AL77: =IF(AND(AL$1>=$O77,AL$1<=$Q77),$G77*IF(AL$1<=$W77,$AD77*($AF77+$AE77*(2*INT((AL$1-$O77))/$U77+$AD77)),IF(AL$1<=$X77,$Y77,IF(AL$1<=$U77+$O77,$AD77*($AH77+$AG77*(2*INT((AL$1-$O77))/$U77+$AD77)),0))),0) -> 9280.3962 | AM77: =IF(AND(AM$1>=$O77,AM$1<=$Q77),$G77*IF(AM$1<=$W77,$AD77*($AF77+$AE77*(2*INT((AM$1-$O77))/$U77+$AD77)),IF(AM$1<=$X77,$Y77,IF(AM$1<=$U77+$O77,$AD77*($AH77+$AG77*(2*INT((AM$1-$O77))/$U77+$AD77)),0))),0) -> 9879.1314 | AN77: =IF(AND(AN$1>=$O77,AN$1<=$Q77),$G77*IF(AN$1<=$W77,$AD77*($AF77+$AE77*(2*INT((AN$1-$O77))/$U77+$AD77)),IF(AN$1<=$X77,$Y77,IF(AN$1<=$U77+$O77,$AD77*($AH77+$AG77*(2*INT((AN$1-$O77))/$U77+$AD77)),0))),0) -> 10477.867 | AO77: =IF(AND(AO$1>=$O77,AO$1<=$Q77),$G77*IF(AO$1<=$W77,$AD77*($AF77+$AE77*(2*INT((AO$1-$O77))/$U77+$AD77)),IF(AO$1<=$X77,$Y77,IF(AO$1<=$U77+$O77,$AD77*($AH77+$AG77*(2*INT((AO$1-$O77))/$U77+$AD77)),0))),0) -> 11076.602 | AP77: =IF(AND(AP$1>=$O77,AP$1<=$Q77),$G77*IF(AP$1<=$W77,$AD77*($AF77+$AE77*(2*INT((AP$1-$O77))/$U77+$AD77)),IF(AP$1<=$X77,$Y77,IF(AP$1<=$U77+$O77,$AD77*($AH77+$AG77*(2*INT((AP$1-$O77))/$U77+$AD77)),0))),0) -> 11675.337 | AQ77: =IF(AND(AQ$1>=$O77,AQ$1<=$Q77),$G77*IF(AQ$1<=$W77,$AD77*($AF77+$AE77*(2*INT((AQ$1-$O77))/$U77+$AD77)),IF(AQ$1<=$X77,$Y77,IF(AQ$1<=$U77+$O77,$AD77*($AH77+$AG77*(2*INT((AQ$1-$O77))/$U77+$AD77)),0))),0) -> 12274.072 | ... EZ77: =IF(AND(EZ$1>=$O77,EZ$1<=$Q77),$G77*IF(EZ$1<=$W77,$AD77*($AF77+$AE77*(2*INT((EZ$1-$O77))/$U77+$AD77)),IF(EZ$1<=$X77,$Y77,IF(EZ$1<=$U77+$O77,$AD77*($AH77+$AG77*(2*INT((EZ$1-$O77))/$U77+$AD77)),0))),0) -> 0
E78: =OFFSET(E78,-1,0)+1 -> 6 | F78: Amenity Deck & Pool | G78: =H78*J78 -> 3680270 | H78: 3680270 | I78: Amount | J78: =INDEX(FACTOR_VALUES,MATCH(I78,FACTOR_NAMES,0),1) -> 1 | K78: =+$G78/Beds -> 2964.4747 | L78: =+$G78/$H$15 -> 4.8563715 | M78: =+$G78/$H$16 -> 8.5844209 | N78: =EOMONTH($M$7,O78-2)+1 -> 46784 | O78: =$N$8 -> 2 | P78: =$O$8 -> 30 | Q78: =O78-1+P78 -> 31 | R78: Curve-End | U78: =+P78 -> 30 | V78: =+R78 -> Curve-End | W78: =INT(U78*AB78)+O78-1 -> 23 | X78: =(U78-INT(U78*(1-AB78)))+O78-1 -> 24 | Y78: =(AB78-(W78-O78+1)/U78)*(AF78+AE78*(2*(W78-O78+1)/U78+(AB78-(W78-O78+1)/U78)))+((X78-O78+1)/U78-AB78)*(AH78+AG78*(2*AB78+((X78-O78+1)/U78-AB78))) -> 0.046984127 | Z78: =IF(V78="curve-front",1,IF(V78="curve-end",3,2)) -> 3 | AA78: =IF(OR(V78="curve-front",V78="curve-mid",V78="curve-end"),2.5,1) -> 2.5 | AB78: =Z78/4 -> 0.75 | AC78: =AA78-1 -> 1.5 | AD78: =1/U78 -> 0.033333333 | AE78: =AC78/(AB78*(2+AC78)) -> 0.57142857 | AF78: =2/(2+AC78) -> 0.57142857 | AG78: =-AC78/(2+AC78)/(1-AB78) -> -1.7142857 | AH78: =2*(1-AB78+AC78)/(2+AC78)/(1-AB78) -> 4 | AJ78: =IF(AND(AJ$1>=$O78,AJ$1<=$Q78),$G78*IF(AJ$1<=$W78,$AD78*($AF78+$AE78*(2*INT((AJ$1-$O78))/$U78+$AD78)),IF(AJ$1<=$X78,$Y78,IF(AJ$1<=$U78+$O78,$AD78*($AH78+$AG78*(2*INT((AJ$1-$O78))/$U78+$AD78)),0))),0) -> 0 | AK78: =IF(AND(AK$1>=$O78,AK$1<=$Q78),$G78*IF(AK$1<=$W78,$AD78*($AF78+$AE78*(2*INT((AK$1-$O78))/$U78+$AD78)),IF(AK$1<=$X78,$Y78,IF(AK$1<=$U78+$O78,$AD78*($AH78+$AG78*(2*INT((AK$1-$O78))/$U78+$AD78)),0))),0) -> 0 | AL78: =IF(AND(AL$1>=$O78,AL$1<=$Q78),$G78*IF(AL$1<=$W78,$AD78*($AF78+$AE78*(2*INT((AL$1-$O78))/$U78+$AD78)),IF(AL$1<=$X78,$Y78,IF(AL$1<=$U78+$O78,$AD78*($AH78+$AG78*(2*INT((AL$1-$O78))/$U78+$AD78)),0))),0) -> 72437.06 | AM78: =IF(AND(AM$1>=$O78,AM$1<=$Q78),$G78*IF(AM$1<=$W78,$AD78*($AF78+$AE78*(2*INT((AM$1-$O78))/$U78+$AD78)),IF(AM$1<=$X78,$Y78,IF(AM$1<=$U78+$O78,$AD78*($AH78+$AG78*(2*INT((AM$1-$O78))/$U78+$AD78)),0))),0) -> 77110.419 | AN78: =IF(AND(AN$1>=$O78,AN$1<=$Q78),$G78*IF(AN$1<=$W78,$AD78*($AF78+$AE78*(2*INT((AN$1-$O78))/$U78+$AD78)),IF(AN$1<=$X78,$Y78,IF(AN$1<=$U78+$O78,$AD78*($AH78+$AG78*(2*INT((AN$1-$O78))/$U78+$AD78)),0))),0) -> 81783.778 | AO78: =IF(AND(AO$1>=$O78,AO$1<=$Q78),$G78*IF(AO$1<=$W78,$AD78*($AF78+$AE78*(2*INT((AO$1-$O78))/$U78+$AD78)),IF(AO$1<=$X78,$Y78,IF(AO$1<=$U78+$O78,$AD78*($AH78+$AG78*(2*INT((AO$1-$O78))/$U78+$AD78)),0))),0) -> 86457.137 | AP78: =IF(AND(AP$1>=$O78,AP$1<=$Q78),$G78*IF(AP$1<=$W78,$AD78*($AF78+$AE78*(2*INT((AP$1-$O78))/$U78+$AD78)),IF(AP$1<=$X78,$Y78,IF(AP$1<=$U78+$O78,$AD78*($AH78+$AG78*(2*INT((AP$1-$O78))/$U78+$AD78)),0))),0) -> 91130.495 | AQ78: =IF(AND(AQ$1>=$O78,AQ$1<=$Q78),$G78*IF(AQ$1<=$W78,$AD78*($AF78+$AE78*(2*INT((AQ$1-$O78))/$U78+$AD78)),IF(AQ$1<=$X78,$Y78,IF(AQ$1<=$U78+$O78,$AD78*($AH78+$AG78*(2*INT((AQ$1-$O78))/$U78+$AD78)),0))),0) -> 95803.854 | ... EZ78: =IF(AND(EZ$1>=$O78,EZ$1<=$Q78),$G78*IF(EZ$1<=$W78,$AD78*($AF78+$AE78*(2*INT((EZ$1-$O78))/$U78+$AD78)),IF(EZ$1<=$X78,$Y78,IF(EZ$1<=$U78+$O78,$AD78*($AH78+$AG78*(2*INT((EZ$1-$O78))/$U78+$AD78)),0))),0) -> 0
E79: =OFFSET(E79,-1,0)+1 -> 7 | G79: =H79*J79 -> 0 | H79: 0 | I79: Amount | J79: =INDEX(FACTOR_VALUES,MATCH(I79,FACTOR_NAMES,0),1) -> 1 | K79: =+$G79/Units -> 0 | L79: =+$G79/$H$15 -> 0 | M79: =+$G79/$H$16 -> 0 | N79: =EOMONTH($M$7,O79-2)+1 -> 46784 | O79: =$N$8 -> 2 | P79: =$O$8 -> 30 | Q79: =O79-1+P79 -> 31 | R79: Curve-End | U79: =+P79 -> 30 | V79: =+R79 -> Curve-End | W79: =INT(U79*AB79)+O79-1 -> 23 | X79: =(U79-INT(U79*(1-AB79)))+O79-1 -> 24 | Y79: =(AB79-(W79-O79+1)/U79)*(AF79+AE79*(2*(W79-O79+1)/U79+(AB79-(W79-O79+1)/U79)))+((X79-O79+1)/U79-AB79)*(AH79+AG79*(2*AB79+((X79-O79+1)/U79-AB79))) -> 0.046984127 | Z79: =IF(V79="curve-front",1,IF(V79="curve-end",3,2)) -> 3 | AA79: =IF(OR(V79="curve-front",V79="curve-mid",V79="curve-end"),2.5,1) -> 2.5 | AB79: =Z79/4 -> 0.75 | AC79: =AA79-1 -> 1.5 | AD79: =1/U79 -> 0.033333333 | AE79: =AC79/(AB79*(2+AC79)) -> 0.57142857 | AF79: =2/(2+AC79) -> 0.57142857 | AG79: =-AC79/(2+AC79)/(1-AB79) -> -1.7142857 | AH79: =2*(1-AB79+AC79)/(2+AC79)/(1-AB79) -> 4 | AJ79: =IF(AND(AJ$1>=$O79,AJ$1<=$Q79),$G79*IF(AJ$1<=$W79,$AD79*($AF79+$AE79*(2*INT((AJ$1-$O79))/$U79+$AD79)),IF(AJ$1<=$X79,$Y79,IF(AJ$1<=$U79+$O79,$AD79*($AH79+$AG79*(2*INT((AJ$1-$O79))/$U79+$AD79)),0))),0) -> 0 | AK79: =IF(AND(AK$1>=$O79,AK$1<=$Q79),$G79*IF(AK$1<=$W79,$AD79*($AF79+$AE79*(2*INT((AK$1-$O79))/$U79+$AD79)),IF(AK$1<=$X79,$Y79,IF(AK$1<=$U79+$O79,$AD79*($AH79+$AG79*(2*INT((AK$1-$O79))/$U79+$AD79)),0))),0) -> 0 | AL79: =IF(AND(AL$1>=$O79,AL$1<=$Q79),$G79*IF(AL$1<=$W79,$AD79*($AF79+$AE79*(2*INT((AL$1-$O79))/$U79+$AD79)),IF(AL$1<=$X79,$Y79,IF(AL$1<=$U79+$O79,$AD79*($AH79+$AG79*(2*INT((AL$1-$O79))/$U79+$AD79)),0))),0) -> 0 | AM79: =IF(AND(AM$1>=$O79,AM$1<=$Q79),$G79*IF(AM$1<=$W79,$AD79*($AF79+$AE79*(2*INT((AM$1-$O79))/$U79+$AD79)),IF(AM$1<=$X79,$Y79,IF(AM$1<=$U79+$O79,$AD79*($AH79+$AG79*(2*INT((AM$1-$O79))/$U79+$AD79)),0))),0) -> 0 | AN79: =IF(AND(AN$1>=$O79,AN$1<=$Q79),$G79*IF(AN$1<=$W79,$AD79*($AF79+$AE79*(2*INT((AN$1-$O79))/$U79+$AD79)),IF(AN$1<=$X79,$Y79,IF(AN$1<=$U79+$O79,$AD79*($AH79+$AG79*(2*INT((AN$1-$O79))/$U79+$AD79)),0))),0) -> 0 | AO79: =IF(AND(AO$1>=$O79,AO$1<=$Q79),$G79*IF(AO$1<=$W79,$AD79*($AF79+$AE79*(2*INT((AO$1-$O79))/$U79+$AD79)),IF(AO$1<=$X79,$Y79,IF(AO$1<=$U79+$O79,$AD79*($AH79+$AG79*(2*INT((AO$1-$O79))/$U79+$AD79)),0))),0) -> 0 | AP79: =IF(AND(AP$1>=$O79,AP$1<=$Q79),$G79*IF(AP$1<=$W79,$AD79*($AF79+$AE79*(2*INT((AP$1-$O79))/$U79+$AD79)),IF(AP$1<=$X79,$Y79,IF(AP$1<=$U79+$O79,$AD79*($AH79+$AG79*(2*INT((AP$1-$O79))/$U79+$AD79)),0))),0) -> 0 | AQ79: =IF(AND(AQ$1>=$O79,AQ$1<=$Q79),$G79*IF(AQ$1<=$W79,$AD79*($AF79+$AE79*(2*INT((AQ$1-$O79))/$U79+$AD79)),IF(AQ$1<=$X79,$Y79,IF(AQ$1<=$U79+$O79,$AD79*($AH79+$AG79*(2*INT((AQ$1-$O79))/$U79+$AD79)),0))),0) -> 0 | ... EZ79: =IF(AND(EZ$1>=$O79,EZ$1<=$Q79),$G79*IF(EZ$1<=$W79,$AD79*($AF79+$AE79*(2*INT((EZ$1-$O79))/$U79+$AD79)),IF(EZ$1<=$X79,$Y79,IF(EZ$1<=$U79+$O79,$AD79*($AH79+$AG79*(2*INT((EZ$1-$O79))/$U79+$AD79)),0))),0) -> 0
E81: ="Total "&E71 -> Total Construction Costs | G81: =IFERROR(SUM(G72:G80),"") -> 1.6084708e+08 | K81: =SUM(K72:K80) -> 129563.07 | L81: =SUM(L72:L80) -> 212.24887 | M81: =SUM(M72:M80) -> 375.18416 | AJ81: =SUM(AJ72:AJ80) -> 0 | AK81: =SUM(AK72:AK80) -> 0 | AL81: =SUM(AL72:AL80) -> 3165878.9 | AM81: =SUM(AM72:AM80) -> 3370129.2 | AN81: =SUM(AN72:AN80) -> 3574379.5 | AO81: =SUM(AO72:AO80) -> 3778629.7 | AP81: =SUM(AP72:AP80) -> 3982880 | AQ81: =SUM(AQ72:AQ80) -> 4187130.2 | ... EZ81: =SUM(EZ72:EZ80) -> 0
D83: 6 | E83: Hard Cost Contingency
E85: =OFFSET(E85,-1,0)+1 -> 1 | F85: Owner Hard Cost Contingency | G85: =H85*J85 -> 8081103.8 | H85: 0.05 | I85: % of Hard Costs | J85: =INDEX(FACTOR_VALUES,MATCH(I85,FACTOR_NAMES,0),1) -> 1.6162208e+08 | K85: =+$G85/Beds -> 6509.367 | L85: =+$G85/$H$15 -> 10.663577 | M85: =+$G85/$H$16 -> 18.849594 | N85: =EOMONTH($M$7,O85-2)+1 -> 46784 | O85: =$N$8 -> 2 | P85: =$O$8 -> 30 | Q85: =O85-1+P85 -> 31 | R85: Curve-End | U85: =+P85 -> 30 | V85: =+R85 -> Curve-End | W85: =INT(U85*AB85)+O85-1 -> 23 | X85: =(U85-INT(U85*(1-AB85)))+O85-1 -> 24 | Y85: =(AB85-(W85-O85+1)/U85)*(AF85+AE85*(2*(W85-O85+1)/U85+(AB85-(W85-O85+1)/U85)))+((X85-O85+1)/U85-AB85)*(AH85+AG85*(2*AB85+((X85-O85+1)/U85-AB85))) -> 0.046984127 | Z85: =IF(V85="curve-front",1,IF(V85="curve-end",3,2)) -> 3 | AA85: =IF(OR(V85="curve-front",V85="curve-mid",V85="curve-end"),2.5,1) -> 2.5 | AB85: =Z85/4 -> 0.75 | AC85: =AA85-1 -> 1.5 | AD85: =1/U85 -> 0.033333333 | AE85: =AC85/(AB85*(2+AC85)) -> 0.57142857 | AF85: =2/(2+AC85) -> 0.57142857 | AG85: =-AC85/(2+AC85)/(1-AB85) -> -1.7142857 | AH85: =2*(1-AB85+AC85)/(2+AC85)/(1-AB85) -> 4 | AJ85: =IF(AND(AJ$1>=$O85,AJ$1<=$Q85),$G85*IF(AJ$1<=$W85,$AD85*($AF85+$AE85*(2*INT((AJ$1-$O85))/$U85+$AD85)),IF(AJ$1<=$X85,$Y85,IF(AJ$1<=$U85+$O85,$AD85*($AH85+$AG85*(2*INT((AJ$1-$O85))/$U85+$AD85)),0))),0) -> 0 | AK85: =IF(AND(AK$1>=$O85,AK$1<=$Q85),$G85*IF(AK$1<=$W85,$AD85*($AF85+$AE85*(2*INT((AK$1-$O85))/$U85+$AD85)),IF(AK$1<=$X85,$Y85,IF(AK$1<=$U85+$O85,$AD85*($AH85+$AG85*(2*INT((AK$1-$O85))/$U85+$AD85)),0))),0) -> 0 | AL85: =IF(AND(AL$1>=$O85,AL$1<=$Q85),$G85*IF(AL$1<=$W85,$AD85*($AF85+$AE85*(2*INT((AL$1-$O85))/$U85+$AD85)),IF(AL$1<=$X85,$Y85,IF(AL$1<=$U85+$O85,$AD85*($AH85+$AG85*(2*INT((AL$1-$O85))/$U85+$AD85)),0))),0) -> 159056.65 | AM85: =IF(AND(AM$1>=$O85,AM$1<=$Q85),$G85*IF(AM$1<=$W85,$AD85*($AF85+$AE85*(2*INT((AM$1-$O85))/$U85+$AD85)),IF(AM$1<=$X85,$Y85,IF(AM$1<=$U85+$O85,$AD85*($AH85+$AG85*(2*INT((AM$1-$O85))/$U85+$AD85)),0))),0) -> 169318.36 | AN85: =IF(AND(AN$1>=$O85,AN$1<=$Q85),$G85*IF(AN$1<=$W85,$AD85*($AF85+$AE85*(2*INT((AN$1-$O85))/$U85+$AD85)),IF(AN$1<=$X85,$Y85,IF(AN$1<=$U85+$O85,$AD85*($AH85+$AG85*(2*INT((AN$1-$O85))/$U85+$AD85)),0))),0) -> 179580.08 | AO85: =IF(AND(AO$1>=$O85,AO$1<=$Q85),$G85*IF(AO$1<=$W85,$AD85*($AF85+$AE85*(2*INT((AO$1-$O85))/$U85+$AD85)),IF(AO$1<=$X85,$Y85,IF(AO$1<=$U85+$O85,$AD85*($AH85+$AG85*(2*INT((AO$1-$O85))/$U85+$AD85)),0))),0) -> 189841.8 | AP85: =IF(AND(AP$1>=$O85,AP$1<=$Q85),$G85*IF(AP$1<=$W85,$AD85*($AF85+$AE85*(2*INT((AP$1-$O85))/$U85+$AD85)),IF(AP$1<=$X85,$Y85,IF(AP$1<=$U85+$O85,$AD85*($AH85+$AG85*(2*INT((AP$1-$O85))/$U85+$AD85)),0))),0) -> 200103.52 | AQ85: =IF(AND(AQ$1>=$O85,AQ$1<=$Q85),$G85*IF(AQ$1<=$W85,$AD85*($AF85+$AE85*(2*INT((AQ$1-$O85))/$U85+$AD85)),IF(AQ$1<=$X85,$Y85,IF(AQ$1<=$U85+$O85,$AD85*($AH85+$AG85*(2*INT((AQ$1-$O85))/$U85+$AD85)),0))),0) -> 210365.24 | ... EZ85: =IF(AND(EZ$1>=$O85,EZ$1<=$Q85),$G85*IF(EZ$1<=$W85,$AD85*($AF85+$AE85*(2*INT((EZ$1-$O85))/$U85+$AD85)),IF(EZ$1<=$X85,$Y85,IF(EZ$1<=$U85+$O85,$AD85*($AH85+$AG85*(2*INT((EZ$1-$O85))/$U85+$AD85)),0))),0) -> 0
E87: ="Total "&E83 -> Total Hard Cost Contingency | G87: =SUM(G84:G86) -> 8081103.8 | K87: =SUM(K84:K86) -> 6509.367 | L87: =SUM(L84:L86) -> 10.663577 | M87: =SUM(M84:M86) -> 18.849594 | AJ87: =SUM(AJ84:AJ86) -> 0 | AK87: =SUM(AK84:AK86) -> 0 | AL87: =SUM(AL84:AL86) -> 159056.65 | AM87: =SUM(AM84:AM86) -> 169318.36 | AN87: =SUM(AN84:AN86) -> 179580.08 | AO87: =SUM(AO84:AO86) -> 189841.8 | AP87: =SUM(AP84:AP86) -> 200103.52 | AQ87: =SUM(AQ84:AQ86) -> 210365.24 | ... EZ87: =SUM(EZ84:EZ86) -> 0
E89: ="TOTAL "&D61 -> TOTAL HARD COSTS | G89: =SUM(G69,G81,G87) -> 1.6970318e+08 | K89: =SUM(K69,K81,K87) -> 136696.71 | L89: =SUM(L69,L81,L87) -> 223.93511 | M89: =SUM(M69,M81,M87) -> 395.84148 | AJ89: =SUM(AJ69,AJ81,AJ87) -> 0 | AK89: =SUM(AK69,AK81,AK87) -> 100000 | AL89: =SUM(AL69,AL81,AL87) -> 3378507 | AM89: =SUM(AM69,AM81,AM87) -> 3614447.6 | AN89: =SUM(AN69,AN81,AN87) -> 3850388.1 | AO89: =SUM(AO69,AO81,AO87) -> 4043471.5 | AP89: =SUM(AP69,AP81,AP87) -> 4182983.5 | AQ89: =SUM(AQ69,AQ81,AQ87) -> 4397495.5 | ... EZ89: =SUM(EZ69,EZ81,EZ87) -> 0
K90: =+$G90/Units -> 0 | L90: =+$G90/$H$15 -> 0 | M90: =+$G90/$H$16 -> 0
D92: SOFT COSTS | H92: Unit Price | I92: Factor | J92: Units | K92: Cost/Bed | L92: Cost/GSF | M92: Cost/NSF | N92: Start Date | O92: Start Month | P92: Months | Q92: End Month | R92: Distribution | S92: Comments / Description | U92: DISTRIBUTION CALCULATIONS
D93: 7 | E93: Architectural / Engineering / Design
E95: =OFFSET(E95,-1,0)+1 -> 1 | F95: Architectural Design Fee | G95: =H95*J95 -> 2358769.6 | H95: 1900 | I95: Total Beds | J95: =INDEX(FACTOR_VALUES,MATCH(I95,FACTOR_NAMES,0),1) -> 1241.4577 | K95: =+$G95/Beds -> 1900 | L95: =+$G95/$H$15 -> 3.1125601 | M95: =+$G95/$H$16 -> 5.5019527 | N95: =EOMONTH($M$7,O95-2)+1 -> 46753 | O95: =$N$7 -> 1 | P95: 1 | Q95: =O95-1+P95 -> 1 | R95: Curve-Front | U95: =+P95 -> 1 | V95: =+R95 -> Curve-Front | W95: =INT(U95*AB95)+O95-1 -> 0 | X95: =(U95-INT(U95*(1-AB95)))+O95-1 -> 1 | Y95: =(AB95-(W95-O95+1)/U95)*(AF95+AE95*(2*(W95-O95+1)/U95+(AB95-(W95-O95+1)/U95)))+((X95-O95+1)/U95-AB95)*(AH95+AG95*(2*AB95+((X95-O95+1)/U95-AB95))) -> 1 | Z95: =IF(V95="curve-front",1,IF(V95="curve-end",3,2)) -> 1 | AA95: =IF(OR(V95="curve-front",V95="curve-mid",V95="curve-end"),2.5,1) -> 2.5 | AB95: =Z95/4 -> 0.25 | AC95: =AA95-1 -> 1.5 | AD95: =1/U95 -> 1 | AE95: =AC95/(AB95*(2+AC95)) -> 1.7142857 | AF95: =2/(2+AC95) -> 0.57142857 | AG95: =-AC95/(2+AC95)/(1-AB95) -> -0.57142857 | AH95: =2*(1-AB95+AC95)/(2+AC95)/(1-AB95) -> 1.7142857 | AJ95: =IF(AND(AJ$1>=$O95,AJ$1<=$Q95),$G95*IF(AJ$1<=$W95,$AD95*($AF95+$AE95*(2*INT((AJ$1-$O95))/$U95+$AD95)),IF(AJ$1<=$X95,$Y95,IF(AJ$1<=$U95+$O95,$AD95*($AH95+$AG95*(2*INT((AJ$1-$O95))/$U95+$AD95)),0))),0) -> 0 | AK95: =IF(AND(AK$1>=$O95,AK$1<=$Q95),$G95*IF(AK$1<=$W95,$AD95*($AF95+$AE95*(2*INT((AK$1-$O95))/$U95+$AD95)),IF(AK$1<=$X95,$Y95,IF(AK$1<=$U95+$O95,$AD95*($AH95+$AG95*(2*INT((AK$1-$O95))/$U95+$AD95)),0))),0) -> 2358769.6 | AL95: =IF(AND(AL$1>=$O95,AL$1<=$Q95),$G95*IF(AL$1<=$W95,$AD95*($AF95+$AE95*(2*INT((AL$1-$O95))/$U95+$AD95)),IF(AL$1<=$X95,$Y95,IF(AL$1<=$U95+$O95,$AD95*($AH95+$AG95*(2*INT((AL$1-$O95))/$U95+$AD95)),0))),0) -> 0 | AM95: =IF(AND(AM$1>=$O95,AM$1<=$Q95),$G95*IF(AM$1<=$W95,$AD95*($AF95+$AE95*(2*INT((AM$1-$O95))/$U95+$AD95)),IF(AM$1<=$X95,$Y95,IF(AM$1<=$U95+$O95,$AD95*($AH95+$AG95*(2*INT((AM$1-$O95))/$U95+$AD95)),0))),0) -> 0 | AN95: =IF(AND(AN$1>=$O95,AN$1<=$Q95),$G95*IF(AN$1<=$W95,$AD95*($AF95+$AE95*(2*INT((AN$1-$O95))/$U95+$AD95)),IF(AN$1<=$X95,$Y95,IF(AN$1<=$U95+$O95,$AD95*($AH95+$AG95*(2*INT((AN$1-$O95))/$U95+$AD95)),0))),0) -> 0 | AO95: =IF(AND(AO$1>=$O95,AO$1<=$Q95),$G95*IF(AO$1<=$W95,$AD95*($AF95+$AE95*(2*INT((AO$1-$O95))/$U95+$AD95)),IF(AO$1<=$X95,$Y95,IF(AO$1<=$U95+$O95,$AD95*($AH95+$AG95*(2*INT((AO$1-$O95))/$U95+$AD95)),0))),0) -> 0 | AP95: =IF(AND(AP$1>=$O95,AP$1<=$Q95),$G95*IF(AP$1<=$W95,$AD95*($AF95+$AE95*(2*INT((AP$1-$O95))/$U95+$AD95)),IF(AP$1<=$X95,$Y95,IF(AP$1<=$U95+$O95,$AD95*($AH95+$AG95*(2*INT((AP$1-$O95))/$U95+$AD95)),0))),0) -> 0 | AQ95: =IF(AND(AQ$1>=$O95,AQ$1<=$Q95),$G95*IF(AQ$1<=$W95,$AD95*($AF95+$AE95*(2*INT((AQ$1-$O95))/$U95+$AD95)),IF(AQ$1<=$X95,$Y95,IF(AQ$1<=$U95+$O95,$AD95*($AH95+$AG95*(2*INT((AQ$1-$O95))/$U95+$AD95)),0))),0) -> 0 | ... EZ95: =IF(AND(EZ$1>=$O95,EZ$1<=$Q95),$G95*IF(EZ$1<=$W95,$AD95*($AF95+$AE95*(2*INT((EZ$1-$O95))/$U95+$AD95)),IF(EZ$1<=$X95,$Y95,IF(EZ$1<=$U95+$O95,$AD95*($AH95+$AG95*(2*INT((EZ$1-$O95))/$U95+$AD95)),0))),0) -> 0
E96: =OFFSET(E96,-1,0)+1 -> 2 | F96: Mechanical / Electrical Engineer | G96: =H96*J96 -> 496583.08 | H96: 400 | I96: Total Beds | J96: =INDEX(FACTOR_VALUES,MATCH(I96,FACTOR_NAMES,0),1) -> 1241.4577 | K96: =+$G96/Beds -> 400 | L96: =+$G96/$H$15 -> 0.65527581 | M96: =+$G96/$H$16 -> 1.1583058 | N96: =EOMONTH($M$7,O96-2)+1 -> 46753 | O96: =$N$7 -> 1 | P96: 1 | Q96: =O96-1+P96 -> 1 | R96: Curve-Front | U96: =+P96 -> 1 | V96: =+R96 -> Curve-Front | W96: =INT(U96*AB96)+O96-1 -> 0 | X96: =(U96-INT(U96*(1-AB96)))+O96-1 -> 1 | Y96: =(AB96-(W96-O96+1)/U96)*(AF96+AE96*(2*(W96-O96+1)/U96+(AB96-(W96-O96+1)/U96)))+((X96-O96+1)/U96-AB96)*(AH96+AG96*(2*AB96+((X96-O96+1)/U96-AB96))) -> 1 | Z96: =IF(V96="curve-front",1,IF(V96="curve-end",3,2)) -> 1 | AA96: =IF(OR(V96="curve-front",V96="curve-mid",V96="curve-end"),2.5,1) -> 2.5 | AB96: =Z96/4 -> 0.25 | AC96: =AA96-1 -> 1.5 | AD96: =1/U96 -> 1 | AE96: =AC96/(AB96*(2+AC96)) -> 1.7142857 | AF96: =2/(2+AC96) -> 0.57142857 | AG96: =-AC96/(2+AC96)/(1-AB96) -> -0.57142857 | AH96: =2*(1-AB96+AC96)/(2+AC96)/(1-AB96) -> 1.7142857 | AJ96: =IF(AND(AJ$1>=$O96,AJ$1<=$Q96),$G96*IF(AJ$1<=$W96,$AD96*($AF96+$AE96*(2*INT((AJ$1-$O96))/$U96+$AD96)),IF(AJ$1<=$X96,$Y96,IF(AJ$1<=$U96+$O96,$AD96*($AH96+$AG96*(2*INT((AJ$1-$O96))/$U96+$AD96)),0))),0) -> 0 | AK96: =IF(AND(AK$1>=$O96,AK$1<=$Q96),$G96*IF(AK$1<=$W96,$AD96*($AF96+$AE96*(2*INT((AK$1-$O96))/$U96+$AD96)),IF(AK$1<=$X96,$Y96,IF(AK$1<=$U96+$O96,$AD96*($AH96+$AG96*(2*INT((AK$1-$O96))/$U96+$AD96)),0))),0) -> 496583.08 | AL96: =IF(AND(AL$1>=$O96,AL$1<=$Q96),$G96*IF(AL$1<=$W96,$AD96*($AF96+$AE96*(2*INT((AL$1-$O96))/$U96+$AD96)),IF(AL$1<=$X96,$Y96,IF(AL$1<=$U96+$O96,$AD96*($AH96+$AG96*(2*INT((AL$1-$O96))/$U96+$AD96)),0))),0) -> 0 | AM96: =IF(AND(AM$1>=$O96,AM$1<=$Q96),$G96*IF(AM$1<=$W96,$AD96*($AF96+$AE96*(2*INT((AM$1-$O96))/$U96+$AD96)),IF(AM$1<=$X96,$Y96,IF(AM$1<=$U96+$O96,$AD96*($AH96+$AG96*(2*INT((AM$1-$O96))/$U96+$AD96)),0))),0) -> 0 | AN96: =IF(AND(AN$1>=$O96,AN$1<=$Q96),$G96*IF(AN$1<=$W96,$AD96*($AF96+$AE96*(2*INT((AN$1-$O96))/$U96+$AD96)),IF(AN$1<=$X96,$Y96,IF(AN$1<=$U96+$O96,$AD96*($AH96+$AG96*(2*INT((AN$1-$O96))/$U96+$AD96)),0))),0) -> 0 | AO96: =IF(AND(AO$1>=$O96,AO$1<=$Q96),$G96*IF(AO$1<=$W96,$AD96*($AF96+$AE96*(2*INT((AO$1-$O96))/$U96+$AD96)),IF(AO$1<=$X96,$Y96,IF(AO$1<=$U96+$O96,$AD96*($AH96+$AG96*(2*INT((AO$1-$O96))/$U96+$AD96)),0))),0) -> 0 | AP96: =IF(AND(AP$1>=$O96,AP$1<=$Q96),$G96*IF(AP$1<=$W96,$AD96*($AF96+$AE96*(2*INT((AP$1-$O96))/$U96+$AD96)),IF(AP$1<=$X96,$Y96,IF(AP$1<=$U96+$O96,$AD96*($AH96+$AG96*(2*INT((AP$1-$O96))/$U96+$AD96)),0))),0) -> 0 | AQ96: =IF(AND(AQ$1>=$O96,AQ$1<=$Q96),$G96*IF(AQ$1<=$W96,$AD96*($AF96+$AE96*(2*INT((AQ$1-$O96))/$U96+$AD96)),IF(AQ$1<=$X96,$Y96,IF(AQ$1<=$U96+$O96,$AD96*($AH96+$AG96*(2*INT((AQ$1-$O96))/$U96+$AD96)),0))),0) -> 0 | ... EZ96: =IF(AND(EZ$1>=$O96,EZ$1<=$Q96),$G96*IF(EZ$1<=$W96,$AD96*($AF96+$AE96*(2*INT((EZ$1-$O96))/$U96+$AD96)),IF(EZ$1<=$X96,$Y96,IF(EZ$1<=$U96+$O96,$AD96*($AH96+$AG96*(2*INT((EZ$1-$O96))/$U96+$AD96)),0))),0) -> 0
E97: =OFFSET(E97,-1,0)+1 -> 3 | F97: Structural Engineer | G97: =H97*J97 -> 496583.08 | H97: 400 | I97: Total Beds | J97: =INDEX(FACTOR_VALUES,MATCH(I97,FACTOR_NAMES,0),1) -> 1241.4577 | K97: =+$G97/Beds -> 400 | L97: =+$G97/$H$15 -> 0.65527581 | M97: =+$G97/$H$16 -> 1.1583058 | N97: =EOMONTH($M$7,O97-2)+1 -> 46753 | O97: =$N$7 -> 1 | P97: 1 | Q97: =O97-1+P97 -> 1 | R97: Curve-Front | U97: =+P97 -> 1 | V97: =+R97 -> Curve-Front | W97: =INT(U97*AB97)+O97-1 -> 0 | X97: =(U97-INT(U97*(1-AB97)))+O97-1 -> 1 | Y97: =(AB97-(W97-O97+1)/U97)*(AF97+AE97*(2*(W97-O97+1)/U97+(AB97-(W97-O97+1)/U97)))+((X97-O97+1)/U97-AB97)*(AH97+AG97*(2*AB97+((X97-O97+1)/U97-AB97))) -> 1 | Z97: =IF(V97="curve-front",1,IF(V97="curve-end",3,2)) -> 1 | AA97: =IF(OR(V97="curve-front",V97="curve-mid",V97="curve-end"),2.5,1) -> 2.5 | AB97: =Z97/4 -> 0.25 | AC97: =AA97-1 -> 1.5 | AD97: =1/U97 -> 1 | AE97: =AC97/(AB97*(2+AC97)) -> 1.7142857 | AF97: =2/(2+AC97) -> 0.57142857 | AG97: =-AC97/(2+AC97)/(1-AB97) -> -0.57142857 | AH97: =2*(1-AB97+AC97)/(2+AC97)/(1-AB97) -> 1.7142857 | AJ97: =IF(AND(AJ$1>=$O97,AJ$1<=$Q97),$G97*IF(AJ$1<=$W97,$AD97*($AF97+$AE97*(2*INT((AJ$1-$O97))/$U97+$AD97)),IF(AJ$1<=$X97,$Y97,IF(AJ$1<=$U97+$O97,$AD97*($AH97+$AG97*(2*INT((AJ$1-$O97))/$U97+$AD97)),0))),0) -> 0 | AK97: =IF(AND(AK$1>=$O97,AK$1<=$Q97),$G97*IF(AK$1<=$W97,$AD97*($AF97+$AE97*(2*INT((AK$1-$O97))/$U97+$AD97)),IF(AK$1<=$X97,$Y97,IF(AK$1<=$U97+$O97,$AD97*($AH97+$AG97*(2*INT((AK$1-$O97))/$U97+$AD97)),0))),0) -> 496583.08 | AL97: =IF(AND(AL$1>=$O97,AL$1<=$Q97),$G97*IF(AL$1<=$W97,$AD97*($AF97+$AE97*(2*INT((AL$1-$O97))/$U97+$AD97)),IF(AL$1<=$X97,$Y97,IF(AL$1<=$U97+$O97,$AD97*($AH97+$AG97*(2*INT((AL$1-$O97))/$U97+$AD97)),0))),0) -> 0 | AM97: =IF(AND(AM$1>=$O97,AM$1<=$Q97),$G97*IF(AM$1<=$W97,$AD97*($AF97+$AE97*(2*INT((AM$1-$O97))/$U97+$AD97)),IF(AM$1<=$X97,$Y97,IF(AM$1<=$U97+$O97,$AD97*($AH97+$AG97*(2*INT((AM$1-$O97))/$U97+$AD97)),0))),0) -> 0 | AN97: =IF(AND(AN$1>=$O97,AN$1<=$Q97),$G97*IF(AN$1<=$W97,$AD97*($AF97+$AE97*(2*INT((AN$1-$O97))/$U97+$AD97)),IF(AN$1<=$X97,$Y97,IF(AN$1<=$U97+$O97,$AD97*($AH97+$AG97*(2*INT((AN$1-$O97))/$U97+$AD97)),0))),0) -> 0 | AO97: =IF(AND(AO$1>=$O97,AO$1<=$Q97),$G97*IF(AO$1<=$W97,$AD97*($AF97+$AE97*(2*INT((AO$1-$O97))/$U97+$AD97)),IF(AO$1<=$X97,$Y97,IF(AO$1<=$U97+$O97,$AD97*($AH97+$AG97*(2*INT((AO$1-$O97))/$U97+$AD97)),0))),0) -> 0 | AP97: =IF(AND(AP$1>=$O97,AP$1<=$Q97),$G97*IF(AP$1<=$W97,$AD97*($AF97+$AE97*(2*INT((AP$1-$O97))/$U97+$AD97)),IF(AP$1<=$X97,$Y97,IF(AP$1<=$U97+$O97,$AD97*($AH97+$AG97*(2*INT((AP$1-$O97))/$U97+$AD97)),0))),0) -> 0 | AQ97: =IF(AND(AQ$1>=$O97,AQ$1<=$Q97),$G97*IF(AQ$1<=$W97,$AD97*($AF97+$AE97*(2*INT((AQ$1-$O97))/$U97+$AD97)),IF(AQ$1<=$X97,$Y97,IF(AQ$1<=$U97+$O97,$AD97*($AH97+$AG97*(2*INT((AQ$1-$O97))/$U97+$AD97)),0))),0) -> 0 | ... EZ97: =IF(AND(EZ$1>=$O97,EZ$1<=$Q97),$G97*IF(EZ$1<=$W97,$AD97*($AF97+$AE97*(2*INT((EZ$1-$O97))/$U97+$AD97)),IF(EZ$1<=$X97,$Y97,IF(EZ$1<=$U97+$O97,$AD97*($AH97+$AG97*(2*INT((EZ$1-$O97))/$U97+$AD97)),0))),0) -> 0
E98: =OFFSET(E98,-1,0)+1 -> 4 | F98: Civil Engineer | G98: =H98*J98 -> 150000 | H98: 150000 | I98: Amount | J98: =INDEX(FACTOR_VALUES,MATCH(I98,FACTOR_NAMES,0),1) -> 1 | K98: =+$G98/Beds -> 120.8257 | L98: =+$G98/$H$15 -> 0.1979354 | M98: =+$G98/$H$16 -> 0.34988279 | N98: =EOMONTH($M$7,O98-2)+1 -> 46753 | O98: =$N$7 -> 1 | P98: 1 | Q98: =O98-1+P98 -> 1 | R98: Curve-Front | U98: =+P98 -> 1 | V98: =+R98 -> Curve-Front | W98: =INT(U98*AB98)+O98-1 -> 0 | X98: =(U98-INT(U98*(1-AB98)))+O98-1 -> 1 | Y98: =(AB98-(W98-O98+1)/U98)*(AF98+AE98*(2*(W98-O98+1)/U98+(AB98-(W98-O98+1)/U98)))+((X98-O98+1)/U98-AB98)*(AH98+AG98*(2*AB98+((X98-O98+1)/U98-AB98))) -> 1 | Z98: =IF(V98="curve-front",1,IF(V98="curve-end",3,2)) -> 1 | AA98: =IF(OR(V98="curve-front",V98="curve-mid",V98="curve-end"),2.5,1) -> 2.5 | AB98: =Z98/4 -> 0.25 | AC98: =AA98-1 -> 1.5 | AD98: =1/U98 -> 1 | AE98: =AC98/(AB98*(2+AC98)) -> 1.7142857 | AF98: =2/(2+AC98) -> 0.57142857 | AG98: =-AC98/(2+AC98)/(1-AB98) -> -0.57142857 | AH98: =2*(1-AB98+AC98)/(2+AC98)/(1-AB98) -> 1.7142857 | AJ98: =IF(AND(AJ$1>=$O98,AJ$1<=$Q98),$G98*IF(AJ$1<=$W98,$AD98*($AF98+$AE98*(2*INT((AJ$1-$O98))/$U98+$AD98)),IF(AJ$1<=$X98,$Y98,IF(AJ$1<=$U98+$O98,$AD98*($AH98+$AG98*(2*INT((AJ$1-$O98))/$U98+$AD98)),0))),0) -> 0 | AK98: =IF(AND(AK$1>=$O98,AK$1<=$Q98),$G98*IF(AK$1<=$W98,$AD98*($AF98+$AE98*(2*INT((AK$1-$O98))/$U98+$AD98)),IF(AK$1<=$X98,$Y98,IF(AK$1<=$U98+$O98,$AD98*($AH98+$AG98*(2*INT((AK$1-$O98))/$U98+$AD98)),0))),0) -> 150000 | AL98: =IF(AND(AL$1>=$O98,AL$1<=$Q98),$G98*IF(AL$1<=$W98,$AD98*($AF98+$AE98*(2*INT((AL$1-$O98))/$U98+$AD98)),IF(AL$1<=$X98,$Y98,IF(AL$1<=$U98+$O98,$AD98*($AH98+$AG98*(2*INT((AL$1-$O98))/$U98+$AD98)),0))),0) -> 0 | AM98: =IF(AND(AM$1>=$O98,AM$1<=$Q98),$G98*IF(AM$1<=$W98,$AD98*($AF98+$AE98*(2*INT((AM$1-$O98))/$U98+$AD98)),IF(AM$1<=$X98,$Y98,IF(AM$1<=$U98+$O98,$AD98*($AH98+$AG98*(2*INT((AM$1-$O98))/$U98+$AD98)),0))),0) -> 0 | AN98: =IF(AND(AN$1>=$O98,AN$1<=$Q98),$G98*IF(AN$1<=$W98,$AD98*($AF98+$AE98*(2*INT((AN$1-$O98))/$U98+$AD98)),IF(AN$1<=$X98,$Y98,IF(AN$1<=$U98+$O98,$AD98*($AH98+$AG98*(2*INT((AN$1-$O98))/$U98+$AD98)),0))),0) -> 0 | AO98: =IF(AND(AO$1>=$O98,AO$1<=$Q98),$G98*IF(AO$1<=$W98,$AD98*($AF98+$AE98*(2*INT((AO$1-$O98))/$U98+$AD98)),IF(AO$1<=$X98,$Y98,IF(AO$1<=$U98+$O98,$AD98*($AH98+$AG98*(2*INT((AO$1-$O98))/$U98+$AD98)),0))),0) -> 0 | AP98: =IF(AND(AP$1>=$O98,AP$1<=$Q98),$G98*IF(AP$1<=$W98,$AD98*($AF98+$AE98*(2*INT((AP$1-$O98))/$U98+$AD98)),IF(AP$1<=$X98,$Y98,IF(AP$1<=$U98+$O98,$AD98*($AH98+$AG98*(2*INT((AP$1-$O98))/$U98+$AD98)),0))),0) -> 0 | AQ98: =IF(AND(AQ$1>=$O98,AQ$1<=$Q98),$G98*IF(AQ$1<=$W98,$AD98*($AF98+$AE98*(2*INT((AQ$1-$O98))/$U98+$AD98)),IF(AQ$1<=$X98,$Y98,IF(AQ$1<=$U98+$O98,$AD98*($AH98+$AG98*(2*INT((AQ$1-$O98))/$U98+$AD98)),0))),0) -> 0 | ... EZ98: =IF(AND(EZ$1>=$O98,EZ$1<=$Q98),$G98*IF(EZ$1<=$W98,$AD98*($AF98+$AE98*(2*INT((EZ$1-$O98))/$U98+$AD98)),IF(EZ$1<=$X98,$Y98,IF(EZ$1<=$U98+$O98,$AD98*($AH98+$AG98*(2*INT((EZ$1-$O98))/$U98+$AD98)),0))),0) -> 0
E99: =OFFSET(E99,-1,0)+1 -> 5 | F99: Interior Design | G99: =H99*J99 -> 496583.08 | H99: 400 | I99: Total Beds | J99: =INDEX(FACTOR_VALUES,MATCH(I99,FACTOR_NAMES,0),1) -> 1241.4577 | K99: =+$G99/Beds -> 400 | L99: =+$G99/$H$15 -> 0.65527581 | M99: =+$G99/$H$16 -> 1.1583058 | N99: =EOMONTH($M$7,O99-2)+1 -> 46753 | O99: =$N$7 -> 1 | P99: 1 | Q99: =O99-1+P99 -> 1 | R99: Curve-Front | U99: =+P99 -> 1 | V99: =+R99 -> Curve-Front | W99: =INT(U99*AB99)+O99-1 -> 0 | X99: =(U99-INT(U99*(1-AB99)))+O99-1 -> 1 | Y99: =(AB99-(W99-O99+1)/U99)*(AF99+AE99*(2*(W99-O99+1)/U99+(AB99-(W99-O99+1)/U99)))+((X99-O99+1)/U99-AB99)*(AH99+AG99*(2*AB99+((X99-O99+1)/U99-AB99))) -> 1 | Z99: =IF(V99="curve-front",1,IF(V99="curve-end",3,2)) -> 1 | AA99: =IF(OR(V99="curve-front",V99="curve-mid",V99="curve-end"),2.5,1) -> 2.5 | AB99: =Z99/4 -> 0.25 | AC99: =AA99-1 -> 1.5 | AD99: =1/U99 -> 1 | AE99: =AC99/(AB99*(2+AC99)) -> 1.7142857 | AF99: =2/(2+AC99) -> 0.57142857 | AG99: =-AC99/(2+AC99)/(1-AB99) -> -0.57142857 | AH99: =2*(1-AB99+AC99)/(2+AC99)/(1-AB99) -> 1.7142857 | AJ99: =IF(AND(AJ$1>=$O99,AJ$1<=$Q99),$G99*IF(AJ$1<=$W99,$AD99*($AF99+$AE99*(2*INT((AJ$1-$O99))/$U99+$AD99)),IF(AJ$1<=$X99,$Y99,IF(AJ$1<=$U99+$O99,$AD99*($AH99+$AG99*(2*INT((AJ$1-$O99))/$U99+$AD99)),0))),0) -> 0 | AK99: =IF(AND(AK$1>=$O99,AK$1<=$Q99),$G99*IF(AK$1<=$W99,$AD99*($AF99+$AE99*(2*INT((AK$1-$O99))/$U99+$AD99)),IF(AK$1<=$X99,$Y99,IF(AK$1<=$U99+$O99,$AD99*($AH99+$AG99*(2*INT((AK$1-$O99))/$U99+$AD99)),0))),0) -> 496583.08 | AL99: =IF(AND(AL$1>=$O99,AL$1<=$Q99),$G99*IF(AL$1<=$W99,$AD99*($AF99+$AE99*(2*INT((AL$1-$O99))/$U99+$AD99)),IF(AL$1<=$X99,$Y99,IF(AL$1<=$U99+$O99,$AD99*($AH99+$AG99*(2*INT((AL$1-$O99))/$U99+$AD99)),0))),0) -> 0 | AM99: =IF(AND(AM$1>=$O99,AM$1<=$Q99),$G99*IF(AM$1<=$W99,$AD99*($AF99+$AE99*(2*INT((AM$1-$O99))/$U99+$AD99)),IF(AM$1<=$X99,$Y99,IF(AM$1<=$U99+$O99,$AD99*($AH99+$AG99*(2*INT((AM$1-$O99))/$U99+$AD99)),0))),0) -> 0 | AN99: =IF(AND(AN$1>=$O99,AN$1<=$Q99),$G99*IF(AN$1<=$W99,$AD99*($AF99+$AE99*(2*INT((AN$1-$O99))/$U99+$AD99)),IF(AN$1<=$X99,$Y99,IF(AN$1<=$U99+$O99,$AD99*($AH99+$AG99*(2*INT((AN$1-$O99))/$U99+$AD99)),0))),0) -> 0 | AO99: =IF(AND(AO$1>=$O99,AO$1<=$Q99),$G99*IF(AO$1<=$W99,$AD99*($AF99+$AE99*(2*INT((AO$1-$O99))/$U99+$AD99)),IF(AO$1<=$X99,$Y99,IF(AO$1<=$U99+$O99,$AD99*($AH99+$AG99*(2*INT((AO$1-$O99))/$U99+$AD99)),0))),0) -> 0 | AP99: =IF(AND(AP$1>=$O99,AP$1<=$Q99),$G99*IF(AP$1<=$W99,$AD99*($AF99+$AE99*(2*INT((AP$1-$O99))/$U99+$AD99)),IF(AP$1<=$X99,$Y99,IF(AP$1<=$U99+$O99,$AD99*($AH99+$AG99*(2*INT((AP$1-$O99))/$U99+$AD99)),0))),0) -> 0 | AQ99: =IF(AND(AQ$1>=$O99,AQ$1<=$Q99),$G99*IF(AQ$1<=$W99,$AD99*($AF99+$AE99*(2*INT((AQ$1-$O99))/$U99+$AD99)),IF(AQ$1<=$X99,$Y99,IF(AQ$1<=$U99+$O99,$AD99*($AH99+$AG99*(2*INT((AQ$1-$O99))/$U99+$AD99)),0))),0) -> 0 | ... EZ99: =IF(AND(EZ$1>=$O99,EZ$1<=$Q99),$G99*IF(EZ$1<=$W99,$AD99*($AF99+$AE99*(2*INT((EZ$1-$O99))/$U99+$AD99)),IF(EZ$1<=$X99,$Y99,IF(EZ$1<=$U99+$O99,$AD99*($AH99+$AG99*(2*INT((EZ$1-$O99))/$U99+$AD99)),0))),0) -> 0
E100: =OFFSET(E100,-1,0)+1 -> 6 | F100: Envelope Consultant | G100: =H100*J100 -> 125000 | H100: {=+_xlfn.IFS($H$10<1000,85000,$H$10>1000, 125000)} -> 125000 | I100: Amount | J100: =INDEX(FACTOR_VALUES,MATCH(I100,FACTOR_NAMES,0),1) -> 1 | K100: =+$G100/Beds -> 100.68809 | L100: =+$G100/$H$15 -> 0.16494617 | M100: =+$G100/$H$16 -> 0.29156899 | N100: =EOMONTH($M$7,O100-2)+1 -> 46753 | O100: =$N$7 -> 1 | P100: 1 | Q100: =O100-1+P100 -> 1 | R100: Curve-Front | S100: $85k if less than 1,000 bed;, $125k if more than 1,000 beds | U100: =+P100 -> 1 | V100: =+R100 -> Curve-Front | W100: =INT(U100*AB100)+O100-1 -> 0 | X100: =(U100-INT(U100*(1-AB100)))+O100-1 -> 1 | Y100: =(AB100-(W100-O100+1)/U100)*(AF100+AE100*(2*(W100-O100+1)/U100+(AB100-(W100-O100+1)/U100)))+((X100-O100+1)/U100-AB100)*(AH100+AG100*(2*AB100+((X100-O100+1)/U100-AB100))) -> 1 | Z100: =IF(V100="curve-front",1,IF(V100="curve-end",3,2)) -> 1 | AA100: =IF(OR(V100="curve-front",V100="curve-mid",V100="curve-end"),2.5,1) -> 2.5 | AB100: =Z100/4 -> 0.25 | AC100: =AA100-1 -> 1.5 | AD100: =1/U100 -> 1 | AE100: =AC100/(AB100*(2+AC100)) -> 1.7142857 | AF100: =2/(2+AC100) -> 0.57142857 | AG100: =-AC100/(2+AC100)/(1-AB100) -> -0.57142857 | AH100: =2*(1-AB100+AC100)/(2+AC100)/(1-AB100) -> 1.7142857 | AJ100: =IF(AND(AJ$1>=$O100,AJ$1<=$Q100),$G100*IF(AJ$1<=$W100,$AD100*($AF100+$AE100*(2*INT((AJ$1-$O100))/$U100+$AD100)),IF(AJ$1<=$X100,$Y100,IF(AJ$1<=$U100+$O100,$AD100*($AH100+$AG100*(2*INT((AJ$1-$O100))/$U100+$AD100)),0))),0) -> 0 | AK100: =IF(AND(AK$1>=$O100,AK$1<=$Q100),$G100*IF(AK$1<=$W100,$AD100*($AF100+$AE100*(2*INT((AK$1-$O100))/$U100+$AD100)),IF(AK$1<=$X100,$Y100,IF(AK$1<=$U100+$O100,$AD100*($AH100+$AG100*(2*INT((AK$1-$O100))/$U100+$AD100)),0))),0) -> 125000 | AL100: =IF(AND(AL$1>=$O100,AL$1<=$Q100),$G100*IF(AL$1<=$W100,$AD100*($AF100+$AE100*(2*INT((AL$1-$O100))/$U100+$AD100)),IF(AL$1<=$X100,$Y100,IF(AL$1<=$U100+$O100,$AD100*($AH100+$AG100*(2*INT((AL$1-$O100))/$U100+$AD100)),0))),0) -> 0 | AM100: =IF(AND(AM$1>=$O100,AM$1<=$Q100),$G100*IF(AM$1<=$W100,$AD100*($AF100+$AE100*(2*INT((AM$1-$O100))/$U100+$AD100)),IF(AM$1<=$X100,$Y100,IF(AM$1<=$U100+$O100,$AD100*($AH100+$AG100*(2*INT((AM$1-$O100))/$U100+$AD100)),0))),0) -> 0 | AN100: =IF(AND(AN$1>=$O100,AN$1<=$Q100),$G100*IF(AN$1<=$W100,$AD100*($AF100+$AE100*(2*INT((AN$1-$O100))/$U100+$AD100)),IF(AN$1<=$X100,$Y100,IF(AN$1<=$U100+$O100,$AD100*($AH100+$AG100*(2*INT((AN$1-$O100))/$U100+$AD100)),0))),0) -> 0 | AO100: =IF(AND(AO$1>=$O100,AO$1<=$Q100),$G100*IF(AO$1<=$W100,$AD100*($AF100+$AE100*(2*INT((AO$1-$O100))/$U100+$AD100)),IF(AO$1<=$X100,$Y100,IF(AO$1<=$U100+$O100,$AD100*($AH100+$AG100*(2*INT((AO$1-$O100))/$U100+$AD100)),0))),0) -> 0 | AP100: =IF(AND(AP$1>=$O100,AP$1<=$Q100),$G100*IF(AP$1<=$W100,$AD100*($AF100+$AE100*(2*INT((AP$1-$O100))/$U100+$AD100)),IF(AP$1<=$X100,$Y100,IF(AP$1<=$U100+$O100,$AD100*($AH100+$AG100*(2*INT((AP$1-$O100))/$U100+$AD100)),0))),0) -> 0 | AQ100: =IF(AND(AQ$1>=$O100,AQ$1<=$Q100),$G100*IF(AQ$1<=$W100,$AD100*($AF100+$AE100*(2*INT((AQ$1-$O100))/$U100+$AD100)),IF(AQ$1<=$X100,$Y100,IF(AQ$1<=$U100+$O100,$AD100*($AH100+$AG100*(2*INT((AQ$1-$O100))/$U100+$AD100)),0))),0) -> 0 | ... EZ100: =IF(AND(EZ$1>=$O100,EZ$1<=$Q100),$G100*IF(EZ$1<=$W100,$AD100*($AF100+$AE100*(2*INT((EZ$1-$O100))/$U100+$AD100)),IF(EZ$1<=$X100,$Y100,IF(EZ$1<=$U100+$O100,$AD100*($AH100+$AG100*(2*INT((EZ$1-$O100))/$U100+$AD100)),0))),0) -> 0
E101: =OFFSET(E101,-1,0)+1 -> 7 | F101: Third Party Civil | G101: =H101*J101 -> 120000 | H101: 120000 | I101: Amount | J101: =INDEX(FACTOR_VALUES,MATCH(I101,FACTOR_NAMES,0),1) -> 1 | K101: =+$G101/Beds -> 96.660562 | L101: =+$G101/$H$15 -> 0.15834832 | M101: =+$G101/$H$16 -> 0.27990623 | N101: =EOMONTH($M$7,O101-2)+1 -> 46753 | O101: =$N$7 -> 1 | P101: 1 | Q101: =O101-1+P101 -> 1 | R101: Curve-Front | U101: =+P101 -> 1 | V101: =+R101 -> Curve-Front | W101: =INT(U101*AB101)+O101-1 -> 0 | X101: =(U101-INT(U101*(1-AB101)))+O101-1 -> 1 | Y101: =(AB101-(W101-O101+1)/U101)*(AF101+AE101*(2*(W101-O101+1)/U101+(AB101-(W101-O101+1)/U101)))+((X101-O101+1)/U101-AB101)*(AH101+AG101*(2*AB101+((X101-O101+1)/U101-AB101))) -> 1 | Z101: =IF(V101="curve-front",1,IF(V101="curve-end",3,2)) -> 1 | AA101: =IF(OR(V101="curve-front",V101="curve-mid",V101="curve-end"),2.5,1) -> 2.5 | AB101: =Z101/4 -> 0.25 | AC101: =AA101-1 -> 1.5 | AD101: =1/U101 -> 1 | AE101: =AC101/(AB101*(2+AC101)) -> 1.7142857 | AF101: =2/(2+AC101) -> 0.57142857 | AG101: =-AC101/(2+AC101)/(1-AB101) -> -0.57142857 | AH101: =2*(1-AB101+AC101)/(2+AC101)/(1-AB101) -> 1.7142857 | AJ101: =IF(AND(AJ$1>=$O101,AJ$1<=$Q101),$G101*IF(AJ$1<=$W101,$AD101*($AF101+$AE101*(2*INT((AJ$1-$O101))/$U101+$AD101)),IF(AJ$1<=$X101,$Y101,IF(AJ$1<=$U101+$O101,$AD101*($AH101+$AG101*(2*INT((AJ$1-$O101))/$U101+$AD101)),0))),0) -> 0 | AK101: =IF(AND(AK$1>=$O101,AK$1<=$Q101),$G101*IF(AK$1<=$W101,$AD101*($AF101+$AE101*(2*INT((AK$1-$O101))/$U101+$AD101)),IF(AK$1<=$X101,$Y101,IF(AK$1<=$U101+$O101,$AD101*($AH101+$AG101*(2*INT((AK$1-$O101))/$U101+$AD101)),0))),0) -> 120000 | AL101: =IF(AND(AL$1>=$O101,AL$1<=$Q101),$G101*IF(AL$1<=$W101,$AD101*($AF101+$AE101*(2*INT((AL$1-$O101))/$U101+$AD101)),IF(AL$1<=$X101,$Y101,IF(AL$1<=$U101+$O101,$AD101*($AH101+$AG101*(2*INT((AL$1-$O101))/$U101+$AD101)),0))),0) -> 0 | AM101: =IF(AND(AM$1>=$O101,AM$1<=$Q101),$G101*IF(AM$1<=$W101,$AD101*($AF101+$AE101*(2*INT((AM$1-$O101))/$U101+$AD101)),IF(AM$1<=$X101,$Y101,IF(AM$1<=$U101+$O101,$AD101*($AH101+$AG101*(2*INT((AM$1-$O101))/$U101+$AD101)),0))),0) -> 0 | AN101: =IF(AND(AN$1>=$O101,AN$1<=$Q101),$G101*IF(AN$1<=$W101,$AD101*($AF101+$AE101*(2*INT((AN$1-$O101))/$U101+$AD101)),IF(AN$1<=$X101,$Y101,IF(AN$1<=$U101+$O101,$AD101*($AH101+$AG101*(2*INT((AN$1-$O101))/$U101+$AD101)),0))),0) -> 0 | AO101: =IF(AND(AO$1>=$O101,AO$1<=$Q101),$G101*IF(AO$1<=$W101,$AD101*($AF101+$AE101*(2*INT((AO$1-$O101))/$U101+$AD101)),IF(AO$1<=$X101,$Y101,IF(AO$1<=$U101+$O101,$AD101*($AH101+$AG101*(2*INT((AO$1-$O101))/$U101+$AD101)),0))),0) -> 0 | AP101: =IF(AND(AP$1>=$O101,AP$1<=$Q101),$G101*IF(AP$1<=$W101,$AD101*($AF101+$AE101*(2*INT((AP$1-$O101))/$U101+$AD101)),IF(AP$1<=$X101,$Y101,IF(AP$1<=$U101+$O101,$AD101*($AH101+$AG101*(2*INT((AP$1-$O101))/$U101+$AD101)),0))),0) -> 0 | AQ101: =IF(AND(AQ$1>=$O101,AQ$1<=$Q101),$G101*IF(AQ$1<=$W101,$AD101*($AF101+$AE101*(2*INT((AQ$1-$O101))/$U101+$AD101)),IF(AQ$1<=$X101,$Y101,IF(AQ$1<=$U101+$O101,$AD101*($AH101+$AG101*(2*INT((AQ$1-$O101))/$U101+$AD101)),0))),0) -> 0 | ... EZ101: =IF(AND(EZ$1>=$O101,EZ$1<=$Q101),$G101*IF(EZ$1<=$W101,$AD101*($AF101+$AE101*(2*INT((EZ$1-$O101))/$U101+$AD101)),IF(EZ$1<=$X101,$Y101,IF(EZ$1<=$U101+$O101,$AD101*($AH101+$AG101*(2*INT((EZ$1-$O101))/$U101+$AD101)),0))),0) -> 0
E102: =OFFSET(E102,-1,0)+1 -> 8 | F102: ADA Consultant | G102: =H102*J102 -> 12500 | H102: 12500 | I102: Amount | J102: =INDEX(FACTOR_VALUES,MATCH(I102,FACTOR_NAMES,0),1) -> 1 | K102: =+$G102/Beds -> 10.068809 | L102: =+$G102/$H$15 -> 0.016494617 | M102: =+$G102/$H$16 -> 0.029156899 | N102: =EOMONTH($M$7,O102-2)+1 -> 46753 | O102: =$N$7 -> 1 | P102: 1 | Q102: =O102-1+P102 -> 1 | R102: Curve-Front | U102: =+P102 -> 1 | V102: =+R102 -> Curve-Front | W102: =INT(U102*AB102)+O102-1 -> 0 | X102: =(U102-INT(U102*(1-AB102)))+O102-1 -> 1 | Y102: =(AB102-(W102-O102+1)/U102)*(AF102+AE102*(2*(W102-O102+1)/U102+(AB102-(W102-O102+1)/U102)))+((X102-O102+1)/U102-AB102)*(AH102+AG102*(2*AB102+((X102-O102+1)/U102-AB102))) -> 1 | Z102: =IF(V102="curve-front",1,IF(V102="curve-end",3,2)) -> 1 | AA102: =IF(OR(V102="curve-front",V102="curve-mid",V102="curve-end"),2.5,1) -> 2.5 | AB102: =Z102/4 -> 0.25 | AC102: =AA102-1 -> 1.5 | AD102: =1/U102 -> 1 | AE102: =AC102/(AB102*(2+AC102)) -> 1.7142857 | AF102: =2/(2+AC102) -> 0.57142857 | AG102: =-AC102/(2+AC102)/(1-AB102) -> -0.57142857 | AH102: =2*(1-AB102+AC102)/(2+AC102)/(1-AB102) -> 1.7142857 | AJ102: =IF(AND(AJ$1>=$O102,AJ$1<=$Q102),$G102*IF(AJ$1<=$W102,$AD102*($AF102+$AE102*(2*INT((AJ$1-$O102))/$U102+$AD102)),IF(AJ$1<=$X102,$Y102,IF(AJ$1<=$U102+$O102,$AD102*($AH102+$AG102*(2*INT((AJ$1-$O102))/$U102+$AD102)),0))),0) -> 0 | AK102: =IF(AND(AK$1>=$O102,AK$1<=$Q102),$G102*IF(AK$1<=$W102,$AD102*($AF102+$AE102*(2*INT((AK$1-$O102))/$U102+$AD102)),IF(AK$1<=$X102,$Y102,IF(AK$1<=$U102+$O102,$AD102*($AH102+$AG102*(2*INT((AK$1-$O102))/$U102+$AD102)),0))),0) -> 12500 | AL102: =IF(AND(AL$1>=$O102,AL$1<=$Q102),$G102*IF(AL$1<=$W102,$AD102*($AF102+$AE102*(2*INT((AL$1-$O102))/$U102+$AD102)),IF(AL$1<=$X102,$Y102,IF(AL$1<=$U102+$O102,$AD102*($AH102+$AG102*(2*INT((AL$1-$O102))/$U102+$AD102)),0))),0) -> 0 | AM102: =IF(AND(AM$1>=$O102,AM$1<=$Q102),$G102*IF(AM$1<=$W102,$AD102*($AF102+$AE102*(2*INT((AM$1-$O102))/$U102+$AD102)),IF(AM$1<=$X102,$Y102,IF(AM$1<=$U102+$O102,$AD102*($AH102+$AG102*(2*INT((AM$1-$O102))/$U102+$AD102)),0))),0) -> 0 | AN102: =IF(AND(AN$1>=$O102,AN$1<=$Q102),$G102*IF(AN$1<=$W102,$AD102*($AF102+$AE102*(2*INT((AN$1-$O102))/$U102+$AD102)),IF(AN$1<=$X102,$Y102,IF(AN$1<=$U102+$O102,$AD102*($AH102+$AG102*(2*INT((AN$1-$O102))/$U102+$AD102)),0))),0) -> 0 | AO102: =IF(AND(AO$1>=$O102,AO$1<=$Q102),$G102*IF(AO$1<=$W102,$AD102*($AF102+$AE102*(2*INT((AO$1-$O102))/$U102+$AD102)),IF(AO$1<=$X102,$Y102,IF(AO$1<=$U102+$O102,$AD102*($AH102+$AG102*(2*INT((AO$1-$O102))/$U102+$AD102)),0))),0) -> 0 | AP102: =IF(AND(AP$1>=$O102,AP$1<=$Q102),$G102*IF(AP$1<=$W102,$AD102*($AF102+$AE102*(2*INT((AP$1-$O102))/$U102+$AD102)),IF(AP$1<=$X102,$Y102,IF(AP$1<=$U102+$O102,$AD102*($AH102+$AG102*(2*INT((AP$1-$O102))/$U102+$AD102)),0))),0) -> 0 | AQ102: =IF(AND(AQ$1>=$O102,AQ$1<=$Q102),$G102*IF(AQ$1<=$W102,$AD102*($AF102+$AE102*(2*INT((AQ$1-$O102))/$U102+$AD102)),IF(AQ$1<=$X102,$Y102,IF(AQ$1<=$U102+$O102,$AD102*($AH102+$AG102*(2*INT((AQ$1-$O102))/$U102+$AD102)),0))),0) -> 0 | ... EZ102: =IF(AND(EZ$1>=$O102,EZ$1<=$Q102),$G102*IF(EZ$1<=$W102,$AD102*($AF102+$AE102*(2*INT((EZ$1-$O102))/$U102+$AD102)),IF(EZ$1<=$X102,$Y102,IF(EZ$1<=$U102+$O102,$AD102*($AH102+$AG102*(2*INT((EZ$1-$O102))/$U102+$AD102)),0))),0) -> 0
E103: =OFFSET(E103,-1,0)+1 -> 9 | F103: Lighting Consultant | G103: =H103*J103 -> 5600 | H103: 5600 | I103: Amount | J103: =INDEX(FACTOR_VALUES,MATCH(I103,FACTOR_NAMES,0),1) -> 1 | K103: =+$G103/Beds -> 4.5108262 | L103: =+$G103/$H$15 -> 0.0073895883 | M103: =+$G103/$H$16 -> 0.013062291 | N103: =EOMONTH($M$7,O103-2)+1 -> 46753 | O103: =$N$7 -> 1 | P103: 1 | Q103: =O103-1+P103 -> 1 | R103: Curve-Front | U103: =+P103 -> 1 | V103: =+R103 -> Curve-Front | W103: =INT(U103*AB103)+O103-1 -> 0 | X103: =(U103-INT(U103*(1-AB103)))+O103-1 -> 1 | Y103: =(AB103-(W103-O103+1)/U103)*(AF103+AE103*(2*(W103-O103+1)/U103+(AB103-(W103-O103+1)/U103)))+((X103-O103+1)/U103-AB103)*(AH103+AG103*(2*AB103+((X103-O103+1)/U103-AB103))) -> 1 | Z103: =IF(V103="curve-front",1,IF(V103="curve-end",3,2)) -> 1 | AA103: =IF(OR(V103="curve-front",V103="curve-mid",V103="curve-end"),2.5,1) -> 2.5 | AB103: =Z103/4 -> 0.25 | AC103: =AA103-1 -> 1.5 | AD103: =1/U103 -> 1 | AE103: =AC103/(AB103*(2+AC103)) -> 1.7142857 | AF103: =2/(2+AC103) -> 0.57142857 | AG103: =-AC103/(2+AC103)/(1-AB103) -> -0.57142857 | AH103: =2*(1-AB103+AC103)/(2+AC103)/(1-AB103) -> 1.7142857 | AJ103: =IF(AND(AJ$1>=$O103,AJ$1<=$Q103),$G103*IF(AJ$1<=$W103,$AD103*($AF103+$AE103*(2*INT((AJ$1-$O103))/$U103+$AD103)),IF(AJ$1<=$X103,$Y103,IF(AJ$1<=$U103+$O103,$AD103*($AH103+$AG103*(2*INT((AJ$1-$O103))/$U103+$AD103)),0))),0) -> 0 | AK103: =IF(AND(AK$1>=$O103,AK$1<=$Q103),$G103*IF(AK$1<=$W103,$AD103*($AF103+$AE103*(2*INT((AK$1-$O103))/$U103+$AD103)),IF(AK$1<=$X103,$Y103,IF(AK$1<=$U103+$O103,$AD103*($AH103+$AG103*(2*INT((AK$1-$O103))/$U103+$AD103)),0))),0) -> 5600 | AL103: =IF(AND(AL$1>=$O103,AL$1<=$Q103),$G103*IF(AL$1<=$W103,$AD103*($AF103+$AE103*(2*INT((AL$1-$O103))/$U103+$AD103)),IF(AL$1<=$X103,$Y103,IF(AL$1<=$U103+$O103,$AD103*($AH103+$AG103*(2*INT((AL$1-$O103))/$U103+$AD103)),0))),0) -> 0 | AM103: =IF(AND(AM$1>=$O103,AM$1<=$Q103),$G103*IF(AM$1<=$W103,$AD103*($AF103+$AE103*(2*INT((AM$1-$O103))/$U103+$AD103)),IF(AM$1<=$X103,$Y103,IF(AM$1<=$U103+$O103,$AD103*($AH103+$AG103*(2*INT((AM$1-$O103))/$U103+$AD103)),0))),0) -> 0 | AN103: =IF(AND(AN$1>=$O103,AN$1<=$Q103),$G103*IF(AN$1<=$W103,$AD103*($AF103+$AE103*(2*INT((AN$1-$O103))/$U103+$AD103)),IF(AN$1<=$X103,$Y103,IF(AN$1<=$U103+$O103,$AD103*($AH103+$AG103*(2*INT((AN$1-$O103))/$U103+$AD103)),0))),0) -> 0 | AO103: =IF(AND(AO$1>=$O103,AO$1<=$Q103),$G103*IF(AO$1<=$W103,$AD103*($AF103+$AE103*(2*INT((AO$1-$O103))/$U103+$AD103)),IF(AO$1<=$X103,$Y103,IF(AO$1<=$U103+$O103,$AD103*($AH103+$AG103*(2*INT((AO$1-$O103))/$U103+$AD103)),0))),0) -> 0 | AP103: =IF(AND(AP$1>=$O103,AP$1<=$Q103),$G103*IF(AP$1<=$W103,$AD103*($AF103+$AE103*(2*INT((AP$1-$O103))/$U103+$AD103)),IF(AP$1<=$X103,$Y103,IF(AP$1<=$U103+$O103,$AD103*($AH103+$AG103*(2*INT((AP$1-$O103))/$U103+$AD103)),0))),0) -> 0 | AQ103: =IF(AND(AQ$1>=$O103,AQ$1<=$Q103),$G103*IF(AQ$1<=$W103,$AD103*($AF103+$AE103*(2*INT((AQ$1-$O103))/$U103+$AD103)),IF(AQ$1<=$X103,$Y103,IF(AQ$1<=$U103+$O103,$AD103*($AH103+$AG103*(2*INT((AQ$1-$O103))/$U103+$AD103)),0))),0) -> 0 | ... EZ103: =IF(AND(EZ$1>=$O103,EZ$1<=$Q103),$G103*IF(EZ$1<=$W103,$AD103*($AF103+$AE103*(2*INT((EZ$1-$O103))/$U103+$AD103)),IF(EZ$1<=$X103,$Y103,IF(EZ$1<=$U103+$O103,$AD103*($AH103+$AG103*(2*INT((EZ$1-$O103))/$U103+$AD103)),0))),0) -> 0
E104: =OFFSET(E104,-1,0)+1 -> 10 | F104: Low Voltage Consultant | G104: =H104*J104 -> 25000 | H104: 25000 | I104: Amount | J104: =INDEX(FACTOR_VALUES,MATCH(I104,FACTOR_NAMES,0),1) -> 1 | K104: =+$G104/Beds -> 20.137617 | L104: =+$G104/$H$15 -> 0.032989234 | M104: =+$G104/$H$16 -> 0.058313798 | N104: =EOMONTH($M$7,O104-2)+1 -> 46753 | O104: =$N$7 -> 1 | P104: 1 | Q104: =O104-1+P104 -> 1 | R104: Curve-Front | U104: =+P104 -> 1 | V104: =+R104 -> Curve-Front | W104: =INT(U104*AB104)+O104-1 -> 0 | X104: =(U104-INT(U104*(1-AB104)))+O104-1 -> 1 | Y104: =(AB104-(W104-O104+1)/U104)*(AF104+AE104*(2*(W104-O104+1)/U104+(AB104-(W104-O104+1)/U104)))+((X104-O104+1)/U104-AB104)*(AH104+AG104*(2*AB104+((X104-O104+1)/U104-AB104))) -> 1 | Z104: =IF(V104="curve-front",1,IF(V104="curve-end",3,2)) -> 1 | AA104: =IF(OR(V104="curve-front",V104="curve-mid",V104="curve-end"),2.5,1) -> 2.5 | AB104: =Z104/4 -> 0.25 | AC104: =AA104-1 -> 1.5 | AD104: =1/U104 -> 1 | AE104: =AC104/(AB104*(2+AC104)) -> 1.7142857 | AF104: =2/(2+AC104) -> 0.57142857 | AG104: =-AC104/(2+AC104)/(1-AB104) -> -0.57142857 | AH104: =2*(1-AB104+AC104)/(2+AC104)/(1-AB104) -> 1.7142857 | AJ104: =IF(AND(AJ$1>=$O104,AJ$1<=$Q104),$G104*IF(AJ$1<=$W104,$AD104*($AF104+$AE104*(2*INT((AJ$1-$O104))/$U104+$AD104)),IF(AJ$1<=$X104,$Y104,IF(AJ$1<=$U104+$O104,$AD104*($AH104+$AG104*(2*INT((AJ$1-$O104))/$U104+$AD104)),0))),0) -> 0 | AK104: =IF(AND(AK$1>=$O104,AK$1<=$Q104),$G104*IF(AK$1<=$W104,$AD104*($AF104+$AE104*(2*INT((AK$1-$O104))/$U104+$AD104)),IF(AK$1<=$X104,$Y104,IF(AK$1<=$U104+$O104,$AD104*($AH104+$AG104*(2*INT((AK$1-$O104))/$U104+$AD104)),0))),0) -> 25000 | AL104: =IF(AND(AL$1>=$O104,AL$1<=$Q104),$G104*IF(AL$1<=$W104,$AD104*($AF104+$AE104*(2*INT((AL$1-$O104))/$U104+$AD104)),IF(AL$1<=$X104,$Y104,IF(AL$1<=$U104+$O104,$AD104*($AH104+$AG104*(2*INT((AL$1-$O104))/$U104+$AD104)),0))),0) -> 0 | AM104: =IF(AND(AM$1>=$O104,AM$1<=$Q104),$G104*IF(AM$1<=$W104,$AD104*($AF104+$AE104*(2*INT((AM$1-$O104))/$U104+$AD104)),IF(AM$1<=$X104,$Y104,IF(AM$1<=$U104+$O104,$AD104*($AH104+$AG104*(2*INT((AM$1-$O104))/$U104+$AD104)),0))),0) -> 0 | AN104: =IF(AND(AN$1>=$O104,AN$1<=$Q104),$G104*IF(AN$1<=$W104,$AD104*($AF104+$AE104*(2*INT((AN$1-$O104))/$U104+$AD104)),IF(AN$1<=$X104,$Y104,IF(AN$1<=$U104+$O104,$AD104*($AH104+$AG104*(2*INT((AN$1-$O104))/$U104+$AD104)),0))),0) -> 0 | AO104: =IF(AND(AO$1>=$O104,AO$1<=$Q104),$G104*IF(AO$1<=$W104,$AD104*($AF104+$AE104*(2*INT((AO$1-$O104))/$U104+$AD104)),IF(AO$1<=$X104,$Y104,IF(AO$1<=$U104+$O104,$AD104*($AH104+$AG104*(2*INT((AO$1-$O104))/$U104+$AD104)),0))),0) -> 0 | AP104: =IF(AND(AP$1>=$O104,AP$1<=$Q104),$G104*IF(AP$1<=$W104,$AD104*($AF104+$AE104*(2*INT((AP$1-$O104))/$U104+$AD104)),IF(AP$1<=$X104,$Y104,IF(AP$1<=$U104+$O104,$AD104*($AH104+$AG104*(2*INT((AP$1-$O104))/$U104+$AD104)),0))),0) -> 0 | AQ104: =IF(AND(AQ$1>=$O104,AQ$1<=$Q104),$G104*IF(AQ$1<=$W104,$AD104*($AF104+$AE104*(2*INT((AQ$1-$O104))/$U104+$AD104)),IF(AQ$1<=$X104,$Y104,IF(AQ$1<=$U104+$O104,$AD104*($AH104+$AG104*(2*INT((AQ$1-$O104))/$U104+$AD104)),0))),0) -> 0 | ... EZ104: =IF(AND(EZ$1>=$O104,EZ$1<=$Q104),$G104*IF(EZ$1<=$W104,$AD104*($AF104+$AE104*(2*INT((EZ$1-$O104))/$U104+$AD104)),IF(EZ$1<=$X104,$Y104,IF(EZ$1<=$U104+$O104,$AD104*($AH104+$AG104*(2*INT((EZ$1-$O104))/$U104+$AD104)),0))),0) -> 0
E105: =OFFSET(E105,-1,0)+1 -> 11 | F105: Landscape Architect | G105: =H105*J105 -> 155182.21 | H105: 125 | I105: Total Beds | J105: =INDEX(FACTOR_VALUES,MATCH(I105,FACTOR_NAMES,0),1) -> 1241.4577 | K105: =+$G105/Beds -> 125 | L105: =+$G105/$H$15 -> 0.20477369 | M105: =+$G105/$H$16 -> 0.36197057 | N105: =EOMONTH($M$7,O105-2)+1 -> 46753 | O105: =$N$7 -> 1 | P105: 1 | Q105: =O105-1+P105 -> 1 | R105: Curve-Front | U105: =+P105 -> 1 | V105: =+R105 -> Curve-Front | W105: =INT(U105*AB105)+O105-1 -> 0 | X105: =(U105-INT(U105*(1-AB105)))+O105-1 -> 1 | Y105: =(AB105-(W105-O105+1)/U105)*(AF105+AE105*(2*(W105-O105+1)/U105+(AB105-(W105-O105+1)/U105)))+((X105-O105+1)/U105-AB105)*(AH105+AG105*(2*AB105+((X105-O105+1)/U105-AB105))) -> 1 | Z105: =IF(V105="curve-front",1,IF(V105="curve-end",3,2)) -> 1 | AA105: =IF(OR(V105="curve-front",V105="curve-mid",V105="curve-end"),2.5,1) -> 2.5 | AB105: =Z105/4 -> 0.25 | AC105: =AA105-1 -> 1.5 | AD105: =1/U105 -> 1 | AE105: =AC105/(AB105*(2+AC105)) -> 1.7142857 | AF105: =2/(2+AC105) -> 0.57142857 | AG105: =-AC105/(2+AC105)/(1-AB105) -> -0.57142857 | AH105: =2*(1-AB105+AC105)/(2+AC105)/(1-AB105) -> 1.7142857 | AJ105: =IF(AND(AJ$1>=$O105,AJ$1<=$Q105),$G105*IF(AJ$1<=$W105,$AD105*($AF105+$AE105*(2*INT((AJ$1-$O105))/$U105+$AD105)),IF(AJ$1<=$X105,$Y105,IF(AJ$1<=$U105+$O105,$AD105*($AH105+$AG105*(2*INT((AJ$1-$O105))/$U105+$AD105)),0))),0) -> 0 | AK105: =IF(AND(AK$1>=$O105,AK$1<=$Q105),$G105*IF(AK$1<=$W105,$AD105*($AF105+$AE105*(2*INT((AK$1-$O105))/$U105+$AD105)),IF(AK$1<=$X105,$Y105,IF(AK$1<=$U105+$O105,$AD105*($AH105+$AG105*(2*INT((AK$1-$O105))/$U105+$AD105)),0))),0) -> 155182.21 | AL105: =IF(AND(AL$1>=$O105,AL$1<=$Q105),$G105*IF(AL$1<=$W105,$AD105*($AF105+$AE105*(2*INT((AL$1-$O105))/$U105+$AD105)),IF(AL$1<=$X105,$Y105,IF(AL$1<=$U105+$O105,$AD105*($AH105+$AG105*(2*INT((AL$1-$O105))/$U105+$AD105)),0))),0) -> 0 | AM105: =IF(AND(AM$1>=$O105,AM$1<=$Q105),$G105*IF(AM$1<=$W105,$AD105*($AF105+$AE105*(2*INT((AM$1-$O105))/$U105+$AD105)),IF(AM$1<=$X105,$Y105,IF(AM$1<=$U105+$O105,$AD105*($AH105+$AG105*(2*INT((AM$1-$O105))/$U105+$AD105)),0))),0) -> 0 | AN105: =IF(AND(AN$1>=$O105,AN$1<=$Q105),$G105*IF(AN$1<=$W105,$AD105*($AF105+$AE105*(2*INT((AN$1-$O105))/$U105+$AD105)),IF(AN$1<=$X105,$Y105,IF(AN$1<=$U105+$O105,$AD105*($AH105+$AG105*(2*INT((AN$1-$O105))/$U105+$AD105)),0))),0) -> 0 | AO105: =IF(AND(AO$1>=$O105,AO$1<=$Q105),$G105*IF(AO$1<=$W105,$AD105*($AF105+$AE105*(2*INT((AO$1-$O105))/$U105+$AD105)),IF(AO$1<=$X105,$Y105,IF(AO$1<=$U105+$O105,$AD105*($AH105+$AG105*(2*INT((AO$1-$O105))/$U105+$AD105)),0))),0) -> 0 | AP105: =IF(AND(AP$1>=$O105,AP$1<=$Q105),$G105*IF(AP$1<=$W105,$AD105*($AF105+$AE105*(2*INT((AP$1-$O105))/$U105+$AD105)),IF(AP$1<=$X105,$Y105,IF(AP$1<=$U105+$O105,$AD105*($AH105+$AG105*(2*INT((AP$1-$O105))/$U105+$AD105)),0))),0) -> 0 | AQ105: =IF(AND(AQ$1>=$O105,AQ$1<=$Q105),$G105*IF(AQ$1<=$W105,$AD105*($AF105+$AE105*(2*INT((AQ$1-$O105))/$U105+$AD105)),IF(AQ$1<=$X105,$Y105,IF(AQ$1<=$U105+$O105,$AD105*($AH105+$AG105*(2*INT((AQ$1-$O105))/$U105+$AD105)),0))),0) -> 0 | ... EZ105: =IF(AND(EZ$1>=$O105,EZ$1<=$Q105),$G105*IF(EZ$1<=$W105,$AD105*($AF105+$AE105*(2*INT((EZ$1-$O105))/$U105+$AD105)),IF(EZ$1<=$X105,$Y105,IF(EZ$1<=$U105+$O105,$AD105*($AH105+$AG105*(2*INT((EZ$1-$O105))/$U105+$AD105)),0))),0) -> 0
E106: =OFFSET(E106,-1,0)+1 -> 12 | F106: Elevator Consultant | G106: =H106*J106 -> 10000 | H106: 10000 | I106: Amount | J106: =INDEX(FACTOR_VALUES,MATCH(I106,FACTOR_NAMES,0),1) -> 1 | K106: =+$G106/Beds -> 8.0550469 | L106: =+$G106/$H$15 -> 0.013195693 | M106: =+$G106/$H$16 -> 0.023325519 | N106: =EOMONTH($M$7,O106-2)+1 -> 46753 | O106: =$N$7 -> 1 | P106: 1 | Q106: =O106-1+P106 -> 1 | R106: Curve-Front | U106: =+P106 -> 1 | V106: =+R106 -> Curve-Front | W106: =INT(U106*AB106)+O106-1 -> 0 | X106: =(U106-INT(U106*(1-AB106)))+O106-1 -> 1 | Y106: =(AB106-(W106-O106+1)/U106)*(AF106+AE106*(2*(W106-O106+1)/U106+(AB106-(W106-O106+1)/U106)))+((X106-O106+1)/U106-AB106)*(AH106+AG106*(2*AB106+((X106-O106+1)/U106-AB106))) -> 1 | Z106: =IF(V106="curve-front",1,IF(V106="curve-end",3,2)) -> 1 | AA106: =IF(OR(V106="curve-front",V106="curve-mid",V106="curve-end"),2.5,1) -> 2.5 | AB106: =Z106/4 -> 0.25 | AC106: =AA106-1 -> 1.5 | AD106: =1/U106 -> 1 | AE106: =AC106/(AB106*(2+AC106)) -> 1.7142857 | AF106: =2/(2+AC106) -> 0.57142857 | AG106: =-AC106/(2+AC106)/(1-AB106) -> -0.57142857 | AH106: =2*(1-AB106+AC106)/(2+AC106)/(1-AB106) -> 1.7142857 | AJ106: =IF(AND(AJ$1>=$O106,AJ$1<=$Q106),$G106*IF(AJ$1<=$W106,$AD106*($AF106+$AE106*(2*INT((AJ$1-$O106))/$U106+$AD106)),IF(AJ$1<=$X106,$Y106,IF(AJ$1<=$U106+$O106,$AD106*($AH106+$AG106*(2*INT((AJ$1-$O106))/$U106+$AD106)),0))),0) -> 0 | AK106: =IF(AND(AK$1>=$O106,AK$1<=$Q106),$G106*IF(AK$1<=$W106,$AD106*($AF106+$AE106*(2*INT((AK$1-$O106))/$U106+$AD106)),IF(AK$1<=$X106,$Y106,IF(AK$1<=$U106+$O106,$AD106*($AH106+$AG106*(2*INT((AK$1-$O106))/$U106+$AD106)),0))),0) -> 10000 | AL106: =IF(AND(AL$1>=$O106,AL$1<=$Q106),$G106*IF(AL$1<=$W106,$AD106*($AF106+$AE106*(2*INT((AL$1-$O106))/$U106+$AD106)),IF(AL$1<=$X106,$Y106,IF(AL$1<=$U106+$O106,$AD106*($AH106+$AG106*(2*INT((AL$1-$O106))/$U106+$AD106)),0))),0) -> 0 | AM106: =IF(AND(AM$1>=$O106,AM$1<=$Q106),$G106*IF(AM$1<=$W106,$AD106*($AF106+$AE106*(2*INT((AM$1-$O106))/$U106+$AD106)),IF(AM$1<=$X106,$Y106,IF(AM$1<=$U106+$O106,$AD106*($AH106+$AG106*(2*INT((AM$1-$O106))/$U106+$AD106)),0))),0) -> 0 | AN106: =IF(AND(AN$1>=$O106,AN$1<=$Q106),$G106*IF(AN$1<=$W106,$AD106*($AF106+$AE106*(2*INT((AN$1-$O106))/$U106+$AD106)),IF(AN$1<=$X106,$Y106,IF(AN$1<=$U106+$O106,$AD106*($AH106+$AG106*(2*INT((AN$1-$O106))/$U106+$AD106)),0))),0) -> 0 | AO106: =IF(AND(AO$1>=$O106,AO$1<=$Q106),$G106*IF(AO$1<=$W106,$AD106*($AF106+$AE106*(2*INT((AO$1-$O106))/$U106+$AD106)),IF(AO$1<=$X106,$Y106,IF(AO$1<=$U106+$O106,$AD106*($AH106+$AG106*(2*INT((AO$1-$O106))/$U106+$AD106)),0))),0) -> 0 | AP106: =IF(AND(AP$1>=$O106,AP$1<=$Q106),$G106*IF(AP$1<=$W106,$AD106*($AF106+$AE106*(2*INT((AP$1-$O106))/$U106+$AD106)),IF(AP$1<=$X106,$Y106,IF(AP$1<=$U106+$O106,$AD106*($AH106+$AG106*(2*INT((AP$1-$O106))/$U106+$AD106)),0))),0) -> 0 | AQ106: =IF(AND(AQ$1>=$O106,AQ$1<=$Q106),$G106*IF(AQ$1<=$W106,$AD106*($AF106+$AE106*(2*INT((AQ$1-$O106))/$U106+$AD106)),IF(AQ$1<=$X106,$Y106,IF(AQ$1<=$U106+$O106,$AD106*($AH106+$AG106*(2*INT((AQ$1-$O106))/$U106+$AD106)),0))),0) -> 0 | ... EZ106: =IF(AND(EZ$1>=$O106,EZ$1<=$Q106),$G106*IF(EZ$1<=$W106,$AD106*($AF106+$AE106*(2*INT((EZ$1-$O106))/$U106+$AD106)),IF(EZ$1<=$X106,$Y106,IF(EZ$1<=$U106+$O106,$AD106*($AH106+$AG106*(2*INT((EZ$1-$O106))/$U106+$AD106)),0))),0) -> 0
E107: =OFFSET(E107,-1,0)+1 -> 13 | F107: Consultant Reimbursements | G107: =H107*J107 -> 100000 | H107: 100000 | I107: Amount | J107: =INDEX(FACTOR_VALUES,MATCH(I107,FACTOR_NAMES,0),1) -> 1 | K107: =+$G107/Beds -> 80.550469 | L107: =+$G107/$H$15 -> 0.13195693 | M107: =+$G107/$H$16 -> 0.23325519 | N107: =EOMONTH($M$7,O107-2)+1 -> 46753 | O107: =$N$7 -> 1 | P107: 1 | Q107: =O107-1+P107 -> 1 | R107: Curve-Front | U107: =+P107 -> 1 | V107: =+R107 -> Curve-Front | W107: =INT(U107*AB107)+O107-1 -> 0 | X107: =(U107-INT(U107*(1-AB107)))+O107-1 -> 1 | Y107: =(AB107-(W107-O107+1)/U107)*(AF107+AE107*(2*(W107-O107+1)/U107+(AB107-(W107-O107+1)/U107)))+((X107-O107+1)/U107-AB107)*(AH107+AG107*(2*AB107+((X107-O107+1)/U107-AB107))) -> 1 | Z107: =IF(V107="curve-front",1,IF(V107="curve-end",3,2)) -> 1 | AA107: =IF(OR(V107="curve-front",V107="curve-mid",V107="curve-end"),2.5,1) -> 2.5 | AB107: =Z107/4 -> 0.25 | AC107: =AA107-1 -> 1.5 | AD107: =1/U107 -> 1 | AE107: =AC107/(AB107*(2+AC107)) -> 1.7142857 | AF107: =2/(2+AC107) -> 0.57142857 | AG107: =-AC107/(2+AC107)/(1-AB107) -> -0.57142857 | AH107: =2*(1-AB107+AC107)/(2+AC107)/(1-AB107) -> 1.7142857 | AJ107: =IF(AND(AJ$1>=$O107,AJ$1<=$Q107),$G107*IF(AJ$1<=$W107,$AD107*($AF107+$AE107*(2*INT((AJ$1-$O107))/$U107+$AD107)),IF(AJ$1<=$X107,$Y107,IF(AJ$1<=$U107+$O107,$AD107*($AH107+$AG107*(2*INT((AJ$1-$O107))/$U107+$AD107)),0))),0) -> 0 | AK107: =IF(AND(AK$1>=$O107,AK$1<=$Q107),$G107*IF(AK$1<=$W107,$AD107*($AF107+$AE107*(2*INT((AK$1-$O107))/$U107+$AD107)),IF(AK$1<=$X107,$Y107,IF(AK$1<=$U107+$O107,$AD107*($AH107+$AG107*(2*INT((AK$1-$O107))/$U107+$AD107)),0))),0) -> 100000 | AL107: =IF(AND(AL$1>=$O107,AL$1<=$Q107),$G107*IF(AL$1<=$W107,$AD107*($AF107+$AE107*(2*INT((AL$1-$O107))/$U107+$AD107)),IF(AL$1<=$X107,$Y107,IF(AL$1<=$U107+$O107,$AD107*($AH107+$AG107*(2*INT((AL$1-$O107))/$U107+$AD107)),0))),0) -> 0 | AM107: =IF(AND(AM$1>=$O107,AM$1<=$Q107),$G107*IF(AM$1<=$W107,$AD107*($AF107+$AE107*(2*INT((AM$1-$O107))/$U107+$AD107)),IF(AM$1<=$X107,$Y107,IF(AM$1<=$U107+$O107,$AD107*($AH107+$AG107*(2*INT((AM$1-$O107))/$U107+$AD107)),0))),0) -> 0 | AN107: =IF(AND(AN$1>=$O107,AN$1<=$Q107),$G107*IF(AN$1<=$W107,$AD107*($AF107+$AE107*(2*INT((AN$1-$O107))/$U107+$AD107)),IF(AN$1<=$X107,$Y107,IF(AN$1<=$U107+$O107,$AD107*($AH107+$AG107*(2*INT((AN$1-$O107))/$U107+$AD107)),0))),0) -> 0 | AO107: =IF(AND(AO$1>=$O107,AO$1<=$Q107),$G107*IF(AO$1<=$W107,$AD107*($AF107+$AE107*(2*INT((AO$1-$O107))/$U107+$AD107)),IF(AO$1<=$X107,$Y107,IF(AO$1<=$U107+$O107,$AD107*($AH107+$AG107*(2*INT((AO$1-$O107))/$U107+$AD107)),0))),0) -> 0 | AP107: =IF(AND(AP$1>=$O107,AP$1<=$Q107),$G107*IF(AP$1<=$W107,$AD107*($AF107+$AE107*(2*INT((AP$1-$O107))/$U107+$AD107)),IF(AP$1<=$X107,$Y107,IF(AP$1<=$U107+$O107,$AD107*($AH107+$AG107*(2*INT((AP$1-$O107))/$U107+$AD107)),0))),0) -> 0 | AQ107: =IF(AND(AQ$1>=$O107,AQ$1<=$Q107),$G107*IF(AQ$1<=$W107,$AD107*($AF107+$AE107*(2*INT((AQ$1-$O107))/$U107+$AD107)),IF(AQ$1<=$X107,$Y107,IF(AQ$1<=$U107+$O107,$AD107*($AH107+$AG107*(2*INT((AQ$1-$O107))/$U107+$AD107)),0))),0) -> 0 | ... EZ107: =IF(AND(EZ$1>=$O107,EZ$1<=$Q107),$G107*IF(EZ$1<=$W107,$AD107*($AF107+$AE107*(2*INT((EZ$1-$O107))/$U107+$AD107)),IF(EZ$1<=$X107,$Y107,IF(EZ$1<=$U107+$O107,$AD107*($AH107+$AG107*(2*INT((EZ$1-$O107))/$U107+$AD107)),0))),0) -> 0
